Workbook

Sheet Modification MORA & R&R Jan2024
E1: 45292 | F1: 45261
D2: USD | E2: 4.7295 | F2: 4.59 | I2: Impaired
D3: EUR | E3: 5.1173 | F3: 5.0768
D4: RM | E4: 1 | F4: 1
B5: 2020 | N5: Using initial rate
B6: No. | C6: Borrower code | D6: GL Code | E6: Borrower | F6: Trade/Non trade | G6: Currency | H6: SME/ NON SME | I6: Status based on AFS FY2020 | J6: Islamic/ conventional | K6: SLO acceptance date | L6: Auto Mora/Mora/Non-auto mora (R&R) | M6: Modification impact (Original Currency) | N6: Amortisation in Jan 2024 | O6: Revised Modification impact (Original Currency) | P6: Fx | Q6: Modification impact (RM) | U6: Initial rate
B7: 1 | C7: 500749 | D7: 134003 | E7: Istanbul Sabiha Gocken | F7: Non trade | G7: EUR | H7: Non SME | I7: =VLOOKUP(C7,[1]Sheet1!$B$1:$M$34,12,FALSE) -> R&R | J7: Conventional | K7: 44161 | L7: Non Auto Mora | M7: 17452.936 | N7: -935.86 | O7: =SUM(M7:N7) -> 16517.076 | P7: =SUMIF($D$2:$D$4,G7,$E$2:$E$4) -> 5.1173 | Q7: =O7*P7 -> 84522.832 | U7: 4.94130
B8: 2 | C8: 500931 | D8: 2230005 | E8: Lipidchem 2 | F8: Non trade | G8: RM | H8: SME | I8: Mora | J8: Islamic | K8: 44104 | L8: Auto Mora | M8: -2916.5081 | N8: -4030.72 | O8: =SUM(M8:N8) -> -6947.2281 | P8: =SUMIF($D$2:$D$4,G8,$E$2:$E$4) -> 1 | Q8: =O8*P8 -> -6947.2281 | U8: 1
G9: RM | M9: =SUMIF($G$7:$G$8,G9,$M$7:$M$8) -> -2916.5081 | N9: =SUMIF($G$7:$G$8,G9,$N$7:$N$8) -> -4030.72 | O9: =SUMIF($G$7:$G$8,G9,$O$7:$O$8) -> -6947.2281 | Q9: =SUM(Q7:Q8) -> 77575.604
G10: USD | M10: =SUMIF($G$7:$G$8,G10,$M$7:$M$8) -> 0 | N10: =SUMIF($G$7:$G$8,G10,$N$7:$N$8) -> 0 | O10: =SUMIF($G$7:$G$8,G10,$O$7:$O$8) -> 0
G11: EUR | M11: =SUMIF($G$7:$G$8,G11,$M$7:$M$8) -> 17452.936 | N11: =SUMIF($G$7:$G$8,G11,$N$7:$N$8) -> -935.86 | O11: =SUMIF($G$7:$G$8,G11,$O$7:$O$8) -> 16517.076
B13: 2021
B14: No. | C14: Borrower code | D14: GL Code | E14: Borrower | F14: Trade/Non trade | G14: Currency | H14: SME/NON SME | J14: Islamic/ conventional | K14: SLO acceptance date | L14: Auto Mora/Mora/Non-auto mora (R&R) | M14: Modification impact (Original Currency) | N14: Amortisation in Jan 2024 | O14: Revised Modification impact (Original Currency) | P14: Fx | Q14: Modification impact (RM)
B15: 1 | C15: 500642 | D15: 134003 | E15: OM Materials (Sarawak) Sdn Bhd (Tranche A1) Facility A | F15: Non trade | G15: USD | H15: Non SME | J15: Conventional | K15: 44322 | L15: R&R | M15: 24038.029 | N15: -700.73 | O15: =SUM(M15:N15) -> 23337.299 | P15: =SUMIF($D$2:$D$4,G15,$E$2:$E$4) -> 4.7295 | Q15: =O15*P15 -> 110373.76 | U15: 4.21100
B16: 2 | C16: 500640 | D16: 134003 | E16: OM Materials (Sarawak) Sdn Bhd (Tranche B) Facility C | F16: Non trade | G16: USD | H16: Non SME | J16: Conventional | K16: 44322 | L16: R&R | M16: 37387.239 | N16: -1059.6 | O16: =SUM(M16:N16) -> 36327.639 | P16: =SUMIF($D$2:$D$4,G16,$E$2:$E$4) -> 4.7295 | Q16: =O16*P16 -> 171811.57 | U16: 4.21100
B17: 3 | C17: 501030 | D17: 2230005 | E17: SSP Raw Metals Trading Sdn Bhd | F17: Non trade | G17: RM | H17: SME | J17: Islamic | K17: 44460 | L17: PEMULIH | M17: 574.1313 | N17: -164.25 | O17: =SUM(M17:N17) -> 409.8813 | P17: =SUMIF($D$2:$D$4,G17,$E$2:$E$4) -> 1 | Q17: =O17*P17 -> 409.8813 | U17: 1
Q18: =SUM(Q15:Q17) -> 282595.2
G19: RM | M19: =SUMIF($G$15:$G$17,G19,$M$15:$M$17) -> 574.1313 | N19: =SUMIF($G$15:$G$17,G19,$N$15:$N$17) -> -164.25 | O19: =SUMIF($G$15:$G$17,G19,$O$15:$O$17) -> 409.8813
G20: USD | M20: =SUMIF($G$15:$G$17,G20,$M$15:$M$17) -> 61425.268 | N20: =SUMIF($G$15:$G$17,G20,$N$15:$N$17) -> -1760.33 | O20: =SUMIF($G$15:$G$17,G20,$O$15:$O$17) -> 59664.938
B23: 2022
B24: No. | C24: Borrower code | D24: GL Code | E24: Borrower | F24: Trade/ Non trade | G24: Currency | H24: SME/NON SME | J24: Islamic/ conventional | K24: SLO acceptance date | L24: Auto Mora/Mora/Non-auto mora (R&R) | M24: Modification impact (Original Currency) | N24: Amortisation in Jan 2024 | O24: Revised Modification impact (Original Currency) | P24: Fx | Q24: Modification impact (RM)
B25: 1 | C25: 500860 | D25: 2230005 | E25: Lantana Services Sdn Bhd | F25: Non trade | G25: RM | H25: SME | J25: Islamic | K25: 44704 | L25: R&R | M25: 318.64742 | N25: -150.87 | O25: =SUM(M25:N25) -> 167.77742 | P25: =SUMIF($D$2:$D$4,G25,$E$2:$E$4) -> 1 | Q25: =O25*P25 -> 167.77742 | U25: 1
B26: 2 | C26: 501010 | D26: 2230005 | E26: Malaysian Phosphate Additives (Sarawak) Sdn Bhd | F26: Non trade | G26: USD | H26: Non SME | J26: Islamic | K26: 44831 | L26: R&R | M26: 22266.865 | N26: -2130.29 | O26: =SUM(M26:N26) -> 20136.575 | P26: =SUMIF($D$2:$D$4,G26,$E$2:$E$4) -> 4.7295 | Q26: =O26*P26 -> 95235.931 | U26: 4.728
Q27: =SUBTOTAL(9,Q25:Q26) -> 95403.708
G28: RM | M28: =SUMIF($G$25:$G$26,G28,$M$25:$M$26) -> 318.64742 | N28: =SUMIF($G$25:$G$26,G28,$N$25:$N$26) -> -150.87 | O28: =SUMIF($G$25:$G$26,G28,$O$25:$O$26) -> 167.77742
G29: USD | M29: =SUMIF($G$25:$G$26,G29,$M$25:$M$26) -> 22266.865 | N29: =SUMIF($G$25:$G$26,G29,$N$25:$N$26) -> -2130.29 | O29: =SUMIF($G$25:$G$26,G29,$O$25:$O$26) -> 20136.575
B32: 2023
B33: No. | C33: Borrower code | D33: GL Code | E33: Borrower | F33: Trade/ Non trade | G33: Currency | H33: SME/NON SME | J33: Islamic/ conventional | K33: SLO acceptance date | L33: Auto Mora/Mora/Non-auto mora (R&R) | M33: Modification impact (Original Currency) | N33: Amortisation in Jan 2024 | O33: Revised Modification impact (Original Currency) | P33: Fx | Q33: Modification impact (RM)
B34: 1 | C34: 500941 | D34: 2230005 | E34: PWN Excellence Sdn Bhd 1 | F34: Non trade | G34: RM | H34: SME | J34: Islamic | K34: 45149 | L34: R&R | M34: -553612.81 | N34: 58307.99 | O34: =SUM(M34:N34) -> -495304.82 | P34: =SUMIF($D$2:$D$4,G34,$E$2:$E$4) -> 1 | Q34: =O34*P34 -> -495304.82 | U34: 1
B35: 2 | C35: 500943 | D35: 2230005 | E35: PWN Excellence Sdn Bhd 3 | F35: Non trade | G35: RM | H35: SME | J35: Islamic | K35: 45149 | L35: R&R | M35: -53001.579 | N35: 4369.71 | O35: =SUM(M35:N35) -> -48631.869 | P35: =SUMIF($D$2:$D$4,G35,$E$2:$E$4) -> 1 | Q35: =O35*P35 -> -48631.869 | U35: 1
Q36: =SUBTOTAL(9,Q34:Q35) -> -543936.69
G37: RM | M37: =SUMIF($G$34:$G$35,G37,$M$34:$M$35) -> -606614.39 | N37: =SUMIF($G$34:$G$35,G37,$N$34:$N$35) -> 62677.7 | O37: =SUMIF($G$34:$G$35,G37,$O$34:$O$35) -> -543936.69
G38: USD | M38: =SUMIF($G$34:$G$35,G38,$M$34:$M$35) -> 0 | N38: =SUMIF($G$34:$G$35,G38,$N$34:$N$35) -> 0 | O38: =SUMIF($G$34:$G$35,G38,$O$34:$O$35) -> 0
G40: TOTAL | Q40: =Q9+Q18+Q27+Q36 -> -88362.172
Q42: As per listing | R42: SAP | S42: Variance
O43: 134003 | P43: Conventional | Q43: =SUMIF($J$6:$J$35,P43,$Q$6:$Q$35) -> 366708.15 | S43: =Q43-R43 -> 366708.15
O44: 2230005 | P44: Islamic | Q44: =SUMIF($J$6:$J$35,P44,$Q$6:$Q$35) -> -455070.33 | S44: =Q44-R44 -> -455070.33
P45: Total | Q45: =SUM(Q43:Q44) -> -88362.172 | R45: =SUM(R43:R44) -> 0 | S45: =SUM(S43:S44) -> -88362.172

Sheet Modification MORA & R&R May2024
E1: 45413 | F1: 45383
D2: USD | E2: 4.707 | F2: 4.77 | I2: Impaired
D3: EUR | E3: 5.1 | F3: 5.1096
D4: RM | E4: 1 | F4: 1
B5: 2020 | N5: Using initial rate
B6: No. | C6: Borrower code | D6: GL Code | E6: Borrower | F6: Trade/Non trade | G6: Currency | H6: SME/ NON SME | I6: Status based on AFS FY2020 | J6: Islamic/ conventional | K6: SLO acceptance date | L6: Auto Mora/Mora/Non-auto mora (R&R) | M6: Modification impact (Original Currency) | N6: Amortisation in May 2024 | O6: Revised Modification impact (Original Currency) | P6: Fx | Q6: Modification impact (RM) | U6: Initial rate
B7: 1 | C7: 500749 | D7: 134003 | E7: Istanbul Sabiha Gocken | F7: Non trade | G7: EUR | H7: Non SME | I7: =VLOOKUP(C7,[1]Sheet1!$B$1:$M$34,12,FALSE) -> R&R | J7: Conventional | K7: 44161 | L7: Non Auto Mora | M7: 13709.496 | N7: -935.86 | O7: =SUM(M7:N7) -> 12773.636 | P7: =SUMIF($D$2:$D$4,G7,$E$2:$E$4) -> 5.1 | Q7: =O7*P7 -> 65145.543 | U7: 4.94130
B8: 2 | C8: 500931 | D8: 2230005 | E8: Lipidchem 2 | F8: Non trade | G8: RM | H8: SME | I8: Mora | J8: Islamic | K8: 44104 | L8: Auto Mora | M8: -16921.728 | N8: -3050.1707 | O8: =SUM(M8:N8) -> -19971.899 | P8: =SUMIF($D$2:$D$4,G8,$E$2:$E$4) -> 1 | Q8: =O8*P8 -> -19971.899 | U8: 1
G9: RM | M9: =SUMIF($G$7:$G$8,G9,$M$7:$M$8) -> -16921.728 | N9: =SUMIF($G$7:$G$8,G9,$N$7:$N$8) -> -3050.1707 | O9: =SUMIF($G$7:$G$8,G9,$O$7:$O$8) -> -19971.899 | Q9: =SUM(Q7:Q8) -> 45173.644
G10: USD | M10: =SUMIF($G$7:$G$8,G10,$M$7:$M$8) -> 0 | N10: =SUMIF($G$7:$G$8,G10,$N$7:$N$8) -> 0 | O10: =SUMIF($G$7:$G$8,G10,$O$7:$O$8) -> 0
G11: EUR | M11: =SUMIF($G$7:$G$8,G11,$M$7:$M$8) -> 13709.496 | N11: =SUMIF($G$7:$G$8,G11,$N$7:$N$8) -> -935.86 | O11: =SUMIF($G$7:$G$8,G11,$O$7:$O$8) -> 12773.636
B13: 2021
B14: No. | C14: Borrower code | D14: GL Code | E14: Borrower | F14: Trade/Non trade | G14: Currency | H14: SME/NON SME | J14: Islamic/ conventional | K14: SLO acceptance date | L14: Auto Mora/Mora/Non-auto mora (R&R) | M14: Modification impact (Original Currency) | N14: Amortisation in May 2024 | O14: Revised Modification impact (Original Currency) | P14: Fx | Q14: Modification impact (RM)
B15: 1 | C15: 500642 | D15: 134003 | E15: OM Materials (Sarawak) Sdn Bhd (Tranche A1) Facility A | F15: Non trade | G15: USD | H15: Non SME | J15: Conventional | K15: 44322 | L15: R&R | M15: 21268.409 | N15: -667.43 | O15: =SUM(M15:N15) -> 20600.979 | P15: =SUMIF($D$2:$D$4,G15,$E$2:$E$4) -> 4.707 | Q15: =O15*P15 -> 96968.808 | U15: 4.21100
B16: 2 | C16: 500640 | D16: 134003 | E16: OM Materials (Sarawak) Sdn Bhd (Tranche B) Facility C | F16: Non trade | G16: USD | H16: Non SME | J16: Conventional | K16: 44322 | L16: R&R | M16: 33196.259 | N16: -1012.18 | O16: =SUM(M16:N16) -> 32184.079 | P16: =SUMIF($D$2:$D$4,G16,$E$2:$E$4) -> 4.707 | Q16: =O16*P16 -> 151490.46 | U16: 4.21100
Q17: =SUM(Q15:Q16) -> 248459.27
G18: RM | M18: =SUMIF($G$15:$G$16,G18,$M$15:$M$16) -> 0 | N18: =SUMIF($G$15:$G$16,G18,$N$15:$N$16) -> 0 | O18: =SUMIF($G$15:$G$16,G18,$O$15:$O$16) -> 0
G19: USD | M19: =SUMIF($G$15:$G$16,G19,$M$15:$M$16) -> 54464.668 | N19: =SUMIF($G$15:$G$16,G19,$N$15:$N$16) -> -1679.61 | O19: =SUMIF($G$15:$G$16,G19,$O$15:$O$16) -> 52785.058
B22: 2022
B23: No. | C23: Borrower code | D23: GL Code | E23: Borrower | F23: Trade/ Non trade | G23: Currency | H23: SME/NON SME | J23: Islamic/ conventional | K23: SLO acceptance date | L23: Auto Mora/Mora/Non-auto mora (R&R) | M23: Modification impact (Original Currency) | N23: Amortisation in May 2024 | O23: Revised Modification impact (Original Currency) | P23: Fx | Q23: Modification impact (RM)
B24: 1 | C24: 501010 | D24: 2230005 | E24: Malaysian Phosphate Additives (Sarawak) Sdn Bhd | F24: Non trade | G24: USD | H24: Non SME | J24: Islamic | K24: 44831 | L24: R&R | M24: 18295.555 | N24: 97.88 | O24: =SUM(M24:N24) -> 18393.435 | P24: =SUMIF($D$2:$D$4,G24,$E$2:$E$4) -> 4.707 | Q24: =O24*P24 -> 86577.898 | U24: 4.728
Q25: =SUBTOTAL(9,Q24:Q24) -> 86577.898
G26: RM | M26: =SUMIF($G$24:$G$24,G26,$M$24:$M$24) -> 0 | N26: =SUMIF($G$24:$G$24,G26,$N$24:$N$24) -> 0 | O26: =SUMIF($G$24:$G$24,G26,$O$24:$O$24) -> 0
G27: USD | M27: =SUMIF($G$24:$G$24,G27,$M$24:$M$24) -> 18295.555 | N27: =SUMIF($G$24:$G$24,G27,$N$24:$N$24) -> 97.88 | O27: =SUMIF($G$24:$G$24,G27,$O$24:$O$24) -> 18393.435
B30: 2023
B31: No. | C31: Borrower code | D31: GL Code | E31: Borrower | F31: Trade/ Non trade | G31: Currency | H31: SME/NON SME | J31: Islamic/ conventional | K31: SLO acceptance date | L31: Auto Mora/Mora/Non-auto mora (R&R) | M31: Modification impact (Original Currency) | N31: Amortisation in May 2024 | O31: Revised Modification impact (Original Currency) | P31: Fx | Q31: Modification impact (RM)
B32: 1 | C32: 500941 | D32: 2230005 | E32: PWN Excellence Sdn Bhd 1 | F32: Non trade | G32: RM | H32: SME | J32: Islamic | K32: 45149 | L32: R&R | M32: -310645.62 | N32: 63939.96 | O32: =SUM(M32:N32) -> -246705.66 | P32: =SUMIF($D$2:$D$4,G32,$E$2:$E$4) -> 1 | Q32: =O32*P32 -> -246705.66 | U32: 1
B33: 2 | C33: 500943 | D33: 2230005 | E33: PWN Excellence Sdn Bhd 3 | F33: Non trade | G33: RM | H33: SME | J33: Islamic | K33: 45149 | L33: R&R | M33: -29547.009 | N33: 7407.43 | O33: =SUM(M33:N33) -> -22139.579 | P33: =SUMIF($D$2:$D$4,G33,$E$2:$E$4) -> 1 | Q33: =O33*P33 -> -22139.579 | U33: 1
Q34: =SUBTOTAL(9,Q32:Q33) -> -268845.24
G35: RM | M35: =SUMIF($G$32:$G$33,G35,$M$32:$M$33) -> -340192.63 | N35: =SUMIF($G$32:$G$33,G35,$N$32:$N$33) -> 71347.39 | O35: =SUMIF($G$32:$G$33,G35,$O$32:$O$33) -> -268845.24
G36: USD | M36: =SUMIF($G$32:$G$33,G36,$M$32:$M$33) -> 0 | N36: =SUMIF($G$32:$G$33,G36,$N$32:$N$33) -> 0 | O36: =SUMIF($G$32:$G$33,G36,$O$32:$O$33) -> 0
G38: TOTAL | Q38: =Q9+Q17+Q25+Q34 -> 111365.57
Q40: As per listing | R40: SAP | S40: Variance
O41: 134003 | P41: Conventional | Q41: =SUMIF($J$6:$J$33,P41,$Q$6:$Q$33) -> 313604.81 | S41: =Q41-R41 -> 313604.81
O42: 2230005 | P42: Islamic | Q42: =SUMIF($J$6:$J$33,P42,$Q$6:$Q$33) -> -202239.24 | S42: =Q42-R42 -> -202239.24
P43: Total | Q43: =SUM(Q41:Q42) -> 111365.57 | R43: =SUM(R41:R42) -> 0 | S43: =SUM(S41:S42) -> 111365.57

Sheet Debtors Listing Islamic (Cost)
A1: Cost Outstanding (MYR) for Islamic Financing as at 31st July 2026 | U1: USD | V1: 4.081 | W1: EUR | X1: 4.7017 | Y1: SGD | Z1: 3.1854
U2: GBP | V2: 5.4924 | W2: AUD | X2: 2.8734
A6: No. | B6: Company | C6: Customer Account | D6: Currency | E6: Remarks | G6: Opening | H6: Disbursement | I6: Adjustment/ Capitalisation | J6: Forex (+) | K6: Unearned | L6: Rental (Ijarah) | M6: Cost Payment | N6: Profit | O6: Adjustment/ Capitalisation | P6: Forex (-) | Q6: Unearned | R6: Balance | T6: Base Currency COD & ARRD | V6: COD & ARRD in Local Currency
K7: Profit | N7: Payment | Q7: Profit
B8: Islamic Financing Facility
B10: Supplier Credit Islamic Financing Facility & Letter of Credit/Trust Receipt
B11: Allied PT Resources Sdn Bhd | C11: 500685 | D11: MYR | G11: 3.6789061e-10 | R11: =G11+H11+J11+K11+I11-M11-O11-P11-Q11-N11 -> 3.6789061e-10
B12: Arab Malaysian Vegetable Oil Products Co Ltd | C12: 500548 | D12: USD | G12: 8.4401108e-09 | R12: =G12+H12+J12+K12+I12-M12-O12-P12-Q12-N12 -> 8.4401108e-09
B13: Arab Malaysian Vegetable Oil Products Co Ltd - Trade | C13: 500556 | D13: USD | G13: 5.1455572e-08 | R13: =G13+H13+J13+K13+I13-M13-O13-P13-Q13-N13 -> 5.1455572e-08
B14: Awin Resources (Malaysia) Ltd | C14: 500858 | D14: USD | G14: -1.3643876e-07 | R14: =G14+H14+J14+K14+I14-M14-O14-P14-Q14-N14 -> -1.3643876e-07
B15: Destini Prima Sdn Bhd | C15: 500731 | D15: USD | G15: -0.0029999966 | R15: =G15+H15+J15+K15+I15-M15-O15-P15-Q15-N15 -> -0.0029999966
B16: Central Sugar Refinery | C16: 500815 | D16: MYR | G16: 1.2805685e-08 | R16: =G16+H16+J16+K16+I16-M16-O16-P16-Q16-N16 -> 1.2805685e-08
B17: Continental Resources Sdn Bhd | C17: 500813 | D17: USD | G17: -3.4749974e-08 | R17: =G17+H17+J17+K17+I17-M17-O17-P17-Q17-N17 -> -3.4749974e-08
B18: EON Metal Technology Sdn Bhd | C18: 500830 | D18: USD | G18: 4.3655746e-10 | R18: =G18+H18+J18+K18+I18-M18-O18-P18-Q18-N18 -> 4.3655746e-10
B19: Destini Shipbuilding & Engineering | C19: 500908 | D19: EUR | G19: 3.9581209e-09 | R19: =G19+H19+J19+K19+I19-M19-O19-P19-Q19-N19 -> 3.9581209e-09
A20: 1 | B20: Envico Enterprise Sdn Bhd | C20: 500968 | D20: USD | E20: Monthly Financial Cost Sep20 - Dec20 | G20: -0.0013749599 | R20: =F20+G20+H20+J20+K20+I20-M20-O20-P20-Q20-N20 -> -0.0013749599 | S20: =R20-V20 -> -0.0013749599 | V20: =T20*$V$1 -> 0 | AC20: =G20+H20+I20+J20-M20-O20-P20 -> -0.0013749599
A21: 1 | B21: Aescomed Healthcare Sdn Bhd | C21: 501125 | D21: MYR | G21: -1.7462298e-10 | R21: =G21+H21+J21+K21+I21-M21-O21-P21-Q21-N21 -> -1.7462298e-10 | S21: =R21-V21 -> -1.7462298e-10 | U21: =D21 -> MYR | V21: =T21 -> 0
A22: 1 | B22: ACE Champion Sdn Bhd | C22: 501285 | D22: MYR | G22: 4579063.4 | H22: 1237439.1 | M22: 965682.83 | R22: =G22+H22+J22+K22+I22-M22-O22-P22-Q22-N22 -> 4850819.7 | S22: =R22-V22 -> 0 | T22: 4850819.7 | U22: =D22 -> MYR | V22: =T22 -> 4850819.7
A23: 2 | B23: Agro 19 Berhad | C23: 501111 | D23: MYR | G23: 9976471.3 | M23: 4092610.8 | R23: =G23+H23+J23+K23+I23-M23-O23-P23-Q23-N23 -> 5883860.4 | S23: =R23-V23 -> 0 | T23: 5883860.5 | U23: =D23 -> MYR | V23: =T23 -> 5883860.5 | AB23: =H23+I23-M23-O23 -> -4092610.8
A24: 3 | B24: Agro 19 Berhad 2 | C24: 501172 | D24: MYR | G24: 29997745 | H24: 17561516 | M24: 19344759 | R24: =G24+H24+J24+K24+I24-M24-O24-P24-Q24-N24 -> 28214502 | S24: =R24-V24 -> 0 | T24: 28214502 | U24: =D24 -> MYR | V24: =T24 -> 28214502
A25: 4 | B25: Agro 19 Berhad 3 | C25: 501291 | D25: MYR | G25: 39822432 | M25: 817900.6 | R25: =G25+H25+J25+K25+I25-M25-O25-P25-Q25-N25 -> 39004531 | S25: =R25-V25 -> 0 | T25: 39004531 | U25: =D25 -> MYR | V25: =T25 -> 39004531
A26: 5 | B26: Agro 19 Berhad 4 | C26: 501350 | D26: MYR | G26: 5000000 | R26: =G26+H26+J26+K26+I26-M26-O26-P26-Q26-N26 -> 5000000 | S26: =R26-V26 -> 0 | T26: 5000000 | U26: =D26 -> MYR | V26: =T26 -> 5000000
A27: 6 | B27: Agro 19 Berhad - RCi | C27: 501356 | D27: MYR | H27: 1357851.1 | R27: =G27+H27+J27+K27+I27-M27-O27-P27-Q27-N27 -> 1357851.1 | S27: =R27-V27 -> 0 | T27: 1357851.1 | U27: =D27 -> MYR | V27: =T27 -> 1357851.1
A28: 7 | B28: AMC Cincaria Sdn Bhd | C28: 501129 | D28: MYR | G28: 3666201.7 | H28: 2026179.2 | M28: 1530367.5 | R28: =G28+H28+J28+K28+I28-M28-O28-P28-Q28-N28 -> 4162013.4 | S28: =R28-V28 -> 0 | T28: 4162013.4 | U28: =D28 -> MYR | V28: =T28 -> 4162013.4
A29: 6 | B29: Ann Joo Integrated Steel Sdn Bhd | C29: 501161 | D29: MYR | G29: 8.7311491e-09 | R29: =G29+H29+J29+K29+I29-M29-O29-P29-Q29-N29 -> 8.7311491e-09 | S29: =R29-V29 -> 8.7311491e-09 | U29: =D29 -> MYR | V29: =T29 -> 0
A30: 7 | B30: Ann Joo Integrated Steel Sdn Bhd - TRi | C30: 501265 | D30: MYR | G30: 0 | R30: =G30+H30+J30+K30+I30-M30-O30-P30-Q30-N30 -> 0 | S30: =R30-V30 -> 0 | U30: =D30 -> MYR | V30: =T30 -> 0
A31: 8 | B31: Bahru Stainless Sdn Bhd 1 | C31: 501351 | D31: USD | H31: 30652750 | P31: 45250 | R31: =G31+H31+J31+K31+I31-M31-O31-P31-Q31-N31 -> 30607500 | S31: =R31-V31 -> 0 | T31: 7500000 | U31: =D31 -> USD | V31: =T31*$V$1 -> 30607500
A32: 9 | B32: Bahru Stainless Sdn Bhd 2 | C32: 501352 | D32: USD | H32: 71567250 | P32: 149750 | R32: =G32+H32+J32+K32+I32-M32-O32-P32-Q32-N32 -> 71417500 | S32: =R32-V32 -> 0 | T32: 17500000 | U32: =D32 -> USD | V32: =T32*$V$1 -> 71417500
A33: 10 | B33: Bateriku (M) Sdn Bhd | C33: 501306 | D33: MYR | G33: 4233375.2 | H33: 4278767.7 | R33: =G33+H33+J33+K33+I33-M33-O33-P33-Q33-N33 -> 8512143 | S33: =R33-V33 -> 0 | T33: 8512143 | U33: =D33 -> MYR | V33: =T33 -> 8512143
A34: 8 | B34: Bertambest Sdn Bhd | C34: 501137 | D34: MYR | G34: -4.6566129e-10 | R34: =G34+H34+J34+K34+I34-M34-O34-P34-Q34-N34 -> -4.6566129e-10 | S34: =R34-V34 -> -4.6566129e-10 | U34: =D34 -> MYR | V34: =T34 -> 0
A35: 11 | B35: Bhavani Foods (M) Sdn Bhd | C35: 501131 | D35: MYR | G35: 1887036.9 | H35: 473970.5 | M35: 519003.55 | R35: =G35+H35+J35+K35+I35-M35-O35-P35-Q35-N35 -> 1842003.8 | S35: =R35-V35 -> 0 | T35: 1842003.8 | U35: =D35 -> MYR | V35: =T35 -> 1842003.8
A36: 12 | B36: Bio Eneco Sdn Bhd | C36: 501035 | D36: MYR | G36: 2442000 | R36: =G36+H36+J36+K36+I36-M36-O36-P36-Q36-N36 -> 2442000 | S36: =R36-V36 -> 0 | T36: 2442000 | U36: =D36 -> MYR | V36: =T36 -> 2442000 | AB36: =H36+I36-M36-O36 -> 0 | AC36: =G36+H36+I36+J36-M36-O36-P36 -> 2442000
A37: 10 | B37: Bousted Petroleum Marketing | C37: 501086 | D37: USD | G37: 0 | R37: =G37+H37+J37+K37+I37-M37-O37-P37-Q37-N37 -> 0 | S37: =R37-V37 -> 0 | U37: =D37 -> USD | V37: =T37*$V$1 -> 0 | AB37: =H37+I37-M37-O37 -> 0 | AC37: =G37+H37+I37+J37-M37-O37-P37 -> 0
A38: 8 | B38: Bousted Petroleum Marketing | C38: 501156 | D38: USD | G38: 6.9849193e-10 | R38: =G38+H38+J38+K38+I38-M38-O38-P38-Q38-N38 -> 6.9849193e-10 | S38: =R38-V38 -> 6.9849193e-10 | U38: =D38 -> USD | V38: =T38*$V$1 -> 0
A39: 13 | B39: Choon Eng (Sarawak) Sdn Bhd | C39: 501142 | D39: MYR | G39: 6979414.4 | M39: 963000 | R39: =G39+H39+J39+K39+I39-M39-O39-P39-Q39-N39 -> 6016414.4 | S39: =R39-V39 -> 0 | T39: 6016414.4 | U39: =D39 -> MYR | V39: =T39 -> 6016414.4
A40: 14 | B40: Coco Oro Jewellery Sdn Bhd - SFi | C40: 501293 | D40: MYR | G40: 7987464 | H40: 1148016.8 | M40: 1138300 | R40: =G40+H40+J40+K40+I40-M40-O40-P40-Q40-N40 -> 7997180.8 | S40: =R40-V40 -> 0 | T40: 7997180.8 | U40: =D40 -> MYR | V40: =T40 -> 7997180.8
A41: 15 | B41: Coco Oro Jewellery Sdn Bhd - RCi | C41: 501318 | D41: MYR | G41: 1998000 | R41: =G41+H41+J41+K41+I41-M41-O41-P41-Q41-N41 -> 1998000 | S41: =R41-V41 -> 0 | T41: 1998000 | V41: =T41 -> 1998000
A42: 16 | B42: Enapak Packaging Sdn Bhd | C42: 501344 | D42: MYR | G42: 3001587.5 | H42: 2977456.5 | R42: =G42+H42+J42+K42+I42-M42-O42-P42-Q42-N42 -> 5979044 | S42: =R42-V42 -> 0 | T42: 5979044 | U42: MYR | V42: =T42 -> 5979044
A43: 17 | B43: Enviros Survey & Consultancy Sdn Bhd - RCi | C43: 501235 | D43: USD | G43: 4077500 | H43: 2467270.6 | J43: 2096.06 | M43: 2465761.6 | P43: 105.05 | R43: =G43+H43+J43+K43+I43-M43-O43-P43-Q43-N43 -> 4081000 | S43: =R43-V43 -> 0.010000001 | T43: 1000000 | U43: USD | V43: =T43*$V$1 -> 4081000
A44: 18 | B44: Enviros Survey & Consultancy Sdn Bhd - SFi | C44: 501323 | D44: USD | G44: 620207.81 | M44: 620207.81 | R44: =G44+H44+J44+K44+I44-M44-O44-P44-Q44-N44 -> 0 | S44: =R44-V44 -> 0 | T44: 0 | U44: MYR | V44: =T44 -> 0
A45: 19 | B45: Evergreen Fibreboard Berhad | C45: 501290 | D45: MYR | G45: 9000000 | H45: 2000000 | M45: 1000000 | R45: =G45+H45+J45+K45+I45-M45-O45-P45-Q45-N45 -> 10000000 | S45: =R45-V45 -> 0 | T45: 10000000 | U45: =D45 -> MYR | V45: =T45 -> 10000000
A46: 20 | B46: Evergreen Fibreboard Berhad - SFi | C46: 501347 | D46: MYR | G46: 2433061.6 | H46: 1530878.1 | M46: 1076768.8 | R46: =G46+H46+J46+K46+I46-M46-O46-P46-Q46-N46 -> 2887170.9 | S46: =R46-V46 -> 0 | T46: 2887170.9 | U46: MYR | V46: =T46 -> 2887170.9
A47: 21 | B47: Fabulous Sunview Sdn Bhd | C47: 501232 | D47: USD | G47: 20164420 | J47: 17524.02 | P47: 215.49 | R47: =G47+H47+J47+K47+I47-M47-O47-P47-Q47-N47 -> 20181728 | S47: =R47-V47 -> 0.01162 | T47: 4945290 | U47: =D47 -> USD | V47: =T47*$V$1 -> 20181728
A48: 22 | B48: Fathopes Energy Sdn Bhd (1) | C48: 501181 | D48: MYR | G48: 7417628.1 | H48: 5147310.5 | M48: 5177733.3 | R48: =G48+H48+J48+K48+I48-M48-O48-P48-Q48-N48 -> 7387205.3 | S48: =R48-V48 -> 0 | T48: 7387205.3 | U48: =D48 -> MYR | V48: =T48 -> 7387205.3
A49: 18 | B49: Fathopes Energy Sdn Bhd (2) | C49: 501208 | D49: MYR | G49: 4.6566129e-10 | R49: =G49+H49+J49+K49+I49-M49-O49-P49-Q49-N49 -> 4.6566129e-10 | S49: =R49-V49 -> 4.6566129e-10 | U49: =D49 -> MYR | V49: =T49 -> 0
A50: 15 | B50: Fathopes Energy Sdn Bhd (3) | C50: 501242 | D50: MYR | G50: 0 | R50: =G50+H50+J50+K50+I50-M50-O50-P50-Q50-N50 -> 0 | S50: =R50-V50 -> 0 | U50: =D50 -> MYR | V50: =T50 -> 0
A51: 23 | B51: Felda Global Ventures Capital | C51: 500784 | D51: MYR | G51: 82000000 | H51: 55000000 | M51: 82000000 | R51: =G51+H51+J51+K51+I51-M51-O51-P51-Q51-N51 -> 55000000 | S51: =R51-V51 -> 0 | T51: 55000000 | U51: =D51 -> MYR | V51: =T51 -> 55000000 | AB51: =H51+I51-M51-O51 -> -27000000 | AC51: =G51+H51+I51+J51-M51-O51-P51 -> 55000000
B52: Felda Global Ventures Plantations | C52: 500671 | D52: MYR | G52: 0 | R52: =G52+H52+J52+K52+I52-M52-O52-P52-Q52-N52 -> 0 | S52: =R52-V52 -> 0 | U52: =D52 -> MYR | AB52: =H52+I52-M52-O52 -> 0 | AC52: =G52+H52+I52+J52-M52-O52-P52 -> 0
B53: Felda Palm Industries Sdn Bhd | C53: 500551 | D53: MYR | G53: 0 | R53: =G53+H53+J53+K53+I53-M53-O53-P53-Q53-N53 -> 0 | S53: =R53-V53 -> 0 | U53: =D53 -> MYR | AB53: =H53+I53-M53-O53 -> 0 | AC53: =G53+H53+I53+J53-M53-O53-P53 -> 0
B54: Felda Rubber Industries Sdn Bhd | C54: 500531 | D54: MYR | G54: 0 | R54: =G54+H54+J54+K54+I54-M54-O54-P54-Q54-N54 -> 0 | S54: =R54-V54 -> 0 | U54: =D54 -> MYR | AB54: =H54+I54-M54-O54 -> 0 | AC54: =G54+H54+I54+J54-M54-O54-P54 -> 0
B55: FPM Sendirian Berhad | C55: 500628 | D55: USD | G55: 0 | R55: =G55+H55+J55+K55+I55-M55-O55-P55-Q55-N55 -> 0 | S55: =R55-V55 -> 0 | U55: =D55 -> USD | AB55: =H55+I55-M55-O55 -> 0 | AC55: =G55+H55+I55+J55-M55-O55-P55 -> 0
B56: KA Petra Sdn Bhd | C56: 500739 | D56: MYR | G56: 0 | R56: =G56+H56+J56+K56+I56-M56-O56-P56-Q56-N56 -> 0 | S56: =R56-V56 -> 0 | U56: =D56 -> MYR | AB56: =H56+I56-M56-O56 -> 0 | AC56: =G56+H56+I56+J56-M56-O56-P56 -> 0
B57: Malaysia Cocoa Manufacturing | C57: 500588 | D57: GBP | G57: 0 | R57: =G57+H57+J57+K57+I57-M57-O57-P57-Q57-N57 -> 0 | S57: =R57-V57 -> 0 | U57: =D57 -> GBP | AB57: =H57+I57-M57-O57 -> 0 | AC57: =G57+H57+I57+J57-M57-O57-P57 -> 0
A58: 3 | B58: Foresight Industries Sdn Bhd | C58: 500851 | D58: MYR | G58: 0 | R58: =G58+H58+J58+K58+I58-M58-O58-P58-Q58-N58 -> 0 | S58: =R58-V58 -> 0 | U58: =D58 -> MYR | V58: =T58 -> 0 | AB58: =H58+I58-M58-O58 -> 0 | AC58: =G58+H58+I58+J58-M58-O58-P58 -> 0
B59: Fleet Palms Sdn Bhd | C59: 500889 | D59: MYR | G59: 0 | R59: =G59+H59+J59+K59+I59-M59-O59-P59-Q59-N59 -> 0 | S59: =R59-V59 -> 0 | U59: =D59 -> MYR | AB59: =H59+I59-M59-O59 -> 0 | AC59: =G59+H59+I59+J59-M59-O59-P59 -> 0
B60: Golden Scoop Sdn Bhd | C60: 500967 | D60: SGD | G60: 0 | R60: =G60+H60+J60+K60+I60-M60-O60-P60-Q60-N60 -> 0 | S60: =R60-V60 -> 0 | U60: =D60 -> SGD | AB60: =H60+I60-M60-O60 -> 0 | AC60: =G60+H60+I60+J60-M60-O60-P60 -> 0
B61: Khee San Food Industries Sdn Bhd | C61: 500950 | D61: USD | G61: 0 | R61: =G61+H61+J61+K61+I61-M61-O61-P61-Q61-N61 -> 0 | S61: =R61-V61 -> 0 | U61: =D61 -> USD | AB61: =H61+I61-M61-O61 -> 0 | AC61: =G61+H61+I61+J61-M61-O61-P61 -> 0
B62: Mewah Datu Sdn Bhd | C62: 500727 | D62: MYR | G62: 0 | R62: =G62+H62+J62+K62+I62-M62-O62-P62-Q62-N62 -> 0 | S62: =R62-V62 -> 0 | U62: =D62 -> MYR | AB62: =H62+I62-M62-O62 -> 0 | AC62: =G62+H62+I62+J62-M62-O62-P62 -> 0
A63: 24 | B63: FR Development Asia Sdn Bhd - RCi | C63: 501310 | D63: MYR | G63: 1000000 | R63: =G63+H63+J63+K63+I63-M63-O63-P63-Q63-N63 -> 1000000 | S63: =R63-V63 -> 0 | T63: 1000000 | U63: =D63 -> MYR | V63: =T63 -> 1000000 | AC63: =G63+H63+I63+J63-M63-O63-P63 -> 1000000
A64: 25 | B64: FR Development Asia Sdn Bhd - SFi | C64: 501261 | D64: MYR | G64: 3941526.9 | H64: 659242.16 | M64: 629866.1 | R64: =G64+H64+J64+K64+I64-M64-O64-P64-Q64-N64 -> 3970902.9 | S64: =R64-V64 -> -0.00058000069 | T64: 3970902.9 | U64: =D64 -> MYR | V64: =T64 -> 3970902.9 | AC64: =G64+H64+I64+J64-M64-O64-P64 -> 3970902.9
A65: 26 | B65: Gemilang Coachwork Sdn Bhd | C65: 501147 | D65: MYR | G65: 4974124.2 | H65: 344523.3 | M65: 501404 | R65: =G65+H65+J65+K65+I65-M65-O65-P65-Q65-N65 -> 4817243.5 | S65: =R65-V65 -> 0 | T65: 4817243.5 | U65: =D65 -> MYR | V65: =T65 -> 4817243.5
A66: 27 | B66: Gemilang Coachwork Sdn Bhd - RCi | C66: 501281 | D66: MYR | G66: 5000000 | R66: =G66+H66+J66+K66+I66-M66-O66-P66-Q66-N66 -> 5000000 | S66: =R66-V66 -> 0 | T66: 5000000 | U66: =D66 -> MYR | V66: =T66 -> 5000000
A67: 28 | B67: Gemilang Coachwork Sdn Bhd - SFi 2 | C67: 501331 | D67: MYR | G67: 9968289 | R67: =G67+H67+J67+K67+I67-M67-O67-P67-Q67-N67 -> 9968289 | S67: =R67-V67 -> 0 | T67: 9968289 | U67: =D67 -> MYR | V67: =T67 -> 9968289
A68: 29 | B68: Gemilang Coachwork Sdn Bhd - SFi 3 | C68: 501348 | D68: USD | G68: 11993129 | H68: 298810.46 | J68: 10559.12 | M68: 69434.65 | P68: 72.68 | R68: =G68+H68+J68+K68+I68-M68-O68-P68-Q68-N68 -> 12232991 | S68: =R68-V68 -> 0.0041235238 | T68: 2997547.4 | U68: USD | V68: =T68*$V$1 -> 12232991
A69: 30 | B69: Glide Technology Sdn Bhd | C69: 501149 | D69: MYR | G69: 2009545.7 | M69: 179846.86 | R69: =G69+H69+J69+K69+I69-M69-O69-P69-Q69-N69 -> 1829698.9 | S69: =R69-V69 -> 0 | T69: 1829698.9 | U69: =D69 -> MYR | V69: =T69 -> 1829698.9
A70: 31 | B70: Hernan Corporation Sdn Bhd | C70: 501128 | D70: USD | G70: 5074542.8 | H70: 6292092.5 | M70: 808930.62 | O70: 802 | P70: 24794.3 | R70: =G70+H70+J70+K70+I70-M70-O70-P70-Q70-N70 -> 10532108 | S70: =R70-V70 -> -0.0029800031 | T70: 2580766.6 | U70: =D70 -> USD | V70: =T70*$V$1 -> 10532108
A71: 32 | B71: Hernan Corporation Sdn Bhd - RCi | C71: 501317 | D71: USD | G71: 1750182.7 | J71: 1521.92 | P71: 19.62 | R71: =G71+H71+J71+K71+I71-M71-O71-P71-Q71-N71 -> 1751685 | S71: =R71-V71 -> 0.0018399996 | T71: 429229.36 | U71: =D71 -> USD | V71: =T71*$V$1 -> 1751685
A72: 33 | B72: Hy-Fresh Industries Sdn Bhd | C72: 501194 | D72: MYR | G72: 6621062.3 | H72: 2242091.9 | M72: 3097318.4 | R72: =G72+H72+J72+K72+I72-M72-O72-P72-Q72-N72 -> 5765835.8 | S72: =R72-V72 -> 7.4505806e-09 | T72: 5765835.8 | U72: =D72 -> MYR | V72: =T72 -> 5765835.8
A73: 34 | B73: Impact Metal Resources Sdn Bhd | C73: 501140 | D73: MYR | G73: 2972218.3 | R73: =G73+H73+J73+K73+I73-M73-O73-P73-Q73-N73 -> 2972218.3 | S73: =R73-V73 -> 0 | T73: 2972218.3 | U73: =D73 -> MYR | V73: =T73 -> 2972218.3
A74: 35 | B74: Impact Metal Resources Sdn Bhd (2) | C74: 501195 | D74: MYR | G74: 6999999.9 | H74: 6385305.1 | M74: 6762174.9 | R74: =G74+H74+J74+K74+I74-M74-O74-P74-Q74-N74 -> 6623130.1 | S74: =R74-V74 -> 0 | T74: 6623130.1 | U74: =D74 -> MYR | V74: =T74 -> 6623130.1
A75: 36 | B75: Ingress Industrial (M) Sdn Bhd (Trade) | C75: 501133 | D75: USD | G75: 13686068 | H75: 6536917.1 | J75: 16604.33 | M75: 4073552.1 | P75: =228.87+0.06 -> 228.93 | R75: =G75+H75+J75+K75+I75-M75-O75-P75-Q75-N75 -> 16165808 | S75: =R75-V75 -> 0.00057000294 | T75: 3961237 | U75: =D75 -> USD | V75: =T75*$V$1 -> 16165808
A76: 7 | B76: Maxim Textile Technology Sdn Bhd | C76: 501095 | D76: USD | G76: 5.6024874e-10 | R76: =G76+H76+J76+K76+I76-M76-O76-P76-Q76-N76 -> 5.6024874e-10 | S76: =R76-V76 -> 5.6024874e-10 | U76: =D76 -> USD | V76: =T76*$V$1 -> 0 | AB76: =H76+I76-M76-O76 -> 0
A77: 32 | B77: Iradar Sdn Bhd | C77: 501245 | D77: MYR | G77: 0 | R77: =G77+H77+J77+K77+I77-M77-O77-P77-Q77-N77 -> 0 | S77: =R77-V77 -> 0 | U77: =D77 -> MYR | V77: =T77 -> 0
A78: 25 | B78: JFC Foods Industries Sdn Bhd | C78: 501213 | D78: MYR | G78: 0 | R78: =G78+H78+J78+K78+I78-M78-O78-P78-Q78-N78 -> 0 | S78: =R78-V78 -> 0 | U78: =D78 -> MYR | V78: =T78 -> 0
A79: 30 | B79: Kennwu Manufacturing (M) Sdn Bhd | C79: 501270 | D79: MYR | G79: 4.6566129e-10 | R79: =G79+H79+J79+K79+I79-M79-O79-P79-Q79-N79 -> 4.6566129e-10 | S79: =R79-V79 -> 4.6566129e-10 | U79: =D79 -> MYR | V79: =T79 -> 0
A80: 33 | B80: Klitz Vibrant Imported Kitchens Sdn Bhd | C80: 501145 | D80: MYR | G80: -4.6566129e-10 | R80: =G80+H80+J80+K80+I80-M80-O80-P80-Q80-N80 -> -4.6566129e-10 | S80: =R80-V80 -> -4.6566129e-10 | U80: =D80 -> MYR | V80: =T80 -> 0
A81: 37 | B81: Kooka Paper Manufacturing Sdn Bhd | C81: 501325 | D81: USD | G81: 18650355 | H81: 5526346.9 | J81: 24711.41 | M81: 7638325.6 | P81: 77.65 | R81: =G81+H81+J81+K81+I81-M81-O81-P81-Q81-N81 -> 16563010 | S81: =R81-V81 -> 0.0045900065 | T81: 4058566.6 | U81: =D81 -> USD | V81: =T81*$V$1 -> 16563010
A82: 38 | B82: Kooka Paper Manufacturing Sdn Bhd (2) | C82: 501330 | D82: USD | G82: 1.03033e+08 | J82: 90240.31 | P82: =1800.02-0.06 -> 1799.96 | R82: =G82+H82+J82+K82+I82-M82-O82-P82-Q82-N82 -> 1.0312144e+08 | S82: =R82-V82 -> 0.0082599968 | T82: 25268669 | U82: =D82 -> USD | V82: =T82*$V$1 -> 1.0312144e+08
A83: 39 | B83: Kyoto Energy Ventures Sdn Bhd | C83: 501160 | D83: MYR | G83: 3371186.7 | H83: 1234232 | R83: =G83+H83+J83+K83+I83-M83-O83-P83-Q83-N83 -> 4605418.7 | S83: =R83-V83 -> 0 | T83: 4605418.7 | U83: =D83 -> MYR | V83: =T83 -> 4605418.7
A84: 40 | B84: Kyoto Energy Ventures Sdn Bhd (2) | C84: 501275 | D84: MYR | G84: 3451826.3 | M84: 700726.7 | R84: =G84+H84+J84+K84+I84-M84-O84-P84-Q84-N84 -> 2751099.6 | S84: =R84-V84 -> 0 | T84: 2751099.6 | U84: =D84 -> MYR | V84: =T84 -> 2751099.6
A85: 41 | B85: MAC World Industries Sdn Bhd | C85: 501220 | D85: MYR | G85: 16269550 | H85: 2910000 | M85: 3714000 | R85: =G85+H85+J85+K85+I85-M85-O85-P85-Q85-N85 -> 15465550 | S85: =R85-V85 -> 0 | T85: 15465550 | U85: =D85 -> MYR | V85: =T85 -> 15465550
A86: 42 | B86: Malaysia Steel Works (KL) Bhd - SFi 1 | C86: 501320 | D86: MYR | G86: 9675561.3 | M86: 1366811.3 | R86: =G86+H86+J86+K86+I86-M86-O86-P86-Q86-N86 -> 8308750 | S86: =R86-V86 -> 0 | T86: 8308750 | U86: =D86 -> MYR | V86: =T86 -> 8308750
A87: 43 | B87: Malaysia Steel Works (KL) Bhd - SFi 2 | C87: 501201 | D87: MYR | G87: 39961050 | M87: 4668008.1 | R87: =G87+H87+J87+K87+I87-M87-O87-P87-Q87-N87 -> 35293042 | S87: =R87-V87 -> 0 | T87: 35293042 | U87: =D87 -> MYR | V87: =T87 -> 35293042
A88: 44 | B88: Master Suppliers Sdn Bhd | C88: 501211 | D88: MYR | G88: 1141930.2 | M88: 508175.74 | R88: =G88+H88+J88+K88+I88-M88-O88-P88-Q88-N88 -> 633754.42 | S88: =R88-V88 -> 0 | T88: 633754.42 | V88: =T88 -> 633754.42
A89: 45 | B89: Mewaholeo Industries Sdn Bhd | C89: 500783 | D89: MYR | G89: 17000000 | H89: 17000000 | M89: 17000000 | R89: =G89+H89+J89+K89+I89-M89-O89-P89-Q89-N89 -> 17000000 | S89: =R89-V89 -> 0 | T89: 17000000 | U89: =D89 -> MYR | V89: =T89 -> 17000000 | AB89: =H89+I89-M89-O89 -> 0 | AC89: =G89+H89+I89+J89-M89-O89-P89 -> 17000000
A90: 46 | B90: Mewah Oils Sdn Bhd | C90: 500790 | D90: MYR | G90: 42400000 | H90: 52200000 | M90: 49700000 | R90: =G90+H90+J90+K90+I90-M90-O90-P90-Q90-N90 -> 44900000 | S90: =R90-V90 -> 0 | T90: 44900000 | U90: =D90 -> MYR | V90: =T90 -> 44900000 | AB90: =H90+I90-M90-O90 -> 2500000 | AC90: =G90+H90+I90+J90-M90-O90-P90 -> 44900000
A91: 7 | B91: International Brass | C91: 500960 | D91: USD | G91: -0.0020499993 | R91: =G91+H91+J91+K91+I91-M91-O91-P91-Q91-N91 -> -0.0020499993 | S91: =R91-V91 -> -0.0020499993 | U91: =D91 -> USD | V91: =T91*$V$1 -> 0 | AB91: =H91+I91-M91-O91 -> 0 | AC91: =G91+H91+I91+J91-M91-O91-P91 -> -0.0020499993
A92: 7 | B92: Padiberas Nasional Berhad | C92: 500865 | D92: MYR | G92: 0 | R92: =G92+H92+J92+K92+I92-M92-O92-P92-Q92-N92 -> 0 | S92: =R92-V92 -> 0 | U92: =D92 -> MYR | V92: =T92 -> 0 | AB92: =H92+I92-M92-O92 -> 0 | AC92: =G92+H92+I92+J92-M92-O92-P92 -> 0
B93: Quantum Orient Sdn Bhd | C93: 500825 | D93: MYR | G93: 0 | R93: =G93+H93+J93+K93+I93-M93-O93-P93-Q93-N93 -> 0 | S93: =R93-V93 -> 0 | U93: =D93 -> MYR | V93: =T93 -> 0 | AB93: =H93+I93-M93-O93 -> 0 | AC93: =G93+H93+I93+J93-M93-O93-P93 -> 0
B94: Polymer Link Sdn Bhd | C94: 500935 | D94: USD | G94: 0 | R94: =G94+H94+J94+K94+I94-M94-O94-P94-Q94-N94 -> 0 | S94: =R94-V94 -> 0 | U94: =D94 -> USD | V94: =T94 -> 0 | AB94: =H94+I94-M94-O94 -> 0 | AC94: =G94+H94+I94+J94-M94-O94-P94 -> 0
B95: Rhinoshield Industries (M) Sdn Bhd | C95: 500949 | D95: MYR | G95: 0 | R95: =G95+H95+J95+K95+I95-M95-O95-P95-Q95-N95 -> 0 | S95: =R95-V95 -> 0 | U95: =D95 -> MYR | V95: =T95 -> 0 | AB95: =H95+I95-M95-O95 -> 0 | AC95: =G95+H95+I95+J95-M95-O95-P95 -> 0
B96: Sanrix Sdn Bhd | C96: 500795 | D96: USD | G96: 0 | R96: =G96+H96+J96+K96+I96-M96-O96-P96-Q96-N96 -> 0 | S96: =R96-V96 -> 0 | U96: =D96 -> USD | V96: =T96 -> 0 | AB96: =H96+I96-M96-O96 -> 0 | AC96: =G96+H96+I96+J96-M96-O96-P96 -> 0
B97: Seacera Tiles Marketing Sdn Bhd | C97: 500835 | D97: USD | G97: 0 | R97: =G97+H97+J97+K97+I97-M97-O97-P97-Q97-N97 -> 0 | S97: =R97-V97 -> 0 | U97: =D97 -> USD | V97: =T97 -> 0 | AB97: =H97+I97-M97-O97 -> 0 | AC97: =G97+H97+I97+J97-M97-O97-P97 -> 0
B98: Seacera Tiles Marketing Sdn Bhd 2 | C98: 500957 | D98: MYR | G98: 0 | R98: =G98+H98+J98+K98+I98-M98-O98-P98-Q98-N98 -> 0 | S98: =R98-V98 -> 0 | U98: =D98 -> MYR | V98: =T98 -> 0 | AB98: =H98+I98-M98-O98 -> 0 | AC98: =G98+H98+I98+J98-M98-O98-P98 -> 0
B99: SME Aerospace (Trade Finance) | C99: 500601 | D99: GBP | G99: 0 | R99: =G99+H99+J99+K99+I99-M99-O99-P99-Q99-N99 -> 0 | S99: =R99-V99 -> 0 | U99: =D99 -> GBP | V99: =T99 -> 0 | AB99: =H99+I99-M99-O99 -> 0 | AC99: =G99+H99+I99+J99-M99-O99-P99 -> 0
B100: Taiace Engineering Sdn Bhd | C100: 500537 | D100: MYR | G100: 0 | R100: =G100+H100+J100+K100+I100-M100-O100-P100-Q100-N100 -> 0 | S100: =R100-V100 -> 0 | U100: =D100 -> MYR | V100: =T100 -> 0 | AB100: =H100+I100-M100-O100 -> 0 | AC100: =G100+H100+I100+J100-M100-O100-P100 -> 0
B101: TPM IT Sdn Bhd | C101: 500532 | D101: USD | G101: 0 | R101: =G101+H101+J101+K101+I101-M101-O101-P101-Q101-N101 -> 0 | S101: =R101-V101 -> 0 | U101: =D101 -> USD | V101: =T101 -> 0 | AB101: =H101+I101-M101-O101 -> 0 | AC101: =G101+H101+I101+J101-M101-O101-P101 -> 0
B102: TT Vision Technologies Sdn Bhd | C102: 500536 | D102: MYR | G102: 0 | R102: =G102+H102+J102+K102+I102-M102-O102-P102-Q102-N102 -> 0 | S102: =R102-V102 -> 0 | U102: =D102 -> MYR | V102: =T102 -> 0 | AB102: =H102+I102-M102-O102 -> 0 | AC102: =G102+H102+I102+J102-M102-O102-P102 -> 0
A103: 7 | B103: SOP Edible Oil Sdn Bhd | C103: 500729 | D103: MYR | G103: 0 | R103: =G103+H103+J103+K103+I103-M103-O103-P103-Q103-N103 -> 0 | S103: =R103-V103 -> 0 | U103: =D103 -> MYR | V103: =T103 -> 0 | AB103: =H103+I103-M103-O103 -> 0 | AC103: =G103+H103+I103+J103-M103-O103-P103 -> 0
B104: SSP Raw Metals Tradings Sdn Bhd | C104: 500985 | D104: MYR | G104: 0 | R104: =G104+H104+J104+K104+I104-M104-O104-P104-Q104-N104 -> 0 | S104: =R104-V104 -> 0 | U104: =D104 -> MYR | V104: =T104 -> 0 | AB104: =H104+I104-M104-O104 -> 0 | AC104: =G104+H104+I104+J104-M104-O104-P104 -> 0
...

Sheet Debtors Listing Islamic (Profit
A1: Profit Outstanding (MYR) for Islamic Financing as at 31st July 2026 | V1: USD | W1: ='Debtors Listing Islamic (Cost)'!V1 -> 4.081 | X1: EUR | Y1: ='Debtors Listing Islamic (Cost)'!X1 -> 4.7017 | Z1: SGD | AA1: ='Debtors Listing Islamic (Cost)'!Z1 -> 3.1854
V2: GBP | W2: ='Debtors Listing Islamic (Cost)'!V2 -> 5.4924 | X2: AUD | Y2: ='Debtors Listing Islamic (Cost)'!X2 -> 2.8734
A4: No. | B4: Company | C4: Customer Account | D4: Currency | E4: Remarks | F4: Audit Adjustment | G4: Opening | H4: Disbursement | I4: Adjustment/ Capitalisation | J4: Forex (+) | K4: Unearned Profit | L4: Rental (Ijarah) | M4: Cost Payment | N4: Profit Payment | O4: Adjustment/ Capitalisation | P4: Forex (-) | Q4: Unearned Profit | R4: Balance | U4: Base Currency COD & ARRD | W4: COD & ARRD in Local Currency
B6: Islamic Financing Facility
B8: Supplier Credit Islamic Financing Facility - Tawaruq
B9: Allied PT Resources Sdn Bhd | C9: 500685 | D9: MYR | G9: 0 | R9: =G9+H9+J9+K9+I9-M9-O9-P9-Q9-N9 -> 0
B10: Arab Malaysian Vegetable Oil Products Co Ltd | C10: 500548 | D10: USD | G10: 0 | R10: =G10+H10+J10+K10+I10-M10-O10-P10-Q10-N10 -> 0
B11: Arab Malaysian Vegetable Oil Products Co Ltd - Trade | C11: 500556 | D11: USD | G11: 0 | R11: =G11+H11+J11+K11+I11-M11-O11-P11-Q11-N11 -> 0
B12: Awin Resources (Malaysia) Ltd | C12: 500858 | D12: USD | G12: 0 | R12: =G12+H12+J12+K12+I12-M12-O12-P12-Q12-N12 -> 0
B13: Destini Prima Sdn Bhd | C13: 500731 | D13: USD | G13: 0 | R13: =G13+H13+J13+K13+I13-M13-O13-P13-Q13-N13 -> 0
B14: Central Sugar Refinery | C14: 500815 | D14: MYR | G14: 0 | R14: =G14+H14+J14+K14+I14-M14-O14-P14-Q14-N14 -> 0
B15: Continental Resources Sdn Bhd | C15: 500813 | D15: USD | G15: 0 | R15: =G15+H15+J15+K15+I15-M15-O15-P15-Q15-N15 -> 0
B16: EON Metal Technology Sdn Bhd | C16: 500830 | D16: USD | G16: 0 | R16: =G16+H16+J16+K16+I16-M16-O16-P16-Q16-N16 -> 0
B17: Destini Shipbuilding & Engineering | C17: 500908 | D17: EUR | G17: 0 | R17: =G17+H17+J17+K17+I17-M17-O17-P17-Q17-N17 -> 0
A18: 1 | B18: Aescomed Healthcare Sdn Bhd | C18: 501125 | D18: MYR | G18: 0 | R18: =G18+H18+J18+K18+I18-M18-O18-P18-Q18-N18 -> 0 | S18: =R18-W18 -> 0 | T18: =D18 -> MYR | W18: =U18 -> 0
A19: 1 | B19: ACE Champion Sdn Bhd | C19: 501285 | D19: MYR | G19: 53602.99 | K19: 28981.82 | N19: 21995.97 | R19: =G19+H19+J19+K19+I19-M19-O19-P19-Q19-N19 -> 60588.84 | S19: =R19-W19 -> -0.01051631 | T19: =D19 -> MYR | U19: 60588.851 | W19: =U19 -> 60588.851
A20: 2 | B20: Agro 19 Berhad | C20: 501111 | D20: MYR | G20: 80463.05 | K20: 52215.59 | N20: 83203.4 | R20: =G20+H20+J20+K20+I20-M20-O20-P20-Q20-N20 -> 49475.24 | S20: =R20-W20 -> -0.00033291231 | T20: =D20 -> MYR | U20: 49475.24 | W20: =U20 -> 49475.24
A21: 3 | B21: Agro 19 Berhad 2 | C21: 501172 | D21: MYR | G21: 519510.75 | K21: 185865.3 | N21: 583821.24 | R21: =G21+H21+J21+K21+I21-M21-O21-P21-Q21-N21 -> 121554.81 | S21: =R21-W21 -> 0.0060155752 | T21: =D21 -> MYR | U21: 121554.8 | W21: =U21 -> 121554.8
A22: 4 | B22: Agro 19 Berhad 3 | C22: 501291 | D22: MYR | G22: 726607.4 | K22: 264168.94 | N22: 26212.24 | R22: =G22+H22+J22+K22+I22-M22-O22-P22-Q22-N22 -> 964564.1 | S22: =R22-W22 -> -0.024193847 | T22: =D22 -> MYR | U22: 964564.12 | W22: =U22 -> 964564.12
A23: 5 | B23: Agro 19 Berhad 4 | C23: 501350 | D23: MYR | G23: 2161.65 | K23: 33505.48 | R23: =G23+H23+J23+K23+I23-M23-O23-P23-Q23-N23 -> 35667.13 | S23: =R23-W23 -> 0.0067123288 | T23: =D23 -> MYR | U23: 35667.123 | W23: =U23 -> 35667.123
A24: 6 | B24: Agro 19 Berhad - RCi | C24: 501356 | D24: MYR | G24: 0 | K24: 588.53 | R24: =G24+H24+J24+K24+I24-M24-O24-P24-Q24-N24 -> 588.53 | S24: =R24-W24 -> 0.0038736712 | T24: =D24 -> MYR | U24: 588.52613 | W24: =U24 -> 588.52613
A25: 7 | B25: AMC Cincaria Sdn Bhd | C25: 501129 | D25: MYR | G25: 16511.49 | K25: 14738.85 | N25: 13451.23 | R25: =G25+H25+J25+K25+I25-M25-O25-P25-Q25-N25 -> 17799.11 | S25: =R25-W25 -> 0.010273112 | T25: =D25 -> MYR | U25: 17799.1 | W25: =U25 -> 17799.1
A26: 6 | B26: Ann Joo Integrated Steel Sdn Bhd | C26: 501161 | D26: MYR | G26: -1.5734258e-10 | R26: =G26+H26+J26+K26+I26-M26-O26-P26-Q26-N26 -> -1.5734258e-10 | S26: =R26-W26 -> -1.5734258e-10 | T26: =D26 -> MYR | W26: =U26 -> 0
A27: 7 | B27: Ann Joo Integrated Steel Sdn Bhd - TRi | C27: 501265 | D27: MYR | G27: 0 | R27: =G27+H27+J27+K27+I27-M27-O27-P27-Q27-N27 -> 0 | S27: =R27-W27 -> 0 | T27: =D27 -> MYR | W27: =U27 -> 0
A28: 7 | B28: AT Precision Engineering Sdn Bhd | C28: 501231 | D28: MYR | G28: -7.2759576e-12 | R28: =G28+H28+J28+K28+I28-M28-O28-P28-Q28-N28 -> -7.2759576e-12 | S28: =R28-W28 -> -7.2759576e-12 | T28: =D28 -> MYR
A29: 8 | B29: Bahru Stainless Sdn Bhd 1 | C29: 501351 | D29: USD | G29: 0 | K29: 84700.01 | R29: =G29+H29+J29+K29+I29-M29-O29-P29-Q29-N29 -> 84700.01 | S29: =R29-W29 -> -0.011388889 | T29: =D29 -> USD | U29: 20754.722 | W29: =U29*$W$1 -> 84700.021
A30: 9 | B30: Bahru Stainless Sdn Bhd 2 | C30: 501352 | D30: USD | G30: 0 | K30: 176607.56 | R30: =G30+H30+J30+K30+I30-M30-O30-P30-Q30-N30 -> 176607.56 | S30: =R30-W30 -> 0.017777778 | T30: =D30 -> USD | U30: 43275.556 | W30: =U30*$W$1 -> 176607.54
A32: 10 | B32: Bateriku (M) Sdn Bhd | C32: 501306 | D32: MYR | G32: 57650.45 | K32: 39949.81 | R32: =G32+H32+J32+K32+I32-M32-O32-P32-Q32-N32 -> 97600.26 | S32: =R32-W32 -> 0.0012039973 | T32: =D32 -> MYR | U32: 97600.259 | W32: =U32 -> 97600.259
A33: 8 | B33: Bertambest Sdn Bhd | C33: 501137 | D33: MYR | G33: 0 | R33: =G33+H33+J33+K33+I33-M33-O33-P33-Q33-N33 -> 0 | S33: =R33-W33 -> 0 | T33: =D33 -> MYR | W33: =U33 -> 0
A34: 11 | B34: Bhavani Foods (M) Sdn Bhd | C34: 501131 | D34: MYR | G34: 19007.85 | K34: 10689.54 | N34: =9695.8+14.08 -> 9709.88 | R34: =G34+H34+J34+K34+I34-M34-O34-P34-Q34-N34 -> 19987.51 | S34: =R34-W34 -> -0.0041657315 | T34: =D34 -> MYR | U34: 19987.514 | W34: =U34 -> 19987.514
A35: 12 | B35: Bio Eneco Sdn Bhd | C35: 501035 | D35: MYR | G35: 10038.29 | K35: 14144.87 | R35: =G35+H35+J35+K35+I35-M35-O35-P35-Q35-N35 -> 24183.16 | S35: =R35-W35 -> 0.00054794521 | T35: =D35 -> MYR | U35: 24183.159 | W35: =U35 -> 24183.159 | AC35: =I35+J35+K35+L35-N35-O35-P35-Q35 -> 14144.87 | AD35: =G35+I35+J35+K35+L35-N35-O35-P35-Q35 -> 24183.16
A36: 10 | B36: Bousted Petroleum Marketing | C36: 501086 | D36: USD | G36: 0 | R36: =G36+H36+J36+K36+I36-M36-O36-P36-Q36-N36 -> 0 | S36: =R36-W36 -> 0 | T36: =D36 -> USD | W36: =U36*$W$1 -> 0
A37: 7 | B37: Bousted Petroleum Marketing | C37: 501156 | D37: USD | G37: 0 | R37: =G37+H37+J37+K37+I37-M37-O37-P37-Q37-N37 -> 0 | S37: =R37-W37 -> 0 | T37: =D37 -> USD | W37: =U37*$W$1 -> 0
A38: 13 | B38: Choon Eng (Sarawak) Sdn Bhd | C38: 501142 | D38: MYR | G38: 60030.59 | K38: 38987.58 | N38: 17633.72 | R38: =G38+H38+J38+K38+I38-M38-O38-P38-Q38-N38 -> 81384.45 | S38: =R38-W38 -> -0.012864142 | T38: =D38 -> MYR | U38: 81384.463 | W38: =U38 -> 81384.463
A39: 14 | B39: Coco Oro Jewellery Sdn Bhd - SFi | C39: 501293 | D39: MYR | G39: 70793.35 | K39: 54275.72 | N39: 28160.01 | R39: =G39+H39+J39+K39+I39-M39-O39-P39-Q39-N39 -> 96909.06 | S39: =R39-W39 -> -0.013535356 | T39: =D39 -> MYR | U39: 96909.074 | W39: =U39 -> 96909.074
A40: 15 | B40: Coco Oro Jewellery Sdn Bhd - RCi | C40: 501318 | D40: MYR | G40: 3525.24 | K40: 13660.3 | R40: =G40+H40+J40+K40+I40-M40-O40-P40-Q40-N40 -> 17185.54 | S40: =R40-W40 -> 0.0030136986 | T40: =D40 -> MYR | U40: 17185.537 | W40: =U40 -> 17185.537
A41: 16 | B41: Enapak Packaging Sdn Bhd | C41: 501344 | D41: MYR | G41: 5052.16 | K41: 29651.23 | R41: =G41+H41+J41+K41+I41-M41-O41-P41-Q41-N41 -> 34703.39 | S41: =R41-W41 -> 0.0011578082 | U41: 34703.389 | W41: =U41 -> 34703.389
A42: 17 | B42: Enviros Survey & Consultancy Sdn Bhd | C42: 501235 | D42: USD | G42: 65863.43 | I42: 19706.86 | J42: 105.05 | K42: =28101.48 -> 28101.48 | N42: 49623.43 | R42: =G42+H42+J42+K42+I42-M42-O42-P42-Q42-N42 -> 64153.39 | S42: =R42-W42 -> -0.0032971179 | T42: =D42 -> USD | U42: 15720.018 | W42: =U42*$W$1 -> 64153.393
A43: 18 | B43: Enviros Survey & Consultancy Sdn Bhd - SFi | C43: 501323 | D43: MYR | G43: 9145.02 | K43: 416.44 | N43: 9561.45 | O43: 0.01 | R43: =G43+H43+J43+K43+I43-M43-O43-P43-Q43-N43 -> 0 | S43: =R43-W43 -> 0 | T43: MYR | U43: 0 | W43: =U43 -> 0
A44: 19 | B44: Evergreen Fibreboard Berhad | C44: 501290 | D44: MYR | G44: 73546.84 | K44: 57276.16 | N44: 34027.4 | R44: =G44+H44+J44+K44+I44-M44-O44-P44-Q44-N44 -> 96795.6 | S44: =R44-W44 -> -0.01369863 | T44: =D44 -> MYR | U44: 96795.614 | W44: =U44 -> 96795.614
A45: 20 | B45: Evergreen Fibreboard Berhad - SFi | C45: 501347 | D45: MYR | G45: 15284.55 | K45: 17883.42 | N45: 14279.25 | R45: =G45+H45+J45+K45+I45-M45-O45-P45-Q45-N45 -> 18888.72 | S45: =R45-W45 -> -0.0053223945 | U45: 18888.725 | W45: =U45 -> 18888.725
A46: 21 | B46: Fabulous Sunview Sdn Bhd | C46: 501232 | D46: USD | G46: 251062.76 | J46: 215.49 | K46: 130698.47 | R46: =G46+H46+J46+K46+I46-M46-O46-P46-Q46-N46 -> 381976.72 | S46: =R46-W46 -> -0.0014957979 | T46: USD | U46: 93598.805 | W46: =U46*$W$1 -> 381976.72
A47: 22 | B47: Fathopes Energy Sdn Bhd (1) | C47: 501181 | D47: MYR | G47: 39038.85 | K47: 53446.97 | N47: 50485.9 | R47: =G47+H47+J47+K47+I47-M47-O47-P47-Q47-N47 -> 41999.92 | S47: =R47-W47 -> -0.0077480301 | T47: =D47 -> MYR | U47: 41999.928 | W47: =U47 -> 41999.928
A48: 18 | B48: Fathopes Energy Sdn Bhd (2) | C48: 501208 | D48: MYR | G48: 0 | R48: =G48+H48+J48+K48+I48-M48-O48-P48-Q48-N48 -> 0 | S48: =R48-W48 -> 0 | T48: =D48 -> MYR | W48: =U48 -> 0
A49: 15 | B49: Fathopes Energy Sdn Bhd (3) | C49: 501242 | D49: MYR | G49: 0 | R49: =G49+H49+J49+K49+I49-M49-O49-P49-Q49-N49 -> 0 | S49: =R49-W49 -> 0 | T49: =D49 -> MYR | W49: =U49 -> 0
A50: 23 | B50: Felda Global Ventures Capital | C50: 500784 | D50: MYR | G50: 85300.82 | K50: 193216.99 | N50: 230706.85 | R50: =G50+H50+J50+K50+I50-M50-O50-P50-Q50-N50 -> 47810.96 | S50: =R50-W50 -> 0.0017808219 | T50: =D50 -> MYR | U50: 47810.958 | W50: =U50 -> 47810.958 | AC50: =I50+J50+K50+L50-N50-O50-P50-Q50 -> -37489.86 | AD50: =G50+I50+J50+K50+L50-N50-O50-P50-Q50 -> 47810.96
B51: Felda Global Ventures Plantations | C51: 500671 | D51: MYR | G51: 0 | R51: =G51+H51+J51+K51+I51-M51-O51-P51-Q51-N51 -> 0 | S51: =R51-W51 -> 0 | T51: =D51 -> MYR | AC51: =I51+J51+K51+L51-N51-O51-P51-Q51 -> 0 | AD51: =G51+I51+J51+K51+L51-N51-O51-P51-Q51 -> 0
B52: Felda Palm Industries Sdn Bhd | C52: 500551 | D52: MYR | G52: 0 | R52: =G52+H52+J52+K52+I52-M52-O52-P52-Q52-N52 -> 0 | S52: =R52-W52 -> 0 | T52: =D52 -> MYR | AC52: =I52+J52+K52+L52-N52-O52-P52-Q52 -> 0 | AD52: =G52+I52+J52+K52+L52-N52-O52-P52-Q52 -> 0
B53: Felda Rubber Industries Sdn Bhd | C53: 500531 | D53: MYR | G53: 0 | R53: =G53+H53+J53+K53+I53-M53-O53-P53-Q53-N53 -> 0 | S53: =R53-W53 -> 0 | T53: =D53 -> MYR | AC53: =I53+J53+K53+L53-N53-O53-P53-Q53 -> 0 | AD53: =G53+I53+J53+K53+L53-N53-O53-P53-Q53 -> 0
B54: FPM Sendirian Berhad | C54: 500628 | D54: USD | G54: 0 | R54: =G54+H54+J54+K54+I54-M54-O54-P54-Q54-N54 -> 0 | S54: =R54-W54 -> 0 | T54: =D54 -> USD | AC54: =I54+J54+K54+L54-N54-O54-P54-Q54 -> 0 | AD54: =G54+I54+J54+K54+L54-N54-O54-P54-Q54 -> 0
B55: KA Petra Sdn Bhd | C55: 500739 | D55: MYR | G55: 0 | R55: =G55+H55+J55+K55+I55-M55-O55-P55-Q55-N55 -> 0 | S55: =R55-W55 -> 0 | T55: =D55 -> MYR | AC55: =I55+J55+K55+L55-N55-O55-P55-Q55 -> 0 | AD55: =G55+I55+J55+K55+L55-N55-O55-P55-Q55 -> 0
B56: Malaysia Cocoa Manufacturing | C56: 500588 | D56: GBP | G56: 0 | R56: =G56+H56+J56+K56+I56-M56-O56-P56-Q56-N56 -> 0 | S56: =R56-W56 -> 0 | T56: =D56 -> GBP | AC56: =I56+J56+K56+L56-N56-O56-P56-Q56 -> 0 | AD56: =G56+I56+J56+K56+L56-N56-O56-P56-Q56 -> 0
A57: 3 | B57: Foresight Industries Sdn Bhd | C57: 500851 | D57: MYR | G57: 0 | R57: =G57+H57+J57+K57+I57-M57-O57-P57-Q57-N57 -> 0 | S57: =R57-W57 -> 0 | T57: =D57 -> MYR | W57: =U57 -> 0 | AC57: =I57+J57+K57+L57-N57-O57-P57-Q57 -> 0 | AD57: =G57+I57+J57+K57+L57-N57-O57-P57-Q57 -> 0
B58: Fleet Palms Sdn Bhd | C58: 500889 | D58: MYR | G58: 0 | R58: =G58+H58+J58+K58+I58-M58-O58-P58-Q58-N58 -> 0 | S58: =R58-W58 -> 0 | T58: =D58 -> MYR | W58: =U58 -> 0 | AC58: =I58+J58+K58+L58-N58-O58-P58-Q58 -> 0 | AD58: =G58+I58+J58+K58+L58-N58-O58-P58-Q58 -> 0
B59: Golden Scoop Sdn Bhd | C59: 500967 | D59: SGD | G59: 0 | R59: =G59+H59+J59+K59+I59-M59-O59-P59-Q59-N59 -> 0 | S59: =R59-W59 -> 0 | T59: =D59 -> SGD | W59: =U59 -> 0 | AC59: =I59+J59+K59+L59-N59-O59-P59-Q59 -> 0 | AD59: =G59+I59+J59+K59+L59-N59-O59-P59-Q59 -> 0
B60: Khee San Food Industries Sdn Bhd | C60: 500950 | D60: USD | G60: 0 | R60: =G60+H60+J60+K60+I60-M60-O60-P60-Q60-N60 -> 0 | S60: =R60-W60 -> 0 | T60: =D60 -> USD | W60: =U60 -> 0 | AC60: =I60+J60+K60+L60-N60-O60-P60-Q60 -> 0 | AD60: =G60+I60+J60+K60+L60-N60-O60-P60-Q60 -> 0
B61: Malaysian Consortium of Rubber Product | C61: 500670 | D61: USD | G61: 0 | R61: =G61+H61+J61+K61+I61-M61-O61-P61-Q61-N61 -> 0 | S61: =R61-W61 -> 0 | T61: =D61 -> USD | W61: =U61 -> 0 | AC61: =I61+J61+K61+L61-N61-O61-P61-Q61 -> 0 | AD61: =G61+I61+J61+K61+L61-N61-O61-P61-Q61 -> 0
B62: Mewah Datu Sdn Bhd | C62: 500727 | D62: MYR | G62: 0 | R62: =G62+H62+J62+K62+I62-M62-O62-P62-Q62-N62 -> 0 | S62: =R62-W62 -> 0 | T62: =D62 -> MYR | W62: =U62 -> 0 | AC62: =I62+J62+K62+L62-N62-O62-P62-Q62 -> 0 | AD62: =G62+I62+J62+K62+L62-N62-O62-P62-Q62 -> 0
A63: 12 | B63: Gaia Plas Sdn Bhd | C63: 501163 | D63: MYR | G63: 0 | R63: =G63+H63+J63+K63+I63-M63-O63-P63-Q63-N63 -> 0 | T63: =D63 -> MYR | W63: =U63 -> 0
A64: 24 | B64: FR Development Asia Sdn Bhd - RCi | C64: 501310 | D64: MYR | G64: 6278.16 | K64: 6004.66 | R64: =G64+H64+J64+K64+I64-M64-O64-P64-Q64-N64 -> 12282.82 | S64: =R64-W64 -> 0.010513932 | T64: =D64 -> MYR | U64: 12282.809 | W64: =U64 -> 12282.809
A65: 25 | B65: FR Development Asia Sdn Bhd - SFi | C65: 501261 | D65: MYR | G65: 31281.13 | K65: 22836.27 | N65: 20136.96 | R65: =G65+H65+J65+K65+I65-M65-O65-P65-Q65-N65 -> 33980.44 | S65: =R65-W65 -> 0.0040955009 | T65: =D65 -> MYR | U65: 33980.436 | W65: =U65 -> 33980.436
A66: 26 | B66: Gemilang Coachwork Sdn Bhd | C66: 501147 | D66: MYR | G66: 100292.82 | K66: 26240.75 | N66: 16022.95 | R66: =G66+H66+J66+K66+I66-M66-O66-P66-Q66-N66 -> 110510.62 | S66: =R66-U66 -> -0.0011850302 | T66: =D66 -> MYR | U66: 110510.62 | W66: =U66*$W$1 -> 450993.85
A67: 27 | B67: Gemilang Coachwork Sdn Bhd - RCi | C67: 501281 | D67: MYR | G67: 85258.15 | K67: 29953.84 | R67: =G67+H67+J67+K67+I67-M67-O67-P67-Q67-N67 -> 115211.99 | S67: =R67-U67 -> -0.0018859918 | T67: =D67 -> MYR | U67: 115211.99 | W67: =U67*$W$1 -> 470180.14
A68: 28 | B68: Gemilang Coachwork Sdn Bhd - SFi 2 | C68: 501331 | D68: MYR | G68: 227207.8 | K68: 59008.57 | R68: =G68+H68+J68+K68+I68-M68-O68-P68-Q68-N68 -> 286216.37 | S68: =R68-U68 -> 0.0018275341 | T68: =D68 -> MYR | U68: 286216.37 | W68: =U68*$W$1 -> 1168049
A69: 29 | B69: Gemilang Coachwork Sdn Bhd - SFi 3 | C69: 501348 | D69: USD | G69: 91325.09 | J69: 72.64 | K69: 94695.36 | N69: 3916.35 | R69: =G69+H69+J69+K69+I69-M69-O69-P69-Q69-N69 -> 182176.74 | S69: =R69-W69 -> -0.0047547302 | T69: =D69 -> USD | U69: 44640.222 | W69: =U69*$W$1 -> 182176.74
A70: 30 | B70: Glide Technology Sdn Bhd | C70: 501149 | D70: MYR | G70: 15181.15 | K70: 11242.36 | N70: 9110.49 | R70: =G70+H70+J70+K70+I70-M70-O70-P70-Q70-N70 -> 17313.02 | S70: =R70-W70 -> 0.0086167123 | T70: =D70 -> MYR | U70: 17313.011 | W70: =U70 -> 17313.011
A71: 31 | B71: Hernan Corporation Sdn Bhd | C71: 501128 | D71: USD | G71: 9702.39 | J71: 8.29 | K71: 44909.08 | R71: =G71+H71+J71+K71+I71-M71-O71-P71-Q71-N71 -> 54619.76 | S71: =R71-W71 -> -0.0041033952 | T71: =D71 -> USD | U71: 13383.917 | W71: =U71*$W$1 -> 54619.764
A72: 32 | B72: Hernan Corporation Sdn Bhd - RCi | C72: 501317 | D72: USD | G72: 22874.5 | J72: 19.64 | K72: 11334.04 | R72: =G72+H72+J72+K72+I72-M72-O72-P72-Q72-N72 -> 34228.18 | S72: =R72-W72 -> -0.0033064748 | T72: =D72 -> USD | U72: 8387.2049 | W72: =U72*$W$1 -> 34228.183
A73: 33 | B73: Hy-Fresh Industries Sdn Bhd | C73: 501194 | D73: MYR | G73: 87785.64 | K73: 39787.64 | N73: 72681.64 | R73: =G73+H73+J73+K73+I73-M73-O73-P73-Q73-N73 -> 54891.64 | S73: =R73-W73 -> -0.014315937 | T73: =D73 -> MYR | U73: 54891.654 | W73: =U73 -> 54891.654
A74: 34 | B74: Impact Metal Resources Sdn Bhd | C74: 501140 | D74: MYR | G74: 17055.29 | K74: 17892.78 | R74: =G74+H74+J74+K74+I74-M74-O74-P74-Q74-N74 -> 34948.07 | S74: =R74-W74 -> -0.028684529 | T74: =D74 -> MYR | U74: 34948.099 | W74: =U74 -> 34948.099
A75: 35 | B75: Impact Metal Resources Sdn Bhd (2) | C75: 501195 | D75: MYR | G75: 140450.12 | K75: 35258.56 | N75: 148740.53 | R75: =G75+H75+J75+K75+I75-M75-O75-P75-Q75-N75 -> 26968.15 | S75: =R75-W75 -> -0.018793153 | T75: =D75 -> MYR | U75: 26968.169 | W75: =U75 -> 26968.169
A76: 36 | B76: Ingress Industrial (M) Sdn Bhd | C76: 501133 | D76: USD | G76: 147841.03 | J76: 228.87 | K76: 113657.93 | N76: 100597.28 | R76: =G76+H76+J76+K76+I76-M76-O76-P76-Q76-N76 -> 161130.55 | S76: =R76-W76 -> -0.0048353001 | T76: =D76 -> USD | U76: 39483.106 | W76: =U76*$W$1 -> 161130.55
A77: 6 | B77: Maxim Textile Technology Sdn Bhd | C77: 501095 | D77: USD | G77: 0 | R77: =G77+H77+J77+K77+I77-M77-O77-P77-Q77-N77 -> 0 | S77: =R77-W77 -> 0 | T77: =D77 -> USD | W77: =U77*$W$1 -> 0
A78: 32 | B78: Iradar Sdn Bhd | C78: 501245 | D78: MYR | G78: 0 | R78: =G78+H78+J78+K78+I78-M78-O78-P78-Q78-N78 -> 0 | S78: =R78-W78 -> 0 | T78: MYR | W78: =U78 -> 0
A79: 25 | B79: JFC Foods Industries Sdn Bhd | C79: 501213 | D79: MYR | G79: 0 | R79: =G79+H79+J79+K79+I79-M79-O79-P79-Q79-N79 -> 0 | S79: =R79-W79 -> 0 | T79: MYR | W79: =U79 -> 0
A80: 30 | B80: Kennwu Manufacturing (M) Sdn Bhd | C80: 501270 | D80: MYR | G80: 0 | R80: =G80+H80+J80+K80+I80-M80-O80-P80-Q80-N80 -> 0 | S80: =R80-W80 -> 0 | T80: MYR | W80: =U80 -> 0
A81: 32 | B81: Klitz Vibrant Imported Kitchens Sdn Bhd | C81: 501145 | D81: MYR | G81: 0 | R81: =G81+H81+J81+K81+I81-M81-O81-P81-Q81-N81 -> 0 | S81: =R81-W81 -> 0 | T81: =D81 -> MYR | W81: =U81 -> 0
A82: 37 | B82: Kooka Paper Manufacturing Sdn Bhd (1) | C82: 501325 | D82: USD | G82: 90495.73 | J82: 77.67 | K82: 20107.13 | R82: =G82+H82+J82+K82+I82-M82-O82-P82-Q82-N82 -> 110680.53 | S82: =R82-W82 -> 0.0046150961 | T82: USD | U82: 27120.932 | W82: =U82*$W$1 -> 110680.53
A83: 38 | B83: Kooka Paper Manufacturing Sdn Bhd (2) | C83: 501330 | D83: USD | G83: 2097028.4 | J83: 1800.02 | K83: 598154.5 | R83: =G83+H83+J83+K83+I83-M83-O83-P83-Q83-N83 -> 2696982.9 | S83: =R83-W83 -> 8.4248837e-05 | T83: USD | U83: 660863.24 | W83: =U83*$W$1 -> 2696982.9
A84: 39 | B84: Kyoto Energy Ventures Sdn Bhd | C84: 501160 | D84: MYR | G84: 36893.54 | K84: 22808.06 | R84: =G84+H84+J84+K84+I84-M84-O84-P84-Q84-N84 -> 59701.6 | S84: =R84-W84 -> 0.0029626877 | T84: =D84 -> MYR | U84: 59701.597 | W84: =U84 -> 59701.597
A85: 40 | B85: Kyoto Energy Ventures Sdn Bhd (2) | C85: 501275 | D85: MYR | G85: 94814.17 | K85: 21458.04 | N85: 24016.7 | R85: =G85+H85+J85+K85+I85-M85-O85-P85-Q85-N85 -> 92255.51 | S85: =R85-W85 -> 0.043308633 | T85: =D85 -> MYR | U85: 92255.467 | W85: =U85 -> 92255.467
A86: 41 | B86: MAC World Industries Sdn Bhd | C86: 501220 | D86: MYR | G86: 208009.06 | K86: 87802.38 | N86: 78141.71 | R86: =G86+H86+J86+K86+I86-M86-O86-P86-Q86-N86 -> 217669.73 | S86: =R86-W86 -> 0.011808219 | T86: =D86 -> MYR | U86: 217669.72 | W86: =U86 -> 217669.72
A87: 42 | B87: Malaysia Steel Works (KL) Bhd - SFi 1 | C87: 501320 | D87: MYR | G87: 20912.21 | K87: 6957.96 | N87: 27870.17 | R87: =G87+H87+J87+K87+I87-M87-O87-P87-Q87-N87 -> 0 | S87: =R87-W87 -> 0 | T87: =D87 -> MYR | U87: 0 | W87: =U87 -> 0
A88: 38 | B88: Malaysia Steel Works (KL) Bhd - SFi 2 | C88: 501201 | D88: MYR | G88: 0 | R88: =G88+H88+J88+K88+I88-M88-O88-P88-Q88-N88 -> 0 | S88: =R88-W88 -> 0 | T88: =D88 -> MYR | W88: =U88 -> 0
A89: 43 | B89: Master Suppliers Sdn Bhd | C89: 501211 | D89: MYR | G89: 8791.42 | K89: 4787.83 | N89: 6360.5 | R89: =G89+H89+J89+K89+I89-M89-O89-P89-Q89-N89 -> 7218.75 | S89: =R89-W89 -> -0.0059177753 | T89: =D89 -> MYR | U89: 7218.7559 | W89: =U89 -> 7218.7559
A90: 44 | B90: Mewaholeo Industries Sdn Bhd | C90: 500783 | D90: MYR | G90: 45040.61 | K90: 82398.63 | N90: 79191.08 | R90: =G90+H90+J90+K90+I90-M90-O90-P90-Q90-N90 -> 48248.16 | S90: =R90-W90 -> 0.061917808 | T90: =D90 -> MYR | U90: 48248.098 | W90: =U90 -> 48248.098 | AC90: =I90+J90+K90+L90-N90-O90-P90-Q90 -> 3207.55 | AD90: =G90+I90+J90+K90+L90-N90-O90-P90-Q90 -> 48248.16
A91: 45 | B91: Mewah Oils Sdn Bhd | C91: 500790 | D91: MYR | G91: 128738.53 | K91: 199957.81 | N91: 219526.26 | R91: =G91+H91+J91+K91+I91-M91-O91-P91-Q91-N91 -> 109170.08 | S91: =R91-W91 -> 0.011232877 | T91: =D91 -> MYR | U91: 109170.07 | W91: =U91 -> 109170.07 | AC91: =I91+J91+K91+L91-N91-O91-P91-Q91 -> -19568.45 | AD91: =G91+I91+J91+K91+L91-N91-O91-P91-Q91 -> 109170.08
A92: 46 | B92: MHC Cold Storage Sdn Bhd - RCi | C92: 501240 | D92: MYR | G92: 67794.49 | K92: 30023.29 | R92: =G92+H92+J92+K92+I92-M92-O92-P92-Q92-N92 -> 97817.78 | S92: =R92-W92 -> -0.028219178 | T92: =D92 -> MYR | U92: 97817.808 | W92: =U92 -> 97817.808
B93: Modenas | C93: 500786 | D93: MYR | E93: Unearned Profit | G93: 0 | R93: =G93+H93+J93+K93+I93-M93-O93-P93-Q93-N93 -> 0 | S93: =R93-W93 -> 0 | T93: =D93 -> MYR | AC93: =I93+J93+K93+L93-N93-O93-P93-Q93 -> 0 | AD93: =G93+I93+J93+K93+L93-N93-O93-P93-Q93 -> 0
B94: Mr Technology Sdn Bhd | C94: 500778 | D94: USD | G94: 0 | R94: =G94+H94+J94+K94+I94-M94-O94-P94-Q94-N94 -> 0 | S94: =R94-W94 -> 0 | T94: =D94 -> USD | AC94: =I94+J94+K94+L94-N94-O94-P94-Q94 -> 0 | AD94: =G94+I94+J94+K94+L94-N94-O94-P94-Q94 -> 0
B95: Pacific Inter-Link Sdn Bhd | C95: 500637 | D95: USD | G95: 0 | R95: =G95+H95+J95+K95+I95-M95-O95-P95-Q95-N95 -> 0 | S95: =R95-W95 -> 0 | T95: =D95 -> USD | AC95: =I95+J95+K95+L95-N95-O95-P95-Q95 -> 0 | AD95: =G95+I95+J95+K95+L95-N95-O95-P95-Q95 -> 0
A96: 6 | B96: International Brass | C96: 500960 | D96: USD | G96: -2.7648639e-10 | R96: =G96+H96+J96+K96+I96-M96-O96-P96-Q96-N96 -> -2.7648639e-10 | S96: =R96-W96 -> -2.7648639e-10 | T96: =D96 -> USD | W96: =U96*$W$1 -> 0 | AC96: =I96+J96+K96+L96-N96-O96-P96-Q96 -> 0 | AD96: =G96+I96+J96+K96+L96-N96-O96-P96-Q96 -> -2.7648639e-10
A97: 6 | B97: Nupon Technology Sdn Bhd | C97: 500887 | D97: USD | G97: 0.00455 | R97: =G97+H97+J97+K97+I97-M97-O97-P97-Q97-N97 -> 0.00455 | S97: =R97-W97 -> 0.00455 | T97: =D97 -> USD | W97: =U97*$W$1 -> 0 | AC97: =I97+J97+K97+L97-N97-O97-P97-Q97 -> 0 | AD97: =G97+I97+J97+K97+L97-N97-O97-P97-Q97 -> 0.00455
A98: 7 | B98: Nupon Technology Sdn Bhd 2 | C98: 501040 | D98: USD | G98: -0.004425 | R98: =G98+H98+J98+K98+I98-M98-O98-P98-Q98-N98 -> -0.004425 | S98: =R98-W98 -> -0.004425 | T98: =D98 -> USD | W98: =U98*$W$1 -> 0 | AC98: =I98+J98+K98+L98-N98-O98-P98-Q98 -> 0 | AD98: =G98+I98+J98+K98+L98-N98-O98-P98-Q98 -> -0.004425
A99: 7 | B99: Padiberas Nasional Berhad | C99: 500865 | D99: MYR | G99: 0 | R99: =G99+H99+J99+K99+I99-M99-O99-P99-Q99-N99 -> 0 | S99: =R99-W99 -> 0 | T99: =D99 -> MYR | W99: =U99 -> 0 | AC99: =I99+J99+K99+L99-N99-O99-P99-Q99 -> 0 | AD99: =G99+I99+J99+K99+L99-N99-O99-P99-Q99 -> 0
B100: Quantum Orient Sdn Bhd | C100: 500825 | D100: MYR | G100: 0 | R100: =G100+H100+J100+K100+I100-M100-O100-P100-Q100-N100 -> 0 | S100: =R100-W100 -> 0 | T100: =D100 -> MYR | W100: =U100 -> 0 | AC100: =I100+J100+K100+L100-N100-O100-P100-Q100 -> 0 | AD100: =G100+I100+J100+K100+L100-N100-O100-P100-Q100 -> 0
B101: Polymer Link Sdn Bhd | C101: 500935 | D101: USD | G101: 0 | R101: =G101+H101+J101+K101+I101-M101-O101-P101-Q101-N101 -> 0 | S101: =R101-W101 -> 0 | T101: =D101 -> USD | W101: =U101 -> 0 | AC101: =I101+J101+K101+L101-N101-O101-P101-Q101 -> 0 | AD101: =G101+I101+J101+K101+L101-N101-O101-P101-Q101 -> 0
B102: Rhinoshield Industries (M) Sdn Bhd | C102: 500949 | D102: MYR | G102: 0 | R102: =G102+H102+J102+K102+I102-M102-O102-P102-Q102-N102 -> 0 | S102: =R102-W102 -> 0 | T102: =D102 -> MYR | W102: =U102 -> 0 | AC102: =I102+J102+K102+L102-N102-O102-P102-Q102 -> 0 | AD102: =G102+I102+J102+K102+L102-N102-O102-P102-Q102 -> 0
B103: Sanrix Sdn Bhd | C103: 500795 | D103: USD | G103: 0 | R103: =G103+H103+J103+K103+I103-M103-O103-P103-Q103-N103 -> 0 | S103: =R103-W103 -> 0 | T103: =D103 -> USD | W103: =U103 -> 0 | AC103: =I103+J103+K103+L103-N103-O103-P103-Q103 -> 0 | AD103: =G103+I103+J103+K103+L103-N103-O103-P103-Q103 -> 0
B104: Seacera Tiles Marketing Sdn Bhd | C104: 500835 | D104: USD | G104: 0 | R104: =G104+H104+J104+K104+I104-M104-O104-P104-Q104-N104 -> 0 | S104: =R104-W104 -> 0 | T104: =D104 -> USD | W104: =U104 -> 0 | AC104: =I104+J104+K104+L104-N104-O104-P104-Q104 -> 0 | AD104: =G104+I104+J104+K104+L104-N104-O104-P104-Q104 -> 0
...

Sheet Modification MORA & R&R
E1: 46204 | F1: 46174
D2: USD | E2: 4.0775 | F2: 4.0775 | I2: Impaired
D3: EUR | E3: 4.6457 | F3: 4.6457
D4: RM | E4: 1 | F4: 1
B5: 2022
B6: No. | C6: Borrower code | D6: GL Code | E6: Borrower | F6: Trade/ Non trade | G6: Currency | H6: SME/NON SME | J6: Islamic/ conventional | K6: SLO acceptance date | L6: Auto Mora/Mora/Non-auto mora (R&R) | M6: Modification impact (Original Currency) | N6: Amortisation in July 2026 | O6: Revised Modification impact (Original Currency) | P6: Fx | Q6: Modification impact (RM)
B7: 1 | C7: 501010 | D7: 2230005 | E7: Malaysian Phosphate Additives (Sarawak) Sdn Bhd | F7: Non trade | G7: USD | H7: Non SME | J7: Islamic | K7: 44831 | L7: R&R | M7: 2604.1799 | N7: =13.93-[3]JV!F47 -> -2604.18 | O7: =SUM(M7:N7) -> -0.00012010165 | P7: =SUMIF($D$2:$D$4,G7,$E$2:$E$4) -> 4.0775 | Q7: =O7*P7 -> -0.00048971447 | U7: 4.728
Q8: =SUBTOTAL(9,Q7:Q7) -> -0.00048971447
G9: RM | M9: =SUMIF($G$7:$G$7,G9,$M$7:$M$7) -> 0 | N9: =SUMIF($G$7:$G$7,G9,$N$7:$N$7) -> 0 | O9: =SUMIF($G$7:$G$7,G9,$O$7:$O$7) -> 0
G10: USD | M10: =SUMIF($G$7:$G$7,G10,$M$7:$M$7) -> 2604.1799 | N10: =SUMIF($G$7:$G$7,G10,$N$7:$N$7) -> -2604.18 | O10: =SUMIF($G$7:$G$7,G10,$O$7:$O$7) -> -0.00012010165
B13: 2023
B14: No. | C14: Borrower code | D14: GL Code | E14: Borrower | F14: Trade/ Non trade | G14: Currency | H14: SME/NON SME | J14: Islamic/ conventional | K14: SLO acceptance date | L14: Auto Mora/Mora/Non-auto mora (R&R) | M14: Modification impact (Original Currency) | N14: =N6 -> Amortisation in July 2026 | O14: Revised Modification impact (Original Currency) | P14: Fx | Q14: Modification impact (RM)
B15: 1 | C15: 500943 | D15: 2230005 | E15: PWN Excellence Sdn Bhd 3 | F15: Non trade | G15: RM | H15: SME | J15: Islamic | K15: 45149 | L15: R&R | M15: 47984.742 | N15: -293.3 | O15: =SUM(M15:N15) -> 47691.442 | P15: =SUMIF($D$2:$D$4,G15,$E$2:$E$4) -> 1 | Q15: =O15*P15 -> 47691.442 | U15: 1
Q16: =SUBTOTAL(9,Q15:Q15) -> 47691.442
G17: RM | M17: =SUMIF($G$15:$G$15,G17,$M$15:$M$15) -> 47984.742 | N17: =SUMIF($G$15:$G$15,G17,$N$15:$N$15) -> -293.3 | O17: =SUMIF($G$15:$G$15,G17,$O$15:$O$15) -> 47691.442
G18: USD | M18: =SUMIF($G$15:$G$15,G18,$M$15:$M$15) -> 0 | N18: =SUMIF($G$15:$G$15,G18,$N$15:$N$15) -> 0 | O18: =SUMIF($G$15:$G$15,G18,$O$15:$O$15) -> 0
B20: 2024
B21: No. | C21: Borrower code | D21: GL Code | E21: Borrower | F21: Trade/ Non trade | G21: Currency | H21: SME/NON SME | J21: Islamic/ conventional | K21: SLO acceptance date | L21: Auto Mora/Mora/Non-auto mora (R&R) | M21: Modification impact (Original Currency) | N21: =N6 -> Amortisation in July 2026 | O21: Revised Modification impact (Original Currency) | P21: Fx | Q21: Modification impact (RM)
B22: 1 | C22: 501050 | D22: 2230005 | E22: Ingress Industrial (Thailand) Co Ltd | F22: Non trade | G22: RM | H22: Non SME | J22: Islamic | K22: 45625 | L22: R&R | M22: -1155735 | N22: 31875.41 | O22: =SUM(M22:N22) -> -1123859.5 | P22: =SUMIF($D$2:$D$4,G22,$E$2:$E$4) -> 1 | Q22: =O22*P22 -> -1123859.5
Q23: =SUBTOTAL(9,Q22:Q22) -> -1123859.5
G24: RM | M24: =SUMIF($G$22,G24,$M$22) -> -1155735 | N24: =SUMIF($G$22,G24,$N$22) -> 31875.41 | O24: =SUMIF($G$22,G24,$O$22) -> -1123859.5
G25: USD | M25: =SUMIF($G$22,G25,$M$22) -> 0 | N25: =SUMIF($G$22,G25,$N$22) -> 0 | O25: =SUMIF($G$22,G25,$O$22) -> 0
B28: 2025
B29: No. | C29: Borrower code | D29: GL Code | E29: Borrower | F29: Trade/ Non trade | G29: Currency | H29: SME/NON SME | J29: Islamic/ conventional | K29: SLO acceptance date | L29: Auto Mora/Mora/Non-auto mora (R&R) | M29: Modification impact (Original Currency) | N29: =N6 -> Amortisation in July 2026 | O29: Revised Modification impact (Original Currency) | P29: Fx | Q29: Modification impact (RM)
B30: 1 | C30: 501215 | D30: 2230005 | E30: JFC Food Industries Sdn Bhd | F30: Non trade | G30: RM | H30: SME | J30: Islamic | K30: 45896 | L30: R&R | M30: 162.39322 | N30: 142.9 | O30: =SUM(M30:N30) -> 305.29322 | P30: =SUMIF($D$2:$D$4,G30,$E$2:$E$4) -> 1 | Q30: =O30*P30 -> 305.29322
B31: 2 | C31: 501307 | D31: 2230005 | E31: YH Polymer Sdn Bhd | F31: Non trade | G31: RM | H31: SME | J31: Islamic | K31: 45971 | L31: R&R | M31: 463.0602 | N31: 340.58 | O31: =SUM(M31:N31) -> 803.6402 | P31: =SUMIF($D$2:$D$4,G31,$E$2:$E$4) -> 1 | Q31: =O31*P31 -> 803.6402
Q32: =SUBTOTAL(9,Q30:Q31) -> 1108.9334
G33: RM | M33: =SUMIF($G$30:$G$31,G33,$M$30:$M$31) -> 625.45342 | N33: =SUMIF($G$30:$G$31,G33,$N$30:$N$31) -> 483.48 | O33: =SUMIF($G$30:$G$31,G33,$O$30:$O$31) -> 1108.9334
G34: USD | M34: =SUMIF($G$30:$G$31,G34,$M$30:$M$31) -> 0 | N34: =SUMIF($G$30:$G$31,G34,$N$30:$N$31) -> 0 | O34: =SUMIF($G$30:$G$31,G34,$O$30:$O$31) -> 0
B36: 2026
B37: No. | C37: Borrower code | D37: GL Code | E37: Borrower | F37: Trade/ Non trade | G37: Currency | H37: SME/NON SME | J37: Islamic/ conventional | K37: SLO acceptance date | L37: Auto Mora/Mora/Non-auto mora (R&R) | M37: Modification impact (Original Currency) | N37: =N14 -> Amortisation in July 2026 | O37: Revised Modification impact (Original Currency) | P37: Fx | Q37: Modification impact (RM)
B38: 1 | C38: 501336 | D38: 2230005 | E38: KENNWU MANUFACTURING (M) SDN. BHD. | F38: Non trade | G38: RM | H38: SME | J38: Islamic | K38: 46129 | L38: R&R | M38: 419.84274 | N38: 206.72 | O38: =SUM(M38:N38) -> 626.56274 | P38: =SUMIF($D$2:$D$4,G38,$E$2:$E$4) -> 1 | Q38: =O38*P38 -> 626.56274
B39: 2 | M39: 0 | O39: =SUM(M39:N39) -> 0 | P39: =SUMIF($D$2:$D$4,G39,$E$2:$E$4) -> 0 | Q39: =O39*P39 -> 0
Q40: =SUBTOTAL(9,Q38:Q39) -> 626.56274
G41: RM | M41: =SUMIF($G$30:$G$31,G41,$M$30:$M$31) -> 625.45342 | N41: =SUMIF($G$30:$G$31,G41,$N$30:$N$31) -> 483.48 | O41: =SUMIF($G$30:$G$31,G41,$O$30:$O$31) -> 1108.9334
G42: USD | M42: =SUMIF($G$30:$G$31,G42,$M$30:$M$31) -> 0 | N42: =SUMIF($G$30:$G$31,G42,$N$30:$N$31) -> 0 | O42: =SUMIF($G$30:$G$31,G42,$O$30:$O$31) -> 0
G44: TOTAL | Q44: =Q8+Q16+Q23+Q32+Q40 -> -1074432.6
Q46: As per listing | R46: SAP | S46: Variance
O47: 134003 | P47: Conventional | Q47: =SUMIF($J$5:$J$39,P47,$Q$5:$Q$39) -> 0 | R47: 0 | S47: =Q47-R47 -> 0
O48: 2230005 | P48: Islamic | Q48: =SUMIF($J$5:$J$39,P48,$Q$5:$Q$39) -> -1074432.6 | S48: =Q48-R48 -> -1074432.6
P49: Total | Q49: =SUM(Q47:Q48) -> -1074432.6 | R49: =SUM(R47:R48) -> 0 | S49: =SUM(S47:S48) -> -1074432.6

Sheet Debtors Listing Conv Jan 2024
A1: Customer Balances as at January 2024
A3: Customer Account Number | B3: Customer Class & Industry | C3: Customer Name | D3: Loan Currency | E3: Opening Principal | F3: Disbursement | G3: Adjustment Capitalization | H3: Forex ( + ) | I3: Repayment | J3: Adjustment Capitalization | K3: Forex ( - ) | L3: Closing Principal
A5: 500937 | C5: THE MINISTRY OF FINANCE LAOS 2 | D5: USD | E5: 2.2491e+08 | F5: 0 | G5: 0 | H5: 6835500 | I5: 0 | J5: 0 | K5: 0 | L5: 2.317455e+08
B6: Active (Cross Border Credit) (Buyer Credit) | E6: 2.2491e+08 | F6: 0 | G6: 0 | H6: 6835500 | I6: 0 | J6: 0 | K6: 0 | L6: 2.317455e+08
A8: 500749 | C8: ISTANBUL SABIHA GOKCEN ULUSLARARASI | D8: EUR | E8: 142150400 | F8: 0 | G8: 0 | H8: 1134000 | I8: 0 | J8: 0 | K8: 0 | L8: 143284400
B9: Active (Overseas Investment) | E9: 142150400 | F9: 0 | G9: 0 | H9: 1134000 | I9: 0 | J9: 0 | K9: 0 | L9: 143284400
A11: 500640 | C11: OM MATERIAL (SARAWAK) SDN BHD | D11: USD | E11: 88355287 | F11: 0 | G11: 0 | H11: 2685307.7 | I11: 0 | J11: 0 | K11: 0 | L11: 91040594
A12: 500642 | C12: OM MATERIAL (SARAWAK) 2 | D12: USD | E12: 1.2136781e+08 | F12: 0 | G12: 0 | H12: 3688629.4 | I12: 0 | J12: 0 | K12: 0 | L12: 1.2505644e+08
A13: 501051 | C13: YINSON BORONIA PRODUCTION B.V (2) | D13: USD | E13: 5.3559792e+08 | F13: 0 | G13: 0 | H13: 16277976 | I13: -8342838 | J13: 0 | K13: 0 | L13: 5.4353306e+08
A14: 501072 | C14: SERI ERLANG (SINGAPORE) PTE LTD | D14: USD | E14: 29462572 | F14: 0 | G14: 0 | H14: 895431.12 | I14: 0 | J14: 0 | K14: 0 | L14: 30358004
A15: 501073 | C15: SERI EVEREST (SINGAPORE) PTE LTD | D15: USD | E15: 29465011 | F15: 0 | G15: 0 | H15: 895505.24 | I15: 0 | J15: 0 | K15: 0 | L15: 30360516
A16: 501075 | C16: SERI ELBERT (SINGAPORE) PTE LTD | D16: USD | E16: 29129172 | F16: 0 | G16: 0 | H16: 884302.85 | I16: -391364.55 | J16: 0 | K16: 0 | L16: 29622110
A17: 501076 | C17: SERI EMORY (SINGAPORE) PTE LTD | D17: USD | E17: 29266433 | F17: 0 | G17: 0 | H17: 887990.85 | I17: -581496.79 | J17: 0 | K17: 0 | L17: 29572927
A18: 501077 | C18: SERI EMEI (SINGAPORE) PTE LTD | D18: USD | E18: 30027308 | F18: 0 | G18: 0 | H18: 911068.12 | I18: -600116.1 | J18: 0 | K18: 0 | L18: 30338260
A19: 501078 | C19: SERI EMPEROR (SINGAPORE) PTE LTD | D19: USD | E19: 29266433 | F19: 0 | G19: 0 | H19: 887990.85 | I19: -581496.79 | J19: 0 | K19: 0 | L19: 29572927
B20: Active (Overseas Projec Fin) | E20: 9.2193794e+08 | F20: 0 | G20: 0 | H20: 28014202 | I20: -10497312 | J20: 0 | K20: 0 | L20: 9.3945483e+08
A22: 500693 | C22: PERUSAHAAN OTOMOBIL NASIONAL (VF) | D22: MYR | E22: 884238.97 | F22: 373789.52 | G22: 0 | H22: 0 | I22: -448532.63 | J22: 0 | K22: 0 | L22: =SUM(E22:K22) -> 809495.86
A23: 500724 | C23: OM MATERIALS (SARAWAK) SDN BHD | D23: USD | E23: 91064746 | F23: 19369912 | G23: 0 | H23: 2370770.8 | I23: -32968618 | J23: 0 | K23: 0 | L23: =SUM(E23:K23) -> 79836811
A24: 500840 | C24: PERTAMA FERROALLOYS SDN BHD | D24: USD | E24: 44918873 | F24: 0 | G24: 0 | H24: 1354613.1 | I24: -24980946 | J24: 0 | K24: 0 | L24: =SUM(E24:K24) -> 21292540
B25: Active (Supplier Credit) (Trade Finance) | E25: =SUM(E22:E24) -> 1.3686786e+08 | F25: =SUM(F22:F24) -> 19743701 | G25: 0 | H25: =SUM(H22:H24) -> 3725383.9 | I25: =SUM(I22:I24) -> -58398097 | J25: 0 | K25: 0 | L25: =SUM(L22:L24) -> 1.0193885e+08
A27: 500400 | C27: THE REPUBLIC OF IRAQ | D27: USD | E27: 1582620.2 | F27: 0 | G27: 0 | H27: 48099.19 | I27: 0 | J27: 0 | K27: 0 | L27: 1630719.4
A28: 500401 | C28: THE REPUBLIC OF SEYCHELLES | D28: USD | E28: 15241920 | F28: 0 | G28: 0 | H28: 459248.4 | I28: -1567158.8 | J28: 0 | K28: 0 | L28: 14134010
A29: 501098 | C29: Sarawak Petchem Sdn Bhd (TL) | D29: USD | E29: 44884213 | F29: 12470012 | G29: 0 | H29: 1366765.3 | I29: 0 | J29: 0 | K29: 0 | L29: 58720990
A30: 501100 | C30: BUMI ARMADA LABUAN LIMITED | D30: USD | E30: 91800000 | F30: 0 | G30: 0 | H30: 2790000 | I30: 0 | J30: 0 | K30: 0 | L30: 94590000
B31: Active (Term Loan) | E31: 1.5350875e+08 | F31: 12470012 | G31: 0 | H31: 4664112.8 | I31: -1567158.8 | J31: 0 | K31: 0 | L31: 1.6907572e+08
A33: 500010 | C33: PT BUMI INTERNATIONAL TANKERS | D33: USD | E33: 12893037 | F33: 0 | G33: 0 | H33: 391847.2 | I33: 0 | J33: 0 | K33: 0 | L33: 13284884
A34: 500011 | C34: PT LAYAR SENTOSA | D34: USD | E34: 13089115 | F34: 0 | G34: 0 | H34: 397806.41 | I34: 0 | J34: 0 | K34: 0 | L34: 13486921
A35: 500039 | C35: PT MAHAKARYA INTI BUANA | D35: USD | E35: 11947770 | F35: 0 | G35: 0 | H35: 363118.49 | I35: 0 | J35: 0 | K35: 0 | L35: 12310888
A36: 500913 | C36: PT SRIWIJAYA AIR | D36: USD | E36: 3.7133704e+08 | F36: 0 | G36: 0 | H36: 11285734 | I36: 0 | J36: 0 | K36: 0 | L36: 3.8262278e+08
B37: Impaired Loan (Buyer Credit) | E37: 4.0926696e+08 | F37: 0 | G37: 0 | H37: 12438506 | I37: 0 | J37: 0 | K37: 0 | L37: 4.2170547e+08
A39: 500577 | C39: NIRMALA VILAS RESTAURANT SDN BHD | D39: MYR | E39: 747562.14 | F39: 0 | G39: 0 | H39: 0 | I39: 0 | J39: 0 | K39: 0 | L39: 747562.14
A40: 500758 | C40: 3 PLUS1 STUDIO SDN BHD 2 | D40: MYR | E40: 975206.98 | F40: 0 | G40: 0 | H40: 0 | I40: 0 | J40: 0 | K40: 0 | L40: 975206.98
A41: 500852 | C41: NEE ASSETS SDN BHD | D41: MYR | E41: 539751.12 | F41: 0 | G41: 0 | H41: 0 | I41: 0 | J41: 0 | K41: 0 | L41: 539751.12
A42: 500866 | C42: NEE ASSETS SDN BHD 1 | D42: MYR | E42: 116666.69 | F42: 0 | G42: 0 | H42: 0 | I42: 0 | J42: 0 | K42: 0 | L42: 116666.69
B43: Impaired Loan (Malaysia Kitchen Fin) | E43: 2379186.9 | F43: 0 | G43: 0 | H43: 0 | I43: 0 | J43: 0 | K43: 0 | L43: 2379186.9
A45: 501045 | C45: SAPURA TMC SDN BHD | D45: USD | E45: 84867032 | F45: 0 | G45: 0 | H45: 2579292.1 | I45: 0 | J45: 0 | K45: 0 | L45: 87446324
B46: Impaired Loan (Overseas Investment) | E46: 84867032 | F46: 0 | G46: 0 | H46: 2579292.1 | I46: 0 | J46: 0 | K46: 0 | L46: 87446324
A48: 500042 | C48: PT EDEN CAPITAL INDONESIA | D48: USD | E48: 13943180 | F48: 0 | G48: 0 | H48: 423763.31 | I48: 0 | J48: 0 | K48: 0 | L48: 14366943
A49: 500522 | C49: VIRTUAL PEAKS GROUP SDN BHD | D49: USD | E49: 7475829.4 | F49: 0 | G49: 0 | H49: 227206.58 | I49: 0 | J49: 0 | K49: 0 | L49: 7703036
A50: 500557 | C50: MARKMORE ENERGY 1 | D50: USD | E50: 1.6073475e+08 | F50: 0 | G50: 0 | H50: 4885075.8 | I50: 0 | J50: 0 | K50: 0 | L50: 1.6561983e+08
A51: 500558 | C51: MARKMORE ENERGY II | D51: USD | E51: 1.8318086e+08 | F51: 0 | G51: 0 | H51: 5567261.3 | I51: 0 | J51: 0 | K51: 0 | L51: 1.8874812e+08
A52: 500883 | C52: UPL LAO CO. LTD 1 | D52: USD | E52: 9800875.1 | F52: 0 | G52: 0 | H52: 297869.72 | I52: 0 | J52: 0 | K52: 0 | L52: 10098745
A53: 500884 | C53: UPL LAO CO. LTD 2 | D53: USD | E53: 17276441 | F53: 0 | G53: 0 | H53: 525068.29 | I53: 0 | J53: 0 | K53: 0 | L53: 17801509
A54: 500885 | C54: SUPERBOOM PROJECTS SDN BHD | D54: USD | E54: 91506001 | F54: 0 | G54: 0 | H54: 2781064.7 | I54: 0 | J54: 0 | K54: 0 | L54: 94287066
A55: 500914 | C55: IMPIANA UBUD (LABUAN) CO. LTD. | D55: USD | E55: 100291500 | F55: 0 | G55: 0 | H55: 3048075 | I55: 0 | J55: 0 | K55: 0 | L55: 103339575
A56: 500980 | C56: VEERAM STONES PVT LTD | D56: USD | E56: 2714466.6 | F56: 0 | G56: 0 | H56: 82498.44 | I56: 0 | J56: 0 | K56: 0 | L56: 2796965.1
B57: Impaired Loan (Overseas Projec Fin) | E57: 5.869239e+08 | F57: 0 | G57: 0 | H57: 17837883 | I57: 0 | J57: 0 | K57: 0 | L57: 6.0476179e+08
A59: 500538 | C59: MIR VALVE SDN BHD | D59: USD | E59: 12880790 | F59: 0 | G59: 0 | H59: 391474.91 | I59: 0 | J59: -33.25 | K59: 0 | L59: =SUM(E59:K59) -> 13272232
B60: Impaired Loan (Supplier Credit) (Trade Finance) | E60: =SUM(E59) -> 12880790 | F60: 0 | G60: 0 | H60: 391474.91 | I60: 0 | J60: =SUM(J59) -> -33.25 | K60: 0 | L60: =SUM(L59) -> 13272232
A62: 501000 | C62: BRAHIM'S OVERSEAS VENTURE SDN BHD | D62: MYR | E62: 15467576 | F62: 0 | G62: 0 | H62: 0 | I62: 0 | J62: 0 | K62: 0 | L62: 15467576
B63: Impaired Loan (Term Loan) | E63: 15467576 | F63: 0 | G63: 0 | H63: 0 | I63: 0 | J63: 0 | K63: 0 | L63: 15467576
A65: 500265 | C65: PT SARI INDAH LESTARI | D65: USD | E65: 82072002 | F65: 0 | G65: 0 | H65: 2494345.1 | I65: 0 | J65: 0 | K65: 0 | L65: =SUM(E65:K65) -> 84566347
A66: 500274 | C66: HONDAAFUSHI INVESTMENT PVT LTD | D66: USD | E66: 40823372 | F66: 0 | G66: 0 | H66: 1240710.3 | I66: 0 | J66: 0 | K66: 0 | L66: =SUM(E66:K66) -> 42064082
A67: 500512 | C67: AL-MANARA WATER COMPANY LIMITED | D67: EUR | E67: 1.0650576e+08 | F67: 0 | G67: 0 | H67: 849646.09 | I67: 0 | J67: 0 | K67: 0 | L67: =SUM(E67:K67) -> 1.0735541e+08
B68: Restuctured (Buyer Credit) | E68: =SUM(E65:E67) -> 2.2940113e+08 | F68: 0 | G68: 0 | H68: =SUM(H65:H67) -> 4584701.5 | I68: 0 | J68: 0 | K68: 0 | L68: =SUM(L65:L67) -> 2.3398584e+08
A70: 500776 | C70: HUMMINGBIRD ENERGY (L) INC (OIF) | D70: USD | E70: 81259249 | F70: 0 | G70: 0 | H70: 2469643.8 | I70: 0 | J70: 0 | K70: 0 | L70: 83728892
B71: Restuctured (Overseas Investment) | E71: 81259249 | F71: 0 | G71: 0 | H71: 2469643.8 | I71: 0 | J71: 0 | K71: 0 | L71: 83728892
A73: 500781 | C73: HUMMINGBIRD ENERGY (L) INC (OPF) | D73: USD | E73: 16983000 | F73: 0 | G73: 0 | H73: 516150 | I73: 0 | J73: 0 | K73: 0 | L73: 17499150
B74: Restuctured (Overseas Projec Fin) | E74: 16983000 | F74: 0 | G74: 0 | H74: 516150 | I74: 0 | J74: 0 | K74: 0 | L74: 17499150
A76: 500555 | C76: SOLARTIF SDN BHD | D76: MYR | E76: 607945.15 | F76: 0 | G76: 0 | H76: 0 | I76: -9938.45 | J76: 0 | K76: 0 | L76: =SUM(E76:K76) -> 598006.7
B77: Restuctured (Supplier Credit) (Trade Finance) | E77: =SUM(E76) -> 607945.15 | F77: 0 | G77: 0 | H77: 0 | I77: =SUM(I76) -> -9938.45 | J77: 0 | K77: 0 | L77: =SUM(L76) -> 598006.7
E79: =E77+E68+E63+E60+E57+E46+E43+E37+E31+E25+E20+E9+E6+E74+E71 -> 3.0194117e+09 | F79: =F77+F68+F63+F60+F57+F46+F43+F37+F31+F25+F20+F9+F6+F74+F71 -> 32213713 | G79: =G77+G68+G63+G60+G57+G46+G43+G37+G31+G25+G20+G9+G6+G74+G71 -> 0 | H79: =H77+H68+H63+H60+H57+H46+H43+H37+H31+H25+H20+H9+H6+H74+H71 -> 85190850 | I79: =I77+I68+I63+I60+I57+I46+I43+I37+I31+I25+I20+I9+I6+I74+I71 -> -70472506 | J79: =J77+J68+J63+J60+J57+J46+J43+J37+J31+J25+J20+J9+J6+J74+J71 -> -33.25 | K79: =K77+K68+K63+K60+K57+K46+K43+K37+K31+K25+K20+K9+K6+K74+K71 -> 0 | L79: =L77+L68+L63+L60+L57+L46+L43+L37+L31+L25+L20+L9+L6+L74+L71 -> 3.0663438e+09

Sheet FS Feb 2022

Sheet Debtors Listing (C) Nov2020
A1: Customer Balances as at November 2020
A3: Customer Account Number | B3: Customer Class & Industry | C3: Customer Name | D3: Loan Currency | E3: Opening Principal | F3: Disbursement | G3: Adjustment Capitalization | H3: Forex ( + ) | I3: Repayment | J3: Adjustment Capitalization | K3: Forex ( - ) | L3: Closing Principal
A5: 500470 | C5: MINISTRY OF FINANCE - LAO PDR | D5: USD | E5: 87763812 | F5: 0 | G5: 0 | H5: 0 | I5: 0 | J5: 0 | K5: -1679437.5 | L5: 86084375
A6: 500937 | C6: MINISTRY OF FINANCE LAOS 2 | D6: USD | E6: 2.4977166e+08 | F6: 18880062 | G6: 0 | H6: 0 | I6: 0 | J6: 0 | K6: -5042298.8 | L6: 2.6360943e+08
B7: Active (Cross Border Credit) (Buyer Credit) | E7: 3.3753547e+08 | F7: 18880062 | G7: 0 | H7: 0 | I7: 0 | J7: 0 | K7: -6721736.3 | L7: 3.496938e+08
A9: 500878 | C9: WOK DELIGHTS SDN BHD | D9: MYR | E9: 1195048.9 | F9: 0 | G9: 0 | H9: 0 | I9: -66391.6 | J9: 0 | K9: 0 | L9: 1128657.3
B10: Active (Malaysia Kitchen Fin) | E10: 1195048.9 | F10: 0 | G10: 0 | H10: 0 | I10: -66391.6 | J10: 0 | K10: 0 | L10: 1128657.3
A12: 500629 | C12: FACADE TREATMENT (Term Loan)CBC | D12: MYR | E12: 1118253.9 | F12: 0 | G12: 0 | H12: 0 | I12: -95556.64 | J12: 0 | K12: 0 | L12: 1022697.2
B13: Active (Overseas Contract Fi) (Term Loan) | E13: 1118253.9 | F13: 0 | G13: 0 | H13: 0 | I13: -95556.64 | J13: 0 | K13: 0 | L13: 1022697.2
A15: 500679 | C15: BUMI ARMADA CAPITAL OFFSHORE LTD | D15: USD | E15: 2.0265414e+08 | F15: 0 | G15: 0 | H15: 0 | I15: -290212.79 | J15: 0 | K15: -3876864.9 | L15: 1.9848706e+08
A16: 500708 | C16: SAPURAKENCANA TMC SDN BHD (1) | D16: USD | E16: 15244632 | F16: 0 | G16: 0 | H16: 0 | I16: 0 | J16: 0 | K16: -291719.43 | L16: 14952913
A17: 500709 | C17: SAPURAKENCANA TMC SDN BHD (2) | D17: USD | E17: 61682670 | F17: 0 | G17: 0 | H17: 0 | I17: 0 | J17: 0 | K17: -1180352 | L17: 60502318
A18: 500749 | C18: ISTANBUL SABIHA GOKCEN ULUSLARARASI | D18: EUR | E18: 186644150 | F18: 0 | G18: 0 | H18: 1282050 | I18: 0 | J18: 0 | K18: 0 | L18: 187926200
B19: Active (Overseas Investment) | E19: 4.6622559e+08 | F19: 0 | G19: 0 | H19: 1282050 | I19: -290212.79 | J19: 0 | K19: -5348936.3 | L19: 4.6186849e+08
A21: 500271 | C21: MBI Development D.O.O, Bosnia&Herze | D21: EUR | E21: 4906248.4 | F21: 0 | G21: 0 | H21: 33700.84 | I21: 0 | J21: 0 | K21: 0 | L21: 4939949.2
A22: 500590 | C22: MBI Development 2 | D22: EUR | E22: 5812039.9 | F22: 0 | G22: 0 | H22: 39922.65 | I22: 0 | J22: 0 | K22: 0 | L22: 5851962.6
A23: 500640 | C23: OM MATERIAL (SARAWAK) SDN BHD | D23: USD | E23: 1.2011245e+08 | F23: 0 | G23: 0 | H23: 0 | I23: 0 | J23: 0 | K23: -2298457.1 | L23: 1.17814e+08
A24: 500642 | C24: OM MATERIAL (SARAWAK) 2 | D24: USD | E24: 1.6285676e+08 | F24: 0 | G24: 0 | H24: 0 | I24: 0 | J24: 0 | K24: -3116406.8 | L24: 1.5974035e+08
A25: 500805 | C25: Armada Kraken Pte Ltd (OPF) | D25: USD | E25: 1.3147652e+08 | F25: 0 | G25: 0 | H25: 0 | I25: 0 | J25: 0 | K25: -2515918.5 | L25: 1.289606e+08
A26: 500807 | C26: Pertama Ferroalloys Sdn Bhd (2) | D26: USD | E26: 74609543 | F26: 0 | G26: 0 | H26: 0 | I26: 0 | J26: 0 | K26: -1427719 | L26: 73181824
A27: 500808 | C27: Pertama Ferroalloys Sdn Bhd (1) | D27: USD | E27: 46006709 | F27: 0 | G27: 0 | H27: 0 | I27: 0 | J27: 0 | K27: -880378.72 | L27: 45126331
A28: 500827 | C28: Pertama Ferroalloys Sdn Bhd (3) | D28: USD | E28: 1.0100638e+08 | F28: 0 | G28: 0 | H28: 0 | I28: 0 | J28: 0 | K28: -1932845.6 | L28: 99073530
A29: 500885 | C29: SUPERBOOM PROJECTS SDN BHD | D29: USD | E29: 82823896 | F29: 0 | G29: 0 | H29: 0 | I29: 0 | J29: 0 | K29: -1584907.9 | L29: 81238988
A30: 500905 | C30: ZICO HOLDINGS INC (OPF) | D30: SGD | E30: 2468116.2 | F30: 0 | G30: 0 | H30: 3787.29 | I30: -124111.39 | J30: 0 | K30: 0 | L30: 2347792.1
A31: 500914 | C31: IMPIANA UBUD (LABUAN) CO. LTD. | D31: USD | E31: 90775825 | F31: 0 | G31: 0 | H31: 0 | I31: 0 | J31: 0 | K31: -1737075 | L31: 89038750
A32: 500927 | C32: BRITISH UNIVERSITY VIETNAM | D32: USD | E32: 78180915 | F32: 0 | G32: 0 | H32: 0 | I32: 0 | J32: 0 | K32: -1496060.3 | L32: 76684854
A33: 501031 | C33: YINSON BORONIA PRODUCTION BV | D33: USD | E33: 0 | F33: 19890123 | G33: 0 | H33: 24435.04 | I33: 0 | J33: 0 | K33: 0 | L33: 19914558
B34: Active (Overseas Projec Fin) | E34: 9.010354e+08 | F34: 19890123 | G34: 0 | H34: 101845.82 | I34: -124111.39 | J34: 0 | K34: -16989769 | L34: 9.0391349e+08
A36: 500538 | C36: MIR VALVE SDN BHD | D36: USD | E36: 11491657 | F36: 1925466.8 | G36: 2.91 | H36: 0 | I36: -261316.26 | J36: 0 | K36: -235354.63 | L36: 12920455
A37: 500693 | C37: PERUSAHAAN OTOMOBIL NASIONAL (VF) | D37: MYR | E37: 10699919 | F37: 4406387.5 | G37: 0 | H37: 0 | I37: -5425782.7 | J37: 0 | K37: 0 | L37: 9680523.9
A38: 500724 | C38: OM Material (Sarawak) Sdn Bhd | D38: USD | E38: 66417050 | F38: 26089648 | G38: 0 | H38: 0 | I38: -16624375 | J38: 0 | K38: -1475148.2 | L38: 74407175
A39: 500840 | C39: Pertama Ferroalloys (Trade) | D39: USD | E39: 26587288 | F39: 0 | G39: 0 | H39: 0 | I39: -9177981.3 | J39: 0 | K39: -374502.45 | L39: 17034805
B40: Active (Supplier Credit) (Trade Finance) | E40: =SUM(E36:E39) -> 1.1519591e+08 | F40: 32421503 | G40: 2.91 | H40: 0 | I40: -31489455 | J40: 0 | K40: -2085005.2 | L40: =SUM(L36:L39) -> 1.1404296e+08
A42: 501000 | C42: Brahim's Overseas Venture Sdn Bhd | D42: MYR | E42: 15467576 | F42: 0 | G42: 0 | H42: 0 | I42: 0 | J42: 0 | K42: 0 | L42: 15467576
B43: Active (Term Loan) | E43: 15467576 | F43: 0 | G43: 0 | H43: 0 | I43: 0 | J43: 0 | K43: 0 | L43: 15467576
A45: 500010 | C45: PT BUMI INTERNATIONAL TANKERS | D45: USD | E45: 11669743 | F45: 0 | G45: 0 | H45: 0 | I45: 0 | J45: 0 | K45: -223310.75 | L45: 11446432
A46: 500011 | C46: PT LAYAR SENTOSA | D46: USD | E46: 11847217 | F46: 0 | G46: 0 | H46: 0 | I46: 0 | J46: 0 | K46: -226706.87 | L46: 11620510
A47: 500042 | C47: PT EDEN CAPITAL INDONESIA | D47: USD | E47: 12629069 | F47: 0 | G47: 0 | H47: 0 | I47: 0 | J47: -8820 | K47: -241499.52 | L47: 12378749
A48: 500265 | C48: PT SARI INDAH LESTARI | D48: USD | E48: 74284996 | F48: 0 | G48: 0 | H48: 0 | I48: 0 | J48: 0 | K48: -1421508.6 | L48: 72863488
A49: 500274 | C49: HONDAAFUSHI INVESTMENT PVT LTD | D49: USD | E49: 36950043 | F49: 0 | G49: 0 | H49: 0 | I49: 0 | J49: 0 | K49: -707071.48 | L49: 36242972
A50: 500913 | C50: PT SRIWIJAYA AIR | D50: USD | E50: 3.3610452e+08 | F50: 0 | G50: 0 | H50: 0 | I50: 0 | J50: 0 | K50: -6431654.7 | L50: 3.2967287e+08
B51: Impaired Loan (Buyer Credit) | E51: 4.8348559e+08 | F51: 0 | G51: 0 | H51: 0 | I51: 0 | J51: -8820 | K51: -9251751.8 | L51: 4.7422502e+08
A53: 500206 | C53: BESTEEL BERHAD | D53: USD | E53: 5851098.7 | F53: 0 | G53: 0 | H53: 0 | I53: 0 | J53: 0 | K53: -111965.91 | L53: 5739132.8
B54: Impaired Loan (Cross Border Credit) (Term Loan) | E54: 5851098.7 | F54: 0 | G54: 0 | H54: 0 | I54: 0 | J54: 0 | K54: -111965.91 | L54: 5739132.8
A56: 500546 | C56: FRESH BOWL FOODS LIMITED | D56: MYR | E56: 398103.51 | F56: 0 | G56: 0 | H56: 0 | I56: -3625.9 | J56: 0 | K56: 0 | L56: 394477.61
A57: 500560 | C57: PANNAH RESOURCES 1 | D57: MYR | E57: 713800 | F57: 0 | G57: 0 | H57: 0 | I57: -2000 | J57: 0 | K57: 0 | L57: 711800
A58: 500577 | C58: NIRMALA VILAS RESTAURANT SDN BHD | D58: MYR | E58: 747562.14 | F58: 0 | G58: 0 | H58: 0 | I58: 0 | J58: 0 | K58: 0 | L58: 747562.14
A59: 500644 | C59: GOLD RAIN RESOURCES | D59: MYR | E59: 1067187.6 | F59: 0 | G59: 0 | H59: 0 | I59: 0 | J59: 0 | K59: 0 | L59: 1067187.6
A60: 500758 | C60: 3 PLUS1 STUDIO SDN BHD 2 | D60: MYR | E60: 975206.98 | F60: 0 | G60: 0 | H60: 0 | I60: 0 | J60: 0 | K60: 0 | L60: 975206.98
A61: 500806 | C61: I & C EATING NETWORK INTERNATIONAL | D61: MYR | E61: 988584.59 | F61: 0 | G61: 0 | H61: 0 | I61: 0 | J61: 0 | K61: 0 | L61: 988584.59
A62: 500852 | C62: NEE ASSETS SDN BHD | D62: MYR | E62: 539751.12 | F62: 0 | G62: 0 | H62: 0 | I62: 0 | J62: 0 | K62: 0 | L62: 539751.12
A63: 500866 | C63: NEE ASSETS SDN BHD 1 | D63: MYR | E63: 116666.69 | F63: 0 | G63: 0 | H63: 0 | I63: 0 | J63: 0 | K63: 0 | L63: 116666.69
B64: Impaired Loan (Malaysia Kitchen Fin) | E64: 5546862.6 | F64: 0 | G64: 0 | H64: 0 | I64: -5625.9 | J64: 0 | K64: 0 | L64: 5541236.7
A66: 500515 | C66: SCOMI TRANSIT PROJECTS BRAZIL | D66: USD | E66: 34038541 | F66: 0 | G66: 0 | H66: 0 | I66: 0 | J66: 0 | K66: -651357.3 | L66: 33387184
B67: Impaired Loan (Overseas Contract Fi) | E67: 34038541 | F67: 0 | G67: 0 | H67: 0 | I67: 0 | J67: 0 | K67: -651357.3 | L67: 33387184
A69: 500776 | C69: HUMMINGBIRD ENERGY (L) INC (OIF) | D69: USD | E69: 73549357 | F69: 0 | G69: 0 | H69: 0 | I69: 0 | J69: 0 | K69: -1407431.4 | L69: 72141926
A70: 500980 | C70: VEERAM STONES PVT LTD | D70: USD | E70: 2648493.7 | F70: 0 | G70: 0 | H70: 0 | I70: 0 | J70: 0 | K70: -50681.22 | L70: 2597812.5
B71: Impaired Loan (Overseas Investment) | E71: 76197851 | F71: 0 | G71: 0 | H71: 0 | I71: 0 | J71: 0 | K71: -1458112.6 | L71: 74739738
A73: 500297 | C73: PHOENIX SURGE SDN BHD (111) | D73: USD | E73: 3920836 | F73: 0 | G73: 0 | H73: 0 | I73: 0 | J73: 0 | K73: -75044.92 | L73: 3845791
A74: 500522 | C74: VIRTUAL PEAKS GROUP SDN BHD | D74: USD | E74: 6766521.4 | F74: 0 | G74: 0 | H74: 0 | I74: 0 | J74: 0 | K74: -129483.32 | L74: 6637038.1
A75: 500557 | C75: MARKMORE ENERGY 1 | D75: USD | E75: 1.4548421e+08 | F75: 0 | G75: 0 | H75: 0 | I75: 0 | J75: 0 | K75: -2783968 | L75: 1.4270024e+08
A76: 500558 | C76: MARKMORE ENERGY II | D76: USD | E76: 1.6580063e+08 | F76: 0 | G76: 0 | H76: 0 | I76: 0 | J76: 0 | K76: -3172740.3 | L76: 1.6262789e+08
A77: 500576 | C77: ILEAVES (UK) LTD | D77: GBP | E77: 3155043 | F77: 0 | G77: 0 | H77: 36597.06 | I77: 0 | J77: 0 | K77: 0 | L77: 3191640
A78: 500631 | C78: MALAYSIAN DELICACIES PTY LTD | D78: AUD | E78: 574149.32 | F78: 0 | G78: 0 | H78: 16387.98 | I78: 0 | J78: 0 | K78: 0 | L78: 590537.3
A79: 500746 | C79: PACIFICLIGHT POWER PTE LTD 2 | D79: SGD | E79: 3.1980735e+08 | F79: 0 | G79: 48535011 | H79: 0 | I79: -1.6017165e+08 | J79: -1.6017165e+08 | K79: -47999074 | L79: 0
A80: 500781 | C80: HUMMINGBIRD ENERGY (L) INC (OPF) | D80: USD | E80: 15371650 | F80: 0 | G80: 0 | H80: 0 | I80: 0 | J80: 0 | K80: -294150 | L80: 15077500
A81: 500883 | C81: UPL LAO CO. LTD 1 | D81: USD | E81: 8870966.3 | F81: 0 | G81: 0 | H81: 0 | I81: 0 | J81: 0 | K81: -169753.75 | L81: 8701212.6
A82: 500884 | C82: UPL LAO CO. LTD 2 | D82: USD | E82: 15637249 | F82: 0 | G82: 0 | H82: 0 | I82: 0 | J82: 0 | K82: -299232.46 | L82: 15338016
B83: Impaired Loan (Overseas Projec Fin) | E83: 6.8538861e+08 | F83: 0 | G83: 48535011 | H83: 52985.04 | I83: -1.6017165e+08 | J83: -1.6017165e+08 | K83: -54923447 | L83: 3.5870986e+08
A85: 500187 | C85: JEWEL GROWTH SDN BHD | D85: MYR | E85: 26832.06 | F85: 0 | G85: 0 | H85: 0 | I85: 0 | J85: 0 | K85: 0 | L85: 26832.06
A86: 500197 | C86: VEHENG GLOBAL TRADERS SDN BHD | D86: MYR | E86: 8200000 | F86: 0 | G86: 0 | H86: 0 | I86: 0 | J86: 0 | K86: 0 | L86: 8200000
A87: 500716 | C87: HOT-CAN SDN BHD | D87: USD | E87: 888345.26 | F87: 0 | G87: 0 | H87: 0 | I87: 0 | J87: 0 | K87: -16999.25 | L87: 871346.01
A88: 500768 | C88: UIL MALAYSIA LTD | D88: USD | E88: 1.0408329e+08 | F88: 0 | G88: 0 | H88: 0 | I88: -12210000 | J88: 0 | K88: -2006724.7 | L88: 89866561
B89: Impaired Loan (Supplier Credit) (Trade Finance) | E89: 1.1319846e+08 | F89: 0 | G89: 0 | H89: 0 | I89: -12210000 | J89: 0 | K89: -2023724 | L89: 98964739
A91: 500962 | C91: Scomi Transit Projects Brazil | E91: 40515000 | F91: 0 | G91: 0 | H91: 0 | I91: 0 | J91: 0 | K91: 0 | L91: 40515000
B92: Impaired Loan (Term Loan) | E92: 40515000 | F92: 0 | G92: 0 | H92: 0 | I92: 0 | J92: 0 | K92: 0 | L92: 40515000
A94: 500039 | C94: PT MAHAKARYA INTI BUANA | D94: USD | E94: 11789651 | F94: 0 | G94: 0 | H94: 0 | I94: 0 | J94: 0 | K94: -225605.31 | L94: 11564046
A95: 500613 | C95: HARTAMANIS (S) PTE LTD (TL2) | D95: MYR | E95: 7458382.5 | F95: 0 | G95: 0 | H95: 0 | I95: 0 | J95: 0 | K95: 0 | L95: 7458382.5
B96: Restuctured | E96: 19248034 | F96: 0 | G96: 0 | H96: 0 | I96: 0 | J96: 0 | K96: -225605.31 | L96: 19022429
A98: 500512 | C98: AL-MANARA WATER COMPANY LIMITED | D98: EUR | E98: 1.0198293e+08 | F98: 0 | G98: 0 | H98: 700515.92 | I98: 0 | J98: 0 | K98: 0 | L98: 1.0268344e+08
B99: Restuctured (Buyer Credit) | E99: 1.0198293e+08 | F99: 0 | G99: 0 | H99: 700515.92 | I99: 0 | J99: 0 | K99: 0 | L99: 1.0268344e+08
A101: 500555 | C101: SOLARTIF SDN BHD | D101: MYR | E101: 781992.08 | F101: 0 | G101: 0 | H101: 0 | I101: -61256.05 | J101: 0 | K101: 0 | L101: 720736.03
B102: Restuctured (Supplier Credit) (Trade Finance) | E102: 781992.08 | F102: 0 | G102: 0 | H102: 0 | I102: -61256.05 | J102: 0 | K102: 0 | L102: 720736.03
A104: 500400 | C104: THE REPUBLIC OF IRAQ | D104: USD | E104: 2387476.2 | F104: 0 | G104: 0 | H104: 0 | I104: 0 | J104: 0 | K104: -45686.43 | L104: 2341789.8
A105: 500401 | C105: THE REPUBLIC OF SEYCHELLES | D105: USD | E105: 20101767 | F105: 0 | G105: 0 | H105: 0 | I105: 0 | J105: 0 | K105: -384664.95 | L105: 19717102
B106: Restuctured (Term Loan) | E106: 22489244 | F106: 0 | G106: 0 | H106: 0 | I106: 0 | J106: 0 | K106: -430351.38 | L106: 22058892
E109: =E106+E102+E99+E96+E92+E89+E83+E71+E67+E64+E54+E51+E43+E40+E34+E19+E13+E10+E7 -> 3.4264975e+09 | F109: 71191688 | G109: 48535014 | H109: 2137396.8 | I109: -2.0451426e+08 | J109: -1.6018047e+08 | K109: -1.0022176e+08 | L109: =L106+L102+L99+L96+L92+L89+L83+L71+L67+L64+L54+L51+L43+L40+L34+L19+L13+L10+L7 -> 3.0834451e+09

Sheet Principal Nov2020
A1: EXIM Bank of Malaysia Customer Balances in Local Currency Time 17:47:12 Date 02.12.2020
A2: Kuala Lumpur RFDSLD00/EIDIL Page 1
A3: Carryforwd Perio 01 - 10 2020 Reporting Period 11 - 11 2020
D5: CoCd | F5: Reconciliation acct | I5: Customer | J5: SearchTerm | K5: SGL Ind. | L5: Crcy | N5: Balance Carryforward | P5: Debit rept.period | Q5: Credit report per. | R5: Accumulated balance
D7: EXIM | F7: 138901 | I7: 500010 | J7: PT BUMI | L7: MYR | N7: 9502406.7 | P7: 0 | Q7: 0 | R7: 9502406.7
D8: EXIM | F8: 138901 | I8: 500010 | J8: PT BUMI | K8: N | L8: MYR | N8: 2167336.4 | P8: 10774270 | Q8: 10997580 | R8: 1944025.6
D9: EXIM | F9: 138901 | I9: 500011 | J9: PTLAYAR | L9: MYR | N9: 9722052.6 | P9: 0 | Q9: 0 | R9: 9722052.6
D10: EXIM | F10: 138901 | I10: 500011 | J10: PTLAYAR | K10: N | L10: MYR | N10: 2125164.5 | P10: 10867255 | Q10: 11093962 | R10: 1898457.6
D11: EXIM | F11: 138901 | I11: 500039 | J11: PTMAHAKARY | L11: MYR | N11: -11346186 | P11: 0 | Q11: 0 | R11: -11346186
D12: EXIM | F12: 138901 | I12: 500039 | J12: PTMAHAKARY | K12: N | L12: MYR | N12: 23135838 | P12: 32217914 | Q12: 32443519 | R12: 22910233
D13: EXIM | F13: 138901 | I13: 500042 | J13: PTEDEN | L13: MYR | N13: 10149768 | P13: 0 | Q13: 8820 | R13: 10140948
D14: EXIM | F14: 138901 | I14: 500042 | J14: PTEDEN | K14: N | L14: MYR | N14: 2479301 | P14: 2279912.8 | Q14: 2521412.3 | R14: 2237801.5
D15: EXIM | F15: 138901 | I15: 500187 | J15: JEWEL | L15: MYR | N15: 26832.06 | P15: 0 | Q15: 0 | R15: 26832.06
D16: EXIM | F16: 138901 | I16: 500197 | J16: VEHENG | L16: MYR | N16: 8200000 | P16: 0 | Q16: 0 | R16: 8200000
D17: EXIM | F17: 138901 | I17: 500206 | J17: BESTEEL | L17: MYR | N17: -2887257 | P17: 0 | Q17: 0 | R17: -2887257
D18: EXIM | F18: 138901 | I18: 500206 | J18: BESTEEL | K18: N | L18: MYR | N18: 8738355.6 | P18: 12226888 | Q18: 12338854 | R18: 8626389.7
D19: EXIM | F19: 138901 | I19: 500265 | J19: PTSARI | L19: MYR | N19: 61312933 | P19: 0 | Q19: 0 | R19: 61312933
D20: EXIM | F20: 138901 | I20: 500265 | J20: PTSARI | K20: N | L20: MYR | N20: 12972063 | P20: 22200738 | Q20: 23622246 | R20: 11550555
D21: EXIM | F21: 138901 | I21: 500271 | J21: MBI | L21: MYR | N21: 4970461.6 | P21: 0 | Q21: 0 | R21: 4970461.6
D22: EXIM | F22: 138901 | I22: 500271 | J22: MBI | K22: N | L22: MYR | N22: -64213.2 | P22: 4979599.2 | Q22: 4945898.4 | R22: -30512.36
D23: EXIM | F23: 138901 | I23: 500274 | J23: HONDAAFUSH | L23: MYR | N23: 27577487 | P23: 0 | Q23: 0 | R23: 27577487
D24: EXIM | F24: 138901 | I24: 500274 | J24: HONDAAFUSH | K24: N | L24: MYR | N24: 9372556.8 | P24: 8847570.3 | Q24: 9554641.8 | R24: 8665485.3
D25: EXIM | F25: 138901 | I25: 500297 | J25: PHOENIX111 | L25: MYR | N25: 3069452.3 | P25: 0 | Q25: 0 | R25: 3069452.3
D26: EXIM | F26: 138901 | I26: 500297 | J26: PHOENIX111 | K26: N | L26: MYR | N26: 851383.63 | P26: 8320657.9 | Q26: 8395702.8 | R26: 776338.71
D27: EXIM | F27: 138901 | I27: 500400 | J27: IRAQ | L27: MYR | N27: 1690251.4 | P27: 0 | Q27: 0 | R27: 1690251.4
D28: EXIM | F28: 138901 | I28: 500400 | J28: IRAQ | K28: N | L28: MYR | N28: 697224.8 | P28: 1237194.3 | Q28: 1282880.7 | R28: 651538.37
D29: EXIM | F29: 138901 | I29: 500401 | J29: SEYCHELLES | L29: MYR | N29: 15268958 | P29: 0 | Q29: 0 | R29: 15268958
D30: EXIM | F30: 138901 | I30: 500401 | J30: SEYCHELLES | K30: N | L30: MYR | N30: 4832809.2 | P30: 4984887.8 | Q30: 5369552.7 | R30: 4448144.2
D31: EXIM | F31: 138901 | I31: 500470 | J31: MOF LAO | L31: MYR | N31: 24792892 | P31: 0 | Q31: 0 | R31: 24792892
D32: EXIM | F32: 138901 | I32: 500470 | J32: MOF LAO | K32: N | L32: MYR | N32: 62970920 | P32: 76239833 | Q32: 77919270 | R32: 61291483
D33: EXIM | F33: 138901 | I33: 500512 | J33: AL-MANARA | L33: MYR | N33: 88715176 | P33: 0 | Q33: 0 | R33: 88715176
D34: EXIM | F34: 138901 | I34: 500512 | J34: AL-MANARA | K34: N | L34: MYR | N34: 13267749 | P34: 14969300 | Q34: 14268784 | R34: 13968265
D35: EXIM | F35: 138901 | I35: 500515 | J35: SCOMI | L35: MYR | N35: 27628532 | P35: 0 | Q35: 0 | R35: 27628532
D36: EXIM | F36: 138901 | I36: 500515 | J36: SCOMI | K36: N | L36: MYR | N36: 6410009.3 | P36: 9057910.3 | Q36: 9709267.6 | R36: 5758652
D37: EXIM | F37: 138901 | I37: 500522 | J37: VIRTUAL | L37: MYR | N37: -1055236.6 | P37: 0 | Q37: 0 | R37: -1055236.6
D38: EXIM | F38: 138901 | I38: 500522 | J38: VIRTUAL | K38: N | L38: MYR | N38: 7821758 | P38: 7692274.7 | Q38: 7821758 | R38: 7692274.7
D39: EXIM | F39: 138901 | I39: 500538 | J39: MIR | L39: MYR | N39: 9999973.8 | P39: 1925469.7 | Q39: 261316.26 | R39: 11664127
D40: EXIM | F40: 138901 | I40: 500538 | J40: MIR | K40: N | L40: MYR | N40: 1491682.8 | P40: 22724452 | Q40: 22959806 | R40: 1256328.2
D41: EXIM | F41: 138901 | I41: 500546 | J41: FRESH | L41: MYR | N41: 398103.51 | P41: 0 | Q41: 3625.9 | R41: 394477.61
D42: EXIM | F42: 138901 | I42: 500555 | J42: SOLARTIF | L42: MYR | N42: 781992.08 | P42: 0 | Q42: 61256.05 | R42: 720736.03
D43: EXIM | F43: 138901 | I43: 500557 | J43: MARKMORE | L43: MYR | N43: 1.1075163e+08 | P43: 0 | Q43: 0 | R43: 1.1075163e+08
D44: EXIM | F44: 138901 | I44: 500557 | J44: MARKMORE | K44: N | L44: MYR | N44: 34732583 | P44: 35128856 | Q44: 37912824 | R44: 31948615
D45: EXIM | F45: 138901 | I45: 500558 | J45: MARKMORE | L45: MYR | N45: 1.2156799e+08 | P45: 0 | Q45: 0 | R45: 1.2156799e+08
D46: EXIM | F46: 138901 | I46: 500558 | J46: MARKMORE | K46: N | L46: MYR | N46: 44232636 | P46: 45914940 | Q46: 49087681 | R46: 41059896
D47: EXIM | F47: 138901 | I47: 500560 | J47: PANNAH | L47: MYR | N47: 713800 | P47: 0 | Q47: 2000 | R47: 711800
D48: EXIM | F48: 138901 | I48: 500576 | J48: ILEAVES | L48: MYR | N48: 2799524 | P48: 0 | Q48: 0 | R48: 2799524
D49: EXIM | F49: 138901 | I49: 500576 | J49: ILEAVES | K49: N | L49: MYR | N49: 355518.98 | P49: 425283.09 | Q49: 388686.03 | R49: 392116.04
D50: EXIM | F50: 138901 | I50: 500577 | J50: NIRMALA | L50: MYR | N50: 747562.14 | P50: 0 | Q50: 0 | R50: 747562.14
D51: EXIM | F51: 138901 | I51: 500590 | J51: MBI2 | L51: MYR | N51: 4765370.5 | P51: 0 | Q51: 0 | R51: 4765370.5
D52: EXIM | F52: 138901 | I52: 500590 | J52: MBI2 | K52: N | L52: MYR | N52: 1046669.4 | P52: 1086592.1 | Q52: 1046669.4 | R52: 1086592.1
D53: EXIM | F53: 138901 | I53: 500613 | J53: HARTAMANIS | L53: MYR | N53: 7458382.5 | P53: 0 | Q53: 0 | R53: 7458382.5
D54: EXIM | F54: 138901 | I54: 500629 | J54: FACADE(TL) | L54: MYR | N54: 1118253.9 | P54: 0 | Q54: 95556.64 | R54: 1022697.2
D55: EXIM | F55: 138901 | I55: 500631 | J55: MALAYSIAND | L55: MYR | N55: 574171.62 | P55: 0 | Q55: 0 | R55: 574171.62
D56: EXIM | F56: 138901 | I56: 500631 | J56: MALAYSIAND | K56: N | L56: MYR | N56: -22.3 | P56: 16680 | Q56: 292.02 | R56: 16365.68
D57: EXIM | F57: 138901 | I57: 500640 | J57: OM MATERIA | L57: MYR | N57: 87503028 | P57: 0 | Q57: 0 | R57: 87503028
D58: EXIM | F58: 138901 | I58: 500640 | J58: OM MATERIA | K58: N | L58: MYR | N58: 32609426 | P58: 32276388 | Q58: 34574845 | R58: 30310968
D59: EXIM | F59: 138901 | I59: 500642 | J59: OM MATERIA | L59: MYR | N59: 1.197046e+08 | P59: 0 | Q59: 0 | R59: 1.197046e+08
D60: EXIM | F60: 138901 | I60: 500642 | J60: OM MATERIA | K60: N | L60: MYR | N60: 43152161 | P60: 40777003 | Q60: 43893410 | R60: 40035754
D61: EXIM | F61: 138901 | I61: 500644 | J61: GOLD RAIN | L61: MYR | N61: 1067187.6 | P61: 0 | Q61: 0 | R61: 1067187.6
D62: EXIM | F62: 138901 | I62: 500679 | J62: BUMI ARMAD | L62: MYR | N62: 1.3695886e+08 | P62: 0 | Q62: 290212.79 | R62: 1.3666865e+08
D63: EXIM | F63: 138901 | I63: 500679 | J63: BUMI ARMAD | K63: N | L63: MYR | N63: 65695274 | P63: 61823369 | Q63: 65700234 | R63: 61818409
D64: EXIM | F64: 138901 | I64: 500693 | J64: PROTON (VF | L64: MYR | N64: 10699919 | P64: 4406387.5 | Q64: 5425782.7 | R64: 9680523.9
D65: EXIM | F65: 138901 | I65: 500708 | J65: SAPURAKENC | L65: MYR | N65: -22705134 | P65: 0 | Q65: 0 | R65: -22705134
D66: EXIM | F66: 138901 | I66: 500708 | J66: SAPURAKENC | K66: N | L66: MYR | N66: 37949766 | P66: 40411402 | Q66: 40703121 | R66: 37658047
D67: EXIM | F67: 138901 | I67: 500709 | J67: SAPURAKENC | L67: MYR | N67: -88829270 | P67: 0 | Q67: 0 | R67: -88829270
D68: EXIM | F68: 138901 | I68: 500709 | J68: SAPURAKENC | K68: N | L68: MYR | N68: 1.5051194e+08 | P68: 1.6047218e+08 | Q68: 1.6165254e+08 | R68: 1.4933159e+08
D69: EXIM | F69: 138901 | I69: 500716 | J69: HOT-CAN | L69: MYR | N69: 639412.21 | P69: 0 | Q69: 0 | R69: 639412.21
D70: EXIM | F70: 138901 | I70: 500716 | J70: HOT-CAN | K70: N | L70: MYR | N70: 248933.05 | P70: 343739.11 | Q70: 360738.36 | R70: 231933.8
D71: EXIM | F71: 138901 | I71: 500724 | J71: OM MATERIA | L71: MYR | N71: 65071667 | P71: 26089648 | Q71: 16624375 | R71: 74536940
D72: EXIM | F72: 138901 | I72: 500724 | J72: OM MATERIA | K72: N | L72: MYR | N72: 1345383.2 | P72: 58301100 | Q72: 59776248 | R72: -129764.91
D73: EXIM | F73: 138901 | I73: 500746 | J73: PACIFICLIG | L73: MYR | N73: 2.7180828e+08 | P73: 3.2034329e+08 | Q73: 5.9215157e+08 | R73: 0
D74: EXIM | F74: 138901 | I74: 500746 | J74: PACIFICLIG | K74: N | L74: MYR | N74: 47999074 | P74: 77554.28 | Q74: 48076629 | R74: 0
D75: EXIM | F75: 138901 | I75: 500749 | J75: ISTANBUL S | L75: MYR | N75: 150936750 | P75: 0 | Q75: 0 | R75: 150936750
D76: EXIM | F76: 138901 | I76: 500749 | J76: ISTANBUL S | K76: N | L76: MYR | N76: 35707400 | P76: 155850450 | Q76: 154568400 | R76: 36989450
D77: EXIM | F77: 138901 | I77: 500758 | J77: 3 PLUS1 ST | L77: MYR | N77: 975206.98 | P77: 0 | Q77: 0 | R77: 975206.98
D78: EXIM | F78: 138901 | I78: 500768 | J78: UIL MALAYS | L78: MYR | N78: 89190621 | P78: 0 | Q78: 12210000 | R78: 76980621
D79: EXIM | F79: 138901 | I79: 500768 | J79: UIL MALAYS | K79: N | L79: MYR | N79: 14892664 | P79: 1.2090163e+08 | Q79: 1.2290835e+08 | R79: 12885939
D80: EXIM | F80: 138901 | I80: 500776 | J80: HUMMINGBIR | L80: MYR | N80: 49937648 | P80: 0 | Q80: 0 | R80: 49937648
D81: EXIM | F81: 138901 | I81: 500776 | J81: HUMMINGBIR | K81: N | L81: MYR | N81: 23611709 | P81: 25127245 | Q81: 26534676 | R81: 22204278
D82: EXIM | F82: 138901 | I82: 500781 | J82: HUMMINGBIR | L82: MYR | N82: 10934542 | P82: 0 | Q82: 0 | R82: 10934542
D83: EXIM | F83: 138901 | I83: 500781 | J83: HUMMINGBIR | K83: N | L83: MYR | N83: 4437108.2 | P83: 8273513.5 | Q83: 8567663.4 | R83: 4142958.2
D84: EXIM | F84: 138901 | I84: 500805 | J84: ARMADA KRA | L84: MYR | N84: 1.3651013e+08 | P84: 0 | Q84: 0 | R84: 1.3651013e+08
D85: EXIM | F85: 138901 | I85: 500805 | J85: ARMADA KRA | K85: N | L85: MYR | N85: -5033607.3 | P85: 10648624 | Q85: 13164543 | R85: -7549525.9
D86: EXIM | F86: 138901 | I86: 500806 | J86: I & C EATI | L86: MYR | N86: 988584.59 | P86: 0 | Q86: 0 | R86: 988584.59
D87: EXIM | F87: 138901 | I87: 500807 | J87: PERTAMA FE | L87: MYR | N87: 77658280 | P87: 0 | Q87: 0 | R87: 77658280
D88: EXIM | F88: 138901 | I88: 500807 | J88: PERTAMA FE | K88: N | L88: MYR | N88: -3048737.1 | P88: 3297553.9 | Q88: 4725273 | R88: -4476456.2
D89: EXIM | F89: 138901 | I89: 500808 | J89: PERTAMA FE | L89: MYR | N89: 48341385 | P89: 0 | Q89: 0 | R89: 48341385
D90: EXIM | F90: 138901 | I90: 500808 | J90: PERTAMA FE | K90: N | L90: MYR | N90: -2334675.4 | P90: 3288005.5 | Q90: 4168384.2 | R90: -3215054.1
D91: EXIM | F91: 138901 | I91: 500827 | J91: PERTAMA FE | L91: MYR | N91: 1.0303549e+08 | P91: 0 | Q91: 0 | R91: 1.0303549e+08
D92: EXIM | F92: 138901 | I92: 500827 | J92: PERTAMA FE | K92: N | L92: MYR | N92: -2029114.9 | P92: 3544078.6 | Q92: 5476924.2 | R92: -3961960.5
D93: EXIM | F93: 138901 | I93: 500840 | J93: PERTAMA F | L93: MYR | N93: 26195072 | P93: 0 | Q93: 9177981.3 | R93: 17017091
D94: EXIM | F94: 138901 | I94: 500840 | J94: PERTAMA F | K94: N | L94: MYR | N94: 392215.84 | P94: 17771452 | Q94: 18145954 | R94: 17713.39
D95: EXIM | F95: 138901 | I95: 500852 | J95: NEE ASSETS | L95: MYR | N95: 539751.12 | P95: 0 | Q95: 0 | R95: 539751.12
D96: EXIM | F96: 138901 | I96: 500866 | J96: NEE ASSETS | L96: MYR | N96: 116666.69 | P96: 0 | Q96: 0 | R96: 116666.69
D97: EXIM | F97: 138901 | I97: 500878 | J97: WOK DELIGH | L97: MYR | N97: 1195048.9 | P97: 0 | Q97: 66391.6 | R97: 1128657.3
D98: EXIM | F98: 138901 | I98: 500883 | J98: UPL LAO CO | L98: MYR | N98: 9642456.5 | P98: 0 | Q98: 0 | R98: 9642456.5
D99: EXIM | F99: 138901 | I99: 500883 | J99: UPL LAO CO | K99: N | L99: MYR | N99: -771490.12 | P99: 789974.43 | Q99: 959728.18 | R99: -941243.87
D100: EXIM | F100: 138901 | I100: 500884 | J100: UPL LAO CO | L100: MYR | N100: 17170952 | P100: 0 | Q100: 0 | R100: 17170952
D101: EXIM | F101: 138901 | I101: 500884 | J101: UPL LAO CO | K101: N | L101: MYR | N101: -1533703.1 | P101: 1553177.7 | Q101: 1852410.2 | R101: -1832935.5
D102: EXIM | F102: 138901 | I102: 500885 | J102: SUPERBOOM | L102: MYR | N102: 87215473 | P102: 0 | Q102: 0 | R102: 87215473
...

Sheet Debtors Listing (C) Dec2020
A1: Customer Balances as at December 2020
A3: Customer Account Number | B3: Customer Class & Industry | C3: Customer Name | D3: Loan Currency | E3: Opening Principal | F3: Disbursement | G3: Adjustment Capitalization | H3: Forex ( + ) | I3: Repayment | J3: Adjustment Capitalization | K3: Forex ( - ) | L3: Closing Principal | M3: Maturity Date
A5: 500470 | C5: MINISTRY OF FINANCE - LAO PDR | D5: USD | E5: 86084375 | F5: 0 | G5: 0 | H5: 0 | I5: -6600750 | J5: 0 | K5: -1152125 | L5: 78331500 | M5: 45287
A6: 500937 | C6: THE MINISTRY OF FINANCE LAOS 2 | D6: USD | E6: 2.6360943e+08 | F6: 0 | G6: 0 | H6: 0 | I6: 0 | J6: 0 | K6: -3751986.9 | L6: 2.5985744e+08
B7: Active (Cross Border Credit) (Buyer Credit) | E7: 3.496938e+08 | F7: 0 | G7: 0 | H7: 0 | I7: -6600750 | J7: 0 | K7: -4904111.9 | L7: 3.3818894e+08
A9: 500878 | C9: WOK DELIGHTS SDN BHD | D9: MYR | E9: 1128657.3 | F9: 0 | G9: 0 | H9: 0 | I9: -66391.6 | J9: 0 | K9: 0 | L9: 1062265.7
B10: Active (Malaysia Kitchen Fin) | E10: 1128657.3 | F10: 0 | G10: 0 | H10: 0 | I10: -66391.6 | J10: 0 | K10: 0 | L10: 1062265.7
A12: 500629 | C12: FACADE TREATMENT (Term Loan)CBC | D12: MYR | E12: 1022697.2 | F12: 0 | G12: 0 | H12: 0 | I12: -1022697.2 | J12: 0 | K12: 0 | L12: 0 | M12: 41916
B13: Active (Overseas Contract Fi) (Term Loan) | E13: 1022697.2 | F13: 0 | G13: 0 | H13: 0 | I13: -1022697.2 | J13: 0 | K13: 0 | L13: 0
A15: 500679 | C15: BUMI ARMADA CAPITAL OFFSHORE LTD | D15: USD | E15: 1.9848706e+08 | F15: 0 | G15: 0 | H15: 0 | I15: -7544523.2 | J15: 0 | K15: -2739675.2 | L15: 1.8820286e+08 | M15: 43397
A16: 500708 | C16: SAPURAKENCANA TMC SDN BHD (1) | D16: USD | E16: 14952913 | F16: 0 | G16: 0 | H16: 0 | I16: 0 | J16: 0 | K16: -212826.74 | L16: 14740086 | M16: 44282
A17: 500709 | C17: SAPURAKENCANA TMC SDN BHD (2) | D17: USD | E17: 60502318 | F17: 0 | G17: 0 | H17: 0 | I17: 0 | J17: 0 | K17: -861137.28 | L17: 59641180 | M17: 44282
A18: 500749 | C18: ISTANBUL SABIHA GOKCEN ULUSLARARASI | D18: EUR | E18: 187926200 | F18: 0 | G18: 0 | H18: 2313850 | I18: 0 | J18: 0 | K18: 0 | L18: 190240050
B19: Active (Overseas Investment) | E19: 4.6186849e+08 | F19: 0 | G19: 0 | H19: 2313850 | I19: -7544523.2 | J19: 0 | K19: -3813639.2 | L19: 4.5282418e+08
A21: 500271 | C21: MBI Development D.O.O, Bosnia&Herze | D21: EUR | E21: 4939949.2 | F21: 0 | G21: 0 | H21: 57864.22 | I21: -2355404.6 | J21: 0 | K21: 0 | L21: 2642408.8 | M21: 44176
A22: 500590 | C22: MBI Development 2 | D22: EUR | E22: 5851962.6 | F22: 0 | G22: 0 | H22: 72052.55 | I22: 0 | J22: 0 | K22: 0 | L22: 5924015.1 | M22: 44176
A23: 500640 | C23: OM MATERIAL (SARAWAK) SDN BHD | D23: USD | E23: 1.17814e+08 | F23: 0 | G23: 0 | H23: 0 | I23: 0 | J23: 0 | K23: -1676861.8 | L23: 1.1613714e+08 | M23: 44102
A24: 500642 | C24: OM MATERIAL (SARAWAK) 2 | D24: USD | E24: 1.5974035e+08 | F24: 0 | G24: 0 | H24: 0 | I24: 0 | J24: 0 | K24: -2273605 | L24: 1.5746674e+08 | M24: 45013
A25: 500805 | C25: Armada Kraken Pte Ltd (OPF) | D25: USD | E25: 1.289606e+08 | F25: 0 | G25: 0 | H25: 0 | I25: -9893611.9 | J25: 0 | K25: -1756109.9 | L25: 1.1731088e+08
A26: 500807 | C26: Pertama Ferroalloys Sdn Bhd (2) | D26: USD | E26: 73181824 | F26: 0 | G26: 0 | H26: 0 | I26: -23084870 | J26: 0 | K26: -1041606.3 | L26: 49055348
A27: 500808 | C27: Pertama Ferroalloys Sdn Bhd (1) | D27: USD | E27: 45126331 | F27: 0 | G27: 0 | H27: 0 | I27: -14234893 | J27: 0 | K27: -642288.91 | L27: 30249148
A28: 500827 | C28: Pertama Ferroalloys Sdn Bhd (3) | D28: USD | E28: 99073530 | F28: 0 | G28: 0 | H28: 0 | I28: -31252289 | J28: 0 | K28: -1410126.3 | L28: 66411115
A29: 500885 | C29: SUPERBOOM PROJECTS SDN BHD | D29: USD | E29: 81238988 | F29: 0 | G29: 0 | H29: 0 | I29: 0 | J29: 0 | K29: -1156285 | L29: 80082703
A30: 500905 | C30: ZICO HOLDINGS INC (OPF) | D30: SGD | E30: 2347792.1 | F30: 0 | G30: 0 | H30: 0 | I30: -123693.72 | J30: 0 | K30: -5494.4 | L30: 2218604
A31: 500914 | C31: IMPIANA UBUD (LABUAN) CO. LTD. | D31: USD | E31: 89038750 | F31: 0 | G31: 0 | H31: 0 | I31: 0 | J31: 0 | K31: -1267300 | L31: 87771450
A32: 500927 | C32: BRITISH UNIVERSITY VIETNAM | D32: USD | E32: 76684854 | F32: 0 | G32: 0 | H32: 0 | I32: 0 | J32: 0 | K32: -1091465.4 | L32: 75593389
A33: 501031 | C33: YINSON BORONIA PRODUCTION BV | D33: USD | E33: 19914558 | F33: 16651488 | G33: 0 | H33: 0 | I33: 0 | J33: 0 | K33: -463861.51 | L33: 36102185
B34: Active (Overseas Projec Fin) | E34: 9.0391349e+08 | F34: 16651488 | G34: 0 | H34: 129916.77 | I34: -80944763 | J34: 0 | K34: -12785005 | L34: 8.2696513e+08
A36: 500538 | C36: MIR VALVE SDN BHD | D36: USD | E36: 12920455 | F36: 238448.58 | G36: 0 | H36: 0 | I36: -1430593.8 | J36: 0 | K36: -175308.54 | L36: 11553002 | M36: 42115
A37: 500693 | C37: PERUSAHAAN OTOMOBIL NASIONAL (VF) | D37: MYR | E37: 9680523.9 | F37: 4368985.7 | G37: 0 | H37: 0 | I37: -5274136.5 | J37: 0 | K37: 0 | L37: 8775373.1 | M37: 42004
A38: 500724 | C38: OM Material (Sarawak) Sdn Bhd | D38: USD | E38: 74407175 | F38: 5833966.8 | G38: 0 | H38: 0 | I38: -26007957 | J38: 0 | K38: -926851.63 | L38: 53306333 | M38: 42165
A39: 500840 | C39: Pertama Ferroalloys (Trade) | D39: USD | E39: 17034805 | F39: 19504489 | G39: 0 | H39: 0 | I39: -6890100 | J39: 0 | K39: -430517.22 | L39: 29218676
B40: Active (Supplier Credit) (Trade Finance) | E40: =SUM(E36:E39) -> 1.1404296e+08 | F40: 29945890 | G40: 0 | H40: 0 | I40: -39602787 | J40: 0 | K40: -1532677.4 | L40: =SUM(L36:L39) -> 1.0285338e+08
A42: 501000 | C42: Brahim's Overseas Venture Sdn Bhd | D42: MYR | E42: 15467576 | F42: 0 | G42: 0 | H42: 0 | I42: 0 | J42: 0 | K42: 0 | L42: 15467576
B43: Active (Term Loan) | E43: 15467576 | F43: 0 | G43: 0 | H43: 0 | I43: 0 | J43: 0 | K43: 0 | L43: 15467576
A45: 500010 | C45: PT BUMI INTERNATIONAL TANKERS | D45: USD | E45: 11446432 | F45: 0 | G45: 0 | H45: 0 | I45: 0 | J45: 0 | K45: -162918.52 | L45: 11283514 | M45: 40522
A46: 500011 | C46: PT LAYAR SENTOSA | D46: USD | E46: 11620510 | F46: 0 | G46: 0 | H46: 0 | I46: 0 | J46: 0 | K46: -165396.22 | L46: 11455114 | M46: 40522
A47: 500042 | C47: PT EDEN CAPITAL INDONESIA | D47: USD | E47: 12378749 | F47: 0 | G47: 0 | H47: 0 | I47: 0 | J47: 0 | K47: -176188.34 | L47: 12202561 | M47: 39685
A48: 500265 | C48: PT SARI INDAH LESTARI | D48: USD | E48: 72863488 | F48: 0 | G48: 0 | H48: 0 | I48: 0 | J48: 0 | K48: -1037075.4 | L48: 71826412 | M48: 41029
A49: 500274 | C49: HONDAAFUSHI INVESTMENT PVT LTD | D49: USD | E49: 36242972 | F49: 0 | G49: 0 | H49: 0 | I49: 0 | J49: 0 | K49: -515850.88 | L49: 35727121 | M49: 42946
A50: 500913 | C50: PT SRIWIJAYA AIR | D50: USD | E50: 3.2967287e+08 | F50: 0 | G50: 0 | H50: 0 | I50: 0 | J50: 0 | K50: -4692276.4 | L50: 3.2498059e+08
B51: Impaired Loan (Buyer Credit) | E51: 4.7422502e+08 | F51: 0 | G51: 0 | H51: 0 | I51: 0 | J51: 0 | K51: -6749705.8 | L51: 4.6747531e+08
A53: 500206 | C53: BESTEEL BERHAD | D53: USD | E53: 5739132.8 | F53: 0 | G53: 8569350.5 | H53: 0 | I53: 0 | J53: -5682093.5 | K53: -8626389.7 | L53: 0 | M53: 43768
B54: Impaired Loan (Cross Border Credit) (Term Loan) | E54: 5739132.8 | F54: 0 | G54: 8569350.5 | H54: 0 | I54: 0 | J54: -5682093.5 | K54: -8626389.7 | L54: 0
A56: 500546 | C56: FRESH BOWL FOODS LIMITED | D56: MYR | E56: 394477.61 | F56: 0 | G56: 0 | H56: 0 | I56: -7477.6 | J56: 0 | K56: 0 | L56: 387000.01 | M56: 42994
A57: 500560 | C57: PANNAH RESOURCES 1 | D57: MYR | E57: 711800 | F57: 0 | G57: 0 | H57: 0 | I57: -2000 | J57: 0 | K57: 0 | L57: 709800 | M57: 42803
A58: 500577 | C58: NIRMALA VILAS RESTAURANT SDN BHD | D58: MYR | E58: 747562.14 | F58: 0 | G58: 0 | H58: 0 | I58: 0 | J58: 0 | K58: 0 | L58: 747562.14 | M58: 42914
A59: 500644 | C59: GOLD RAIN RESOURCES | D59: MYR | E59: 1067187.6 | F59: 0 | G59: 0 | H59: 0 | I59: 0 | J59: 0 | K59: 0 | L59: 1067187.6 | M59: 43305
A60: 500758 | C60: 3 PLUS1 STUDIO SDN BHD 2 | D60: MYR | E60: 975206.98 | F60: 0 | G60: 0 | H60: 0 | I60: 0 | J60: 0 | K60: 0 | L60: 975206.98
A61: 500806 | C61: I & C EATING NETWORK INTERNATIONAL | D61: MYR | E61: 988584.59 | F61: 0 | G61: 0 | H61: 0 | I61: 0 | J61: 0 | K61: 0 | L61: 988584.59
A62: 500852 | C62: NEE ASSETS SDN BHD | D62: MYR | E62: 539751.12 | F62: 0 | G62: 0 | H62: 0 | I62: 0 | J62: 0 | K62: 0 | L62: 539751.12
A63: 500866 | C63: NEE ASSETS SDN BHD 1 | D63: MYR | E63: 116666.69 | F63: 0 | G63: 0 | H63: 0 | I63: 0 | J63: 0 | K63: 0 | L63: 116666.69
B64: Impaired Loan (Malaysia Kitchen Fin) | E64: 5541236.7 | F64: 0 | G64: 0 | H64: 0 | I64: -9477.6 | J64: 0 | K64: 0 | L64: 5531759.1
A66: 500515 | C66: SCOMI TRANSIT PROJECTS BRAZIL | D66: USD | E66: 33387184 | F66: 0 | G66: 0 | H66: 0 | I66: 0 | J66: 0 | K66: -475204.09 | L66: 32911980 | M66: 42324
B67: Impaired Loan (Overseas Contract Fi) | E67: 33387184 | F67: 0 | G67: 0 | H67: 0 | I67: 0 | J67: 0 | K67: -475204.09 | L67: 32911980
A69: 500776 | C69: HUMMINGBIRD ENERGY (L) INC (OIF) | D69: USD | E69: 72141926 | F69: 0 | G69: 0 | H69: 0 | I69: 0 | J69: 0 | K69: -1026805.3 | L69: 71115120 | M69: 25.03.2016
A70: 500980 | C70: VEERAM STONES PVT LTD | D70: USD | E70: 2597812.5 | F70: 0 | G70: 0 | H70: 0 | I70: -51739.5 | J70: 0 | K70: -36452.25 | L70: 2509620.8
B71: Impaired Loan (Overseas Investment) | E71: 74739738 | F71: 0 | G71: 0 | H71: 0 | I71: -51739.5 | J71: 0 | K71: -1063257.6 | L71: 73624741
A73: 500297 | C73: PHOENIX SURGE SDN BHD (111) | D73: USD | E73: 3845791 | F73: 0 | G73: 0 | H73: 0 | I73: 0 | J73: 0 | K73: -54749.66 | L73: 3791041.4 | M73: 43018
A74: 500522 | C74: VIRTUAL PEAKS GROUP SDN BHD | D74: USD | E74: 6637038.1 | F74: 0 | G74: 0 | H74: 0 | I74: 0 | J74: 0 | K74: -94465.81 | L74: 6542572.3 | M74: 44167
A75: 500557 | C75: MARKMORE ENERGY 1 | D75: USD | E75: 1.4270024e+08 | F75: 0 | G75: 0 | H75: 0 | I75: 0 | J75: 0 | K75: -2031070.9 | L75: 1.4066917e+08 | M75: 42842
A76: 500558 | C76: MARKMORE ENERGY II | D76: USD | E76: 1.6262789e+08 | F76: 0 | G76: 0 | H76: 0 | I76: 0 | J76: 0 | K76: -2314703.6 | L76: 1.6031318e+08 | M76: 42842
A77: 500576 | C77: ILEAVES (UK) LTD | D77: GBP | E77: 3191640 | F77: 0 | G77: 0 | H77: 33601.17 | I77: 0 | J77: 0 | K77: 0 | L77: 3225241.2
A78: 500631 | C78: MALAYSIAN DELICACIES PTY LTD | D78: AUD | E78: 590537.3 | F78: 0 | G78: 0 | H78: 17920.68 | I78: 0 | J78: 0 | K78: 0 | L78: 608457.98 | M78: 43309
A79: 500781 | C79: HUMMINGBIRD ENERGY (L) INC (OPF) | D79: USD | E79: 15077500 | F79: 0 | G79: 0 | H79: 0 | I79: 0 | J79: 0 | K79: -214600 | L79: 14862900
A80: 500883 | C80: UPL LAO CO. LTD 1 | D80: USD | E80: 8701212.6 | F80: 0 | G80: 0 | H80: 0 | I80: 0 | J80: 0 | K80: -123845.45 | L80: 8577367.1
A81: 500884 | C81: UPL LAO CO. LTD 2 | D81: USD | E81: 15338016 | F81: 0 | G81: 0 | H81: 0 | I81: 0 | J81: 0 | K81: -218307.99 | L81: 15119708
B82: Impaired Loan (Overseas Projec Fin) | E82: 3.5870986e+08 | F82: 0 | G82: 0 | H82: 51521.85 | I82: 0 | J82: 0 | K82: -5051743.5 | L82: 3.5370964e+08
A84: 500187 | C84: JEWEL GROWTH SDN BHD | D84: MYR | E84: 26832.06 | F84: 0 | G84: 0 | H84: 0 | I84: 0 | J84: 0 | K84: 0 | L84: 26832.06 | M84: 39812
A85: 500197 | C85: VEHENG GLOBAL TRADERS SDN BHD | D85: MYR | E85: 8200000 | F85: 0 | G85: 0 | H85: 0 | I85: 0 | J85: 0 | K85: 0 | L85: 8200000 | M85: 40117
A86: 500716 | C86: HOT-CAN SDN BHD | D86: USD | E86: 871346.01 | F86: 0 | G86: 223273.79 | H86: 0 | I86: 0 | J86: -862686 | K86: -231933.8 | L86: 0 | M86: 42026
A87: 500768 | C87: UIL MALAYSIA LTD | D87: USD | E87: 89866561 | F87: 0 | G87: 12345637 | H87: 0 | I87: -40505000 | J87: -48821259 | K87: -12885939 | L87: 0
B88: Impaired Loan (Supplier Credit) (Trade Finance) | E88: 98964739 | F88: 0 | G88: 12568911 | H88: 0 | I88: -40505000 | J88: -49683945 | K88: -13117873 | L88: 8226832.1
A90: 500962 | C90: Scomi Transit Projects Brazil | E90: 40515000 | F90: 0 | G90: 0 | H90: 0 | I90: 0 | J90: 0 | K90: 0 | L90: 40515000
B91: Impaired Loan (Term Loan) | E91: 40515000 | F91: 0 | G91: 0 | H91: 0 | I91: 0 | J91: 0 | K91: 0 | L91: 40515000
A93: 500039 | C93: PT MAHAKARYA INTI BUANA | D93: USD | E93: 11564046 | F93: 0 | G93: 0 | H93: 0 | I93: 0 | J93: 0 | K93: -164592.55 | L93: 11399454 | M93: 41435
A94: 500613 | C94: HARTAMANIS (S) PTE LTD (TL2) | D94: MYR | E94: 7458382.5 | F94: 0 | G94: 0 | H94: 0 | I94: 0 | J94: 0 | K94: 0 | L94: 7458382.5 | M94: 42396
B95: Restuctured | E95: 19022429 | F95: 0 | G95: 0 | H95: 0 | I95: 0 | J95: 0 | K95: -164592.55 | L95: 18857836
A97: 500512 | C97: AL-MANARA WATER COMPANY LIMITED | D97: EUR | E97: 1.0268344e+08 | F97: 0 | G97: 0 | H97: 1264294.7 | I97: 0 | J97: 0 | K97: 0 | L97: 1.0394774e+08 | M97: 44165
B98: Restuctured (Buyer Credit) | E98: 1.0268344e+08 | F98: 0 | G98: 0 | H98: 1264294.7 | I98: 0 | J98: 0 | K98: 0 | L98: 1.0394774e+08
A100: 500555 | C100: SOLARTIF SDN BHD | D100: MYR | E100: 720736.03 | F100: 0 | G100: 0 | H100: 0 | I100: -24553.19 | J100: 0 | K100: 0 | L100: 696182.84 | M100: 41313
B101: Restuctured (Supplier Credit) (Trade Finance) | E101: 720736.03 | F101: 0 | G101: 0 | H101: 0 | I101: -24553.19 | J101: 0 | K101: 0 | L101: 696182.84
A103: 500400 | C103: THE REPUBLIC OF IRAQ | D103: USD | E103: 2341789.8 | F103: 0 | G103: 0 | H103: 0 | I103: 0 | J103: 0 | K103: -33330.95 | L103: 2308458.9 | M103: 46813
A104: 500401 | C104: THE REPUBLIC OF SEYCHELLES | D104: USD | E104: 19717102 | F104: 0 | G104: 0 | H104: 0 | I104: 0 | J104: 0 | K104: -280636.03 | L104: 19436466 | M104: 46583
B105: Restuctured (Term Loan) | E105: 22058892 | F105: 0 | G105: 0 | H105: 0 | I105: 0 | J105: 0 | K105: -313966.98 | L105: 21744925
E108: =E105+E101+E98+E95+E91+E88+E82+E71+E67+E64+E54+E51+E43+E40+E34+E19+E13+E10+E7 -> 3.0834451e+09 | F108: =F105+F101+F98+F95+F91+F88+F82+F71+F67+F64+F54+F51+F43+F40+F34+F19+F13+F10+F7 -> 46597378 | G108: =G105+G101+G98+G95+G91+G88+G82+G71+G67+G64+G54+G51+G43+G40+G34+G19+G13+G10+G7 -> 21138262 | H108: =H105+H101+H98+H95+H91+H88+H82+H71+H67+H64+H54+H51+H43+H40+H34+H19+H13+H10+H7 -> 3759583.3 | I108: =I105+I101+I98+I95+I91+I88+I82+I71+I67+I64+I54+I51+I43+I40+I34+I19+I13+I10+I7 -> -1.7637268e+08 | J108: =J105+J101+J98+J95+J91+J88+J82+J71+J67+J64+J54+J51+J43+J40+J34+J19+J13+J10+J7 -> -55366038 | K108: =K105+K101+K98+K95+K91+K88+K82+K71+K67+K64+K54+K51+K43+K40+K34+K19+K13+K10+K7 -> -58598166 | L108: =L105+L101+L98+L95+L91+L88+L82+L71+L67+L64+L54+L51+L43+L40+L34+L19+L13+L10+L7 -> 2.8646034e+09

Sheet Mora
B1: Borrower | C1: Trade/ Non trade | D1: Islamic / Conventional | E1: SME/ Corporate/ Commercial | F1: Auto Mora/Mora/Non-auto mora (R&R) | G1: Currency | H1: Modification impact (Post) | I1: Rate | J1: Modification impact (Post) RM Sep 2020 | K1: Rate | L1: Modification impact (Post) RM Oct 2020 | N1: Rate | O1: Modification impact (Post) RM Nov 2020 | Q1: Rate | R1: Modification impact (Post) RM Dec 2020 | T1: Rate | U1: Modification impact (Post) RM Jan 2021 | W1: Rate | X1: Modification impact (Post) RM Feb 2021 | Y1: Rate | Z1: Modification impact (Post) RM Mar 2021 | AC1: Modification impact (Post) RM Apr 2021
A2: 1 | B2: Façade Treatment Engineering | C2: Non trade | D2: Conventional | E2: SME | F2: Auto Mora | G2: MYR | H2: 0 | I2: 1 | K2: 1 | L2: =H2*K2 -> 0 | N2: 1 | O2: =H2*N2 -> 0 | Q2: 1 | R2: =H2*Q2 -> 0 | T2: 1 | U2: =H2*T2 -> 0 | W2: 1 | X2: =H2*W2 -> 0 | Y2: 1 | Z2: =J2*Y2 -> 0 | AC2: =L2*AB2 -> 0
A3: 2 | B3: Wok Delights Sdn Bhd | C3: Non trade | D3: Conventional | E3: SME | F3: Auto Mora | G3: MYR | H3: 0 | I3: 1 | K3: 1 | L3: =H3*K3 -> 0 | N3: 1 | O3: =H3*N3 -> 0 | Q3: 1 | R3: =H3*Q3 -> 0 | T3: 1 | U3: =H3*T3 -> 0 | W3: 1 | X3: -55529.45 | Y3: 1 | Z3: -55529.45 | AC3: -55529.45 | AD3: =X3-Z3 -> 0
A4: 3 | B4: Ingress Katayama technical centre (IF-i) | C4: Non trade | D4: Islamic | E4: SME | F4: Auto Mora | G4: MYR | H4: -451147.24 | I4: 1 | J4: =H4*I4 -> -451147.24 | K4: 1 | L4: =H4*K4 -> -451147.24 | N4: 1 | O4: =H4*N4 -> -451147.24 | Q4: 1 | R4: =H4*Q4 -> -451147.24 | T4: 1 | U4: =H4*T4 -> -451147.24 | W4: 1 | X4: =H4*W4 -> -451147.24 | Y4: 1 | Z4: =J4*Y4 -> -451147.24 | AC4: =L4*AB4 -> 0 | AD4: =U4-X4 -> 0
A5: 4 | B5: Ingress Katayama technical centre (TF-i) | C5: Non trade | D5: Islamic | E5: SME | F5: Auto Mora | G5: MYR | H5: -329666.72 | I5: 1 | J5: =H5*I5 -> -329666.72 | K5: 1 | L5: =H5*K5 -> -329666.72 | N5: 1 | O5: =H5*N5 -> -329666.72 | Q5: 1 | R5: =H5*Q5 -> -329666.72 | T5: 1 | U5: =H5*T5 -> -329666.72 | W5: 1 | X5: =H5*W5 -> -329666.72 | Y5: 1 | Z5: =J5*Y5 -> -329666.72 | AC5: =L5*AB5 -> 0 | AD5: =U5-X5 -> 0
A6: 5 | B6: Lipidchem 1 | C6: Non trade | D6: Islamic | E6: SME | F6: Auto Mora | G6: MYR | H6: -33516.044 | I6: 1 | J6: =H6*I6 -> -33516.044 | K6: 1 | L6: =H6*K6 -> -33516.044 | N6: 1 | O6: =H6*N6 -> -33516.044 | Q6: 1 | R6: =H6*Q6 -> -33516.044 | T6: 1 | U6: =H6*T6 -> -33516.044 | W6: 1 | X6: =H6*W6 -> -33516.044 | Y6: 1 | Z6: =J6*Y6 -> -33516.044 | AC6: =L6*AB6 -> 0 | AD6: =U6-X6 -> 0
A7: 6 | B7: Lipidchem 2 | C7: Non trade | D7: Islamic | E7: SME | F7: Auto Mora | G7: MYR | H7: -261559.97 | I7: 1 | J7: =H7*I7 -> -261559.97 | K7: 1 | L7: =H7*K7 -> -261559.97 | N7: 1 | O7: =H7*N7 -> -261559.97 | Q7: 1 | R7: =H7*Q7 -> -261559.97 | T7: 1 | U7: =H7*T7 -> -261559.97 | W7: 1 | X7: =H7*W7 -> -261559.97 | Y7: 1 | Z7: =J7*Y7 -> -261559.97 | AC7: =L7*AB7 -> 0 | AD7: =U7-X7 -> 0
A8: 7 | B8: PWN Excellence Sdn Bhd 1 | C8: Non trade | D8: Islamic | E8: SME | F8: Auto Mora | G8: MYR | H8: -3212958.2 | I8: 1 | J8: =H8*I8 -> -3212958.2 | K8: 1 | L8: =H8*K8 -> -3212958.2 | N8: 1 | O8: =H8*N8 -> -3212958.2 | Q8: 1 | R8: =H8*Q8 -> -3212958.2 | T8: 1 | U8: =H8*T8 -> -3212958.2 | W8: 1 | X8: =H8*W8 -> -3212958.2 | Y8: 1 | Z8: =J8*Y8 -> -3212958.2 | AC8: =L8*AB8 -> 0 | AD8: =U8-X8 -> 0
A9: 8 | B9: PWN Excellence Sdn Bhd 2 | C9: Non trade | D9: Islamic | E9: SME | F9: Auto Mora | G9: MYR | H9: -306100.55 | I9: 1 | J9: =H9*I9 -> -306100.55 | K9: 1 | L9: =H9*K9 -> -306100.55 | N9: 1 | O9: =H9*N9 -> -306100.55 | Q9: 1 | R9: =H9*Q9 -> -306100.55 | T9: 1 | U9: =H9*T9 -> -306100.55 | W9: 1 | X9: =H9*W9 -> -306100.55 | Y9: 1 | Z9: =J9*Y9 -> -306100.55 | AC9: =L9*AB9 -> 0 | AD9: =U9-X9 -> 0
A10: 9 | B10: PWN Excellence Sdn Bhd 3 | C10: Non trade | D10: Islamic | E10: SME | F10: Auto Mora | G10: MYR | H10: -1662540.6 | I10: 1 | J10: =H10*I10 -> -1662540.6 | K10: 1 | L10: =H10*K10 -> -1662540.6 | N10: 1 | O10: =H10*N10 -> -1662540.6 | Q10: 1 | R10: =H10*Q10 -> -1662540.6 | T10: 1 | U10: =H10*T10 -> -1662540.6 | W10: 1 | X10: =H10*W10 -> -1662540.6 | Y10: 1 | Z10: =J10*Y10 -> -1662540.6 | AC10: =L10*AB10 -> 0 | AD10: =U10-X10 -> 0
A11: 10 | B11: Tabco Food | C11: Non trade | D11: Islamic | E11: SME | F11: Auto Mora | G11: MYR | H11: -85330.865 | I11: 1 | J11: =H11*I11 -> -85330.865 | K11: 1 | L11: =H11*K11 -> -85330.865 | N11: 1 | O11: =H11*N11 -> -85330.865 | Q11: 1 | R11: =H11*Q11 -> -85330.865 | T11: 1 | U11: =H11*T11 -> -85330.865 | W11: 1 | X11: =H11*W11 -> -85330.865 | Y11: 1 | Z11: =J11*Y11 -> -85330.865 | AC11: =L11*AB11 -> 0 | AD11: =U11-X11 -> 0
A12: 11 | B12: Tabco food | C12: Non trade | D12: Islamic | E12: SME | F12: Auto Mora | G12: MYR | H12: -107821.04 | I12: 1 | J12: =H12*I12 -> -107821.04 | K12: 1 | L12: =H12*K12 -> -107821.04 | N12: 1 | O12: =H12*N12 -> -107821.04 | Q12: 1 | R12: =H12*Q12 -> -107821.04 | T12: 1 | U12: =H12*T12 -> -107821.04 | W12: 1 | X12: =H12*W12 -> -107821.04 | Y12: 1 | Z12: =J12*Y12 -> -107821.04 | AC12: =L12*AB12 -> 0 | AD12: =U12-X12 -> 0
A13: 12 | B13: UCM Industrial Corporation | C13: Trade | D13: Islamic | E13: SME | F13: Auto Mora | G13: MYR | H13: -5640.3697 | I13: 1 | J13: =H13*I13 -> -5640.3697 | K13: 1 | L13: =H13*K13 -> -5640.3697 | N13: 1 | O13: =H13*N13 -> -5640.3697 | Q13: 1 | R13: =H13*Q13 -> -5640.3697 | T13: 1 | U13: =H13*T13 -> -5640.3697 | W13: 1 | X13: =H13*W13 -> -5640.3697 | Y13: 1 | Z13: =J13*Y13 -> -5640.3697 | AC13: =L13*AB13 -> 0 | AD13: =U13-X13 -> 0
A14: 13 | B14: Impiana Ubud (Labuan) Co. Ltd | C14: Non trade | D14: Conventional | E14: Non SME | F14: Non Auto Mora | G14: USD | H14: -6585324.3 | I14: 4.1555 | J14: =H14*I14 -> -27365315 | K14: 4.1545 | L14: =H14*K14 -> -27358730 | M14: =J14-L14 -> -6585.3243 | N14: 4.075 | O14: =H14*N14 -> -26835196 | P14: =L14-O14 -> -523533.28 | Q14: 4.017 | R14: =H14*Q14 -> -26453248 | S14: =O14-R14 -> -381948.81 | T14: 4.045 | U14: =H14*T14 -> -26637637 | V14: =R14-U14 -> 184389.08 | W14: 4.0495 | X14: =H14*W14 -> -26667271 | Y14: 4.146 | Z14: =H14*$Y$14 -> -27302754 | AA14: 4.0975 | AB14: =U14-X14 -> 29633.959 | AC14: =H14*$AA$14 -> -26983366
A15: 14 | B15: Mir Valve | C15: Trade | D15: Conventional | E15: SME | F15: Non Auto Mora | G15: USD | H15: -8133.6474 | I15: 4.1555 | J15: =H15*I15 -> -33799.372 | K15: 4.1545 | L15: =H15*K15 -> -33791.238 | M15: =J15-L15 -> -8.1336474 | N15: 4.075 | O15: =H15*N15 -> -33144.613 | P15: =L15-O15 -> -646.62497 | Q15: 4.017 | R15: =H15*Q15 -> -32672.862 | S15: =O15-R15 -> -471.75155 | T15: 4.045 | U15: =H15*T15 -> -32900.604 | V15: =R15-U15 -> 227.74213 | W15: 4.0495 | X15: =H15*W15 -> -32937.205 | Y15: 4.146 | Z15: =H15*$Y$14 -> -33722.102 | AA15: 4.0975 | AB15: =U15-X15 -> 36.601413 | AC15: =H15*$AA$14 -> -33327.62
A16: 15 | B16: Pertama Ferraalloys Sdn Bhd | C16: Non trade | D16: Conventional | E16: Non SME | F16: Non Auto Mora | G16: USD | H16: -37664.752 | I16: 4.1555 | J16: =H16*I16 -> -156515.88 | K16: 4.1545 | L16: =H16*K16 -> -156478.21 | M16: =J16-L16 -> -37.664752 | N16: 4.075 | O16: =H16*N16 -> -153483.87 | P16: =L16-O16 -> -2994.3478 | Q16: 4.017 | R16: =H16*Q16 -> -151299.31 | S16: =O16-R16 -> -2184.5556 | T16: 4.045 | U16: =H16*T16 -> -152353.92 | V16: =R16-U16 -> 1054.6131 | W16: 4.0495 | X16: =H16*W16 -> -152523.41 | Y16: 4.146 | Z16: =H16*$Y$14 -> -156158.06 | AA16: 4.0975 | AB16: =U16-X16 -> 169.49139 | AC16: =H16*$AA$14 -> -154331.32
A17: 16 | B17: Pertama Ferraalloys Sdn Bhd | C17: Non trade | D17: Conventional | E17: Non SME | F17: Non Auto Mora | G17: USD | H17: -61497.389 | I17: 4.1555 | J17: =H17*I17 -> -255552.4 | K17: 4.1545 | L17: =H17*K17 -> -255490.9 | M17: =J17-L17 -> -61.497389 | N17: 4.075 | O17: =H17*N17 -> -250601.86 | P17: =L17-O17 -> -4889.0424 | Q17: 4.017 | R17: =H17*Q17 -> -247035.01 | S17: =O17-R17 -> -3566.8486 | T17: 4.045 | U17: =H17*T17 -> -248756.94 | V17: =R17-U17 -> 1721.9269 | W17: 4.0495 | X17: =H17*W17 -> -249033.68 | Y17: 4.146 | Z17: =H17*$Y$14 -> -254968.18 | AA17: 4.0975 | AB17: =U17-X17 -> 276.73825 | AC17: =H17*$AA$14 -> -251985.55
A18: 17 | B18: Pertama Ferraalloys Sdn Bhd | C18: Non trade | D18: Conventional | E18: Non SME | F18: Non Auto Mora | G18: USD | H18: -87180.238 | I18: 4.1555 | J18: =H18*I18 -> -362277.48 | K18: 4.1545 | L18: =H18*K18 -> -362190.3 | M18: =J18-L18 -> -87.180238 | N18: 4.075 | O18: =H18*N18 -> -355259.47 | P18: =L18-O18 -> -6930.8289 | Q18: 4.017 | R18: =H18*Q18 -> -350203.02 | S18: =O18-R18 -> -5056.4538 | T18: 4.045 | U18: =H18*T18 -> -352644.06 | V18: =R18-U18 -> 2441.0467 | W18: 4.0495 | X18: =H18*W18 -> -353036.37 | Y18: 4.146 | Z18: =H18*$Y$14 -> -361449.27 | AA18: 4.0975 | AB18: =U18-X18 -> 392.31107 | AC18: =H18*$AA$14 -> -357221.03
A19: 18 | B19: Envico Enterprises Sdn Bhd | C19: Trade | D19: Islamic | E19: SME | F19: Non Auto Mora | G19: USD | H19: -13002.709 | I19: 4.1555 | J19: =H19*I19 -> -54032.757 | K19: 4.1545 | L19: =H19*K19 -> -54019.754 | M19: =J19-L19 -> -13.002709 | N19: 4.075 | O19: =H19*N19 -> -52986.039 | P19: =L19-O19 -> -1033.7154 | Q19: 4.017 | R19: =H19*Q19 -> -52231.882 | S19: =O19-R19 -> -754.15712 | T19: 4.045 | U19: =H19*T19 -> -52595.958 | V19: =R19-U19 -> 364.07585 | W19: 4.0495 | X19: =H19*W19 -> -52654.47 | Y19: 4.146 | Z19: =H19*$Y$14 -> -53909.231 | AA19: 4.0975 | AB19: =U19-X19 -> 58.51219 | AC19: =H19*$AA$14 -> -53278.6 | AD19: =Z19-AC19 -> -630.63138
A20: 19 | B20: Helms Geomarine | C20: Non trade | D20: Islamic | E20: SME | F20: Non Auto Mora | G20: USD | H20: -15168.479 | I20: 4.1555 | J20: =H20*I20 -> -63032.615 | K20: 4.1545 | L20: =H20*K20 -> -63017.447 | M20: =J20-L20 -> -15.168479 | N20: 4.075 | O20: =H20*N20 -> -61811.553 | P20: =L20-O20 -> -1205.8941 | Q20: 4.017 | R20: =H20*Q20 -> -60931.781 | S20: =O20-R20 -> -879.77179 | T20: 4.045 | U20: =H20*T20 -> -61356.498 | V20: =R20-U20 -> 424.71742 | W20: 4.0495 | X20: =H20*W20 -> -61424.756 | Y20: 4.146 | Z20: =H20*$Y$14 -> -62888.515 | AA20: 4.0975 | AB20: =U20-X20 -> 68.258156 | AC20: =H20*$AA$14 -> -62152.843 | AD20: =Z20-AC20 -> -735.67124
A21: 20 | B21: Impiana Seminyak (Labuan) Co Ltd (OIF-i 1) | C21: Non trade | D21: Islamic | E21: Non SME | F21: Non Auto Mora | G21: USD | H21: -1292915.6 | I21: 4.1555 | J21: =H21*I21 -> -5372710.9 | K21: 4.1545 | L21: =H21*K21 -> -5371418 | M21: =J21-L21 -> -1292.9156 | N21: 4.075 | O21: =H21*N21 -> -5268631.2 | P21: =L21-O21 -> -102786.79 | Q21: 4.017 | R21: =H21*Q21 -> -5193642.1 | S21: =O21-R21 -> -74989.107 | T21: 4.045 | U21: =H21*T21 -> -5229843.8 | V21: =R21-U21 -> 36201.638 | W21: 4.0495 | X21: =H21*W21 -> -5235661.9 | Y21: 4.146 | Z21: =H21*$Y$14 -> -5360428.2 | AA21: 4.0975 | AB21: =U21-X21 -> 5818.1204 | AC21: =H21*$AA$14 -> -5297721.8 | AD21: =Z21-AC21 -> -62706.408
A22: 21 | B22: Impiana Seminyak (Labuan) Co Ltd (OIF-i 2) | C22: Non trade | D22: Islamic | E22: Non SME | F22: Non Auto Mora | G22: USD | H22: -167301.16 | I22: 4.1555 | J22: =H22*I22 -> -695219.95 | K22: 4.1545 | L22: =H22*K22 -> -695052.65 | M22: =J22-L22 -> -167.30116 | N22: 4.075 | O22: =H22*N22 -> -681752.21 | P22: =L22-O22 -> -13300.442 | Q22: 4.017 | R22: =H22*Q22 -> -672048.74 | S22: =O22-R22 -> -9703.467 | T22: 4.045 | U22: =H22*T22 -> -676733.17 | V22: =R22-U22 -> 4684.4323 | W22: 4.0495 | X22: =H22*W22 -> -677486.03 | Y22: 4.146 | Z22: =H22*$Y$14 -> -693630.59 | AA22: 4.0975 | AB22: =U22-X22 -> 752.8552 | AC22: =H22*$AA$14 -> -685516.48 | AD22: =Z22-AC22 -> -8114.106
A23: 22 | B23: International Brass | C23: Trade | D23: Islamic | E23: SME | F23: Non Auto Mora | G23: USD | H23: -2352.5762 | I23: 4.1555 | J23: =H23*I23 -> -9776.1303 | K23: 4.1545 | L23: =H23*K23 -> -9773.7777 | M23: =J23-L23 -> -2.3525762 | N23: 4.075 | O23: =H23*N23 -> -9586.7479 | P23: =L23-O23 -> -187.02981 | Q23: 4.017 | R23: =H23*Q23 -> -9450.2985 | S23: =O23-R23 -> -136.44942 | T23: 4.045 | U23: =H23*T23 -> -9516.1706 | V23: =R23-U23 -> 65.872133 | W23: 4.0495 | X23: =H23*W23 -> -9526.7572 | Y23: 4.146 | Z23: =H23*$Y$14 -> -9753.7808 | AA23: 4.0975 | AB23: =U23-X23 -> 10.586593 | AC23: =H23*$AA$14 -> -9639.6809 | AD23: =Z23-AC23 -> -114.09994
A24: 23 | B24: Nupon Technology Sdn Bhd | C24: Trade | D24: Islamic | E24: SME | F24: Non Auto Mora | G24: USD | H24: -683.1548 | I24: 4.1555 | J24: =H24*I24 -> -2838.8498 | K24: 4.1545 | L24: =H24*K24 -> -2838.1666 | M24: =J24-L24 -> -0.6831548 | N24: 4.075 | O24: =H24*N24 -> -2783.8558 | P24: =L24-O24 -> -54.310806 | Q24: 4.017 | R24: =H24*Q24 -> -2744.2328 | S24: =O24-R24 -> -39.622978 | T24: 4.045 | U24: =H24*T24 -> -2763.3611 | V24: =R24-U24 -> 19.128334 | W24: 4.0495 | X24: =H24*W24 -> -2766.4353 | Y24: 4.146 | Z24: =H24*$Y$14 -> -2832.3598 | AA24: 4.0975 | AB24: =U24-X24 -> 3.0741966 | AC24: =H24*$AA$14 -> -2799.2268 | AD24: =Z24-AC24 -> -33.133008
A25: 24 | B25: Smart Glove Corporation Sdn Bhd | C25: Non trade | D25: Islamic | E25: SME | F25: Non Auto Mora | G25: USD | H25: -385716.25 | I25: 4.1555 | J25: =H25*I25 -> -1602843.9 | K25: 4.1545 | L25: =H25*K25 -> -1602458.2 | M25: =J25-L25 -> -385.71625 | N25: 4.075 | O25: =H25*N25 -> -1571793.7 | P25: =L25-O25 -> -30664.442 | Q25: 4.017 | R25: =H25*Q25 -> -1549422.2 | S25: =O25-R25 -> -22371.543 | T25: 4.045 | U25: =H25*T25 -> -1560222.2 | V25: =R25-U25 -> 10800.055 | W25: 4.0495 | X25: =H25*W25 -> -1561958 | Y25: 4.146 | Z25: =H25*$Y$14 -> -1599179.6 | AA25: 4.0975 | AB25: =U25-X25 -> 1735.7231 | AC25: =H25*$AA$14 -> -1580472.3 | AD25: =Z25-AC25 -> -18707.238
A26: 25 | B26: SMH Rail Sdn Bhd 1 | C26: Non trade | D26: Islamic | E26: SME | F26: Non Auto Mora | G26: USD | H26: -46526.4 | I26: 4.1555 | J26: =H26*I26 -> -193340.46 | K26: 4.1545 | L26: =H26*K26 -> -193293.93 | M26: =J26-L26 -> -46.5264 | N26: 4.075 | O26: =H26*N26 -> -189595.08 | P26: =L26-O26 -> -3698.8488 | Q26: 4.017 | R26: =H26*Q26 -> -186896.55 | S26: =O26-R26 -> -2698.5312 | T26: 4.045 | U26: =H26*T26 -> -188199.29 | V26: =R26-U26 -> 1302.7392 | W26: 4.0495 | X26: =H26*W26 -> -188408.66 | Y26: 4.146 | Z26: =H26*$Y$14 -> -192898.46 | AA26: 4.0975 | AB26: =U26-X26 -> 209.3688 | AC26: =H26*$AA$14 -> -190641.93 | AD26: =Z26-AC26 -> -2256.5304
A27: 26 | B27: SMH Rail Sdn Bhd 2 | C27: Non trade | D27: Islamic | E27: SME | F27: Non Auto Mora | G27: USD | H27: -77178.265 | I27: 4.1555 | J27: =H27*I27 -> -320714.28 | K27: 4.1545 | L27: =H27*K27 -> -320637.1 | M27: =J27-L27 -> -77.178265 | N27: 4.075 | O27: =H27*N27 -> -314501.43 | P27: =L27-O27 -> -6135.672 | Q27: 4.017 | R27: =H27*Q27 -> -310025.09 | S27: =O27-R27 -> -4476.3393 | T27: 4.045 | U27: =H27*T27 -> -312186.08 | V27: =R27-U27 -> 2160.9914 | W27: 4.0495 | X27: =H27*W27 -> -312533.38 | Y27: 4.146 | Z27: =H27*$Y$14 -> -319981.09 | AA27: 4.0975 | AB27: =U27-X27 -> 347.30219 | AC27: =H27*$AA$14 -> -316237.94 | AD27: =Z27-AC27 -> -3743.1458
A28: 27 | B28: SMH Rail Sdn Bhd 3 | C28: Non trade | D28: Islamic | E28: SME | F28: Non Auto Mora | G28: USD | H28: -197021.63 | I28: 4.1555 | J28: =H28*I28 -> -818723.39 | K28: 4.1545 | L28: =H28*K28 -> -818526.37 | M28: =J28-L28 -> -197.02163 | N28: 4.075 | O28: =H28*N28 -> -802863.15 | P28: =L28-O28 -> -15663.22 | Q28: 4.017 | R28: =H28*Q28 -> -791435.9 | S28: =O28-R28 -> -11427.255 | T28: 4.045 | U28: =H28*T28 -> -796952.5 | V28: =R28-U28 -> 5516.6057 | W28: 4.0495 | X28: =H28*W28 -> -797839.1 | Y28: 4.146 | Z28: =H28*$Y$14 -> -816851.69 | AA28: 4.0975 | AB28: =U28-X28 -> 886.59735 | AC28: =H28*$AA$14 -> -807296.14 | AD28: =Z28-AC28 -> -9555.5492
A29: 28 | B29: SMH Rail Thailand | C29: Non trade | D29: Islamic | E29: SME | F29: Non Auto Mora | G29: USD | H29: -170730.65 | I29: 4.1555 | J29: =H29*I29 -> -709471.2 | K29: 4.1545 | L29: =H29*K29 -> -709300.47 | M29: =J29-L29 -> -170.73065 | N29: 4.075 | O29: =H29*N29 -> -695727.39 | P29: =L29-O29 -> -13573.086 | Q29: 4.017 | R29: =H29*Q29 -> -685825.01 | S29: =O29-R29 -> -9902.3775 | T29: 4.045 | U29: =H29*T29 -> -690605.47 | V29: =R29-U29 -> 4780.4581 | W29: 4.0495 | X29: =H29*W29 -> -691373.76 | Y29: 4.146 | Z29: =H29*$Y$14 -> -707849.26 | AA29: 4.0975 | AB29: =U29-X29 -> 768.28791 | AC29: =H29*$AA$14 -> -699568.83 | AD29: =Z29-AC29 -> -8280.4364
A30: 29 | B30: Superboom Projects Sdn Bhd | C30: Non trade | D30: Conventional | E30: SME | F30: Non Auto Mora | G30: USD | H30: -1463337.6 | I30: 4.1555 | J30: =H30*I30 -> -6080899.4 | K30: 4.1545 | L30: =H30*K30 -> -6079436.1 | M30: =J30-L30 -> -1463.3376 | N30: 4.075 | O30: =H30*N30 -> -5963100.7 | P30: =L30-O30 -> -116335.34 | Q30: 4.017 | R30: =H30*Q30 -> -5878227.2 | S30: =O30-R30 -> -84873.581 | T30: 4.045 | U30: =H30*T30 -> -5919200.6 | V30: =R30-U30 -> 40973.453 | W30: 4.0495 | X30: =H30*W30 -> -5925785.6 | Y30: 4.146 | Z30: =H30*$Y$14 -> -6066997.7 | AA30: 4.0975 | AB30: =U30-X30 -> 6585.0192 | AC30: =H30*$AA$14 -> -5996025.8 | AD30: =Z30-AC30 -> -70971.874
A31: 30 | B31: Wilson International trading | C31: Trade | D31: Islamic | E31: SME | F31: Non Auto Mora | G31: USD | I31: 4.1555 | J31: =H31*I31 -> 0 | K31: 4.1545 | L31: =H31*K31 -> 0 | M31: =J31-L31 -> 0 | N31: 4.075 | O31: =H31*N31 -> 0 | P31: =L31-O31 -> 0 | Q31: 4.017 | R31: =H31*Q31 -> 0 | S31: =O31-R31 -> 0 | T31: 4.045 | U31: =H31*T31 -> 0 | V31: =R31-U31 -> 0 | W31: 4.0495 | X31: =H31*W31 -> 0 | Y31: 4.146 | Z31: =H31*$Y$14 -> 0 | AA31: 4.0975 | AB31: =U31-X31 -> 0 | AC31: =H31*$AA$14 -> 0 | AD31: =Z31-AC31 -> 0
A32: 31 | B32: WSA Venture Australia (M) Sdn Bhd | C32: Trade | D32: Islamic | E32: SME | F32: Non Auto Mora | G32: USD | H32: -1884.0242 | I32: 4.1555 | J32: =H32*I32 -> -7829.0627 | K32: 4.1545 | L32: =H32*K32 -> -7827.1787 | M32: =J32-L32 -> -1.8840242 | N32: 4.075 | O32: =H32*N32 -> -7677.3988 | P32: =L32-O32 -> -149.77993 | Q32: 4.017 | R32: =H32*Q32 -> -7568.1254 | S32: =O32-R32 -> -109.27341 | T32: 4.045 | U32: =H32*T32 -> -7620.8781 | V32: =R32-U32 -> 52.752679 | W32: 4.0495 | X32: =H32*W32 -> -7629.3562 | Y32: 4.146 | Z32: =H32*$Y$14 -> -7811.1645 | AA32: 4.0975 | AB32: =U32-X32 -> 8.4781091 | AC32: =H32*$AA$14 -> -7719.7893 | AD32: =Z32-AC32 -> -91.375176
A33: 32 | B33: WSA Venture Australia (M) Sdn Bhd | C33: Trade | D33: Islamic | E33: SME | F33: Non Auto Mora | G33: USD | H33: -1143.2671 | I33: 4.1555 | J33: =H33*I33 -> -4750.8466 | K33: 4.1545 | L33: =H33*K33 -> -4749.7033 | M33: =J33-L33 -> -1.1432671 | N33: 4.075 | O33: =H33*N33 -> -4658.8136 | P33: =L33-O33 -> -90.889738 | Q33: 4.017 | R33: =H33*Q33 -> -4592.5041 | S33: =O33-R33 -> -66.309494 | T33: 4.045 | U33: =H33*T33 -> -4624.5156 | V33: =R33-U33 -> 32.01148 | W33: 4.0495 | X33: =H33*W33 -> -4629.6603 | Y33: 4.146 | Z33: =H33*$Y$14 -> -4739.9856 | AA33: 4.0975 | AB33: =U33-X33 -> 5.1447021 | AC33: =H33*$AA$14 -> -4684.5371 | AD33: =Z33-AC33 -> -55.448456
A34: 33 | B34: Hyrax Oil (LCTR) | C34: Trade | D34: Islamic | E34: SME | F34: Non Auto Mora | G34: USD | H34: -179.70601 | I34: 4.1555 | J34: =H34*I34 -> -746.7683 | K34: 4.1545 | L34: =H34*K34 -> -746.5886 | M34: =J34-L34 -> -0.17970601 | N34: 4.075 | O34: =H34*N34 -> -732.30197 | P34: =L34-O34 -> -14.286627 | Q34: 4.017 | R34: =H34*Q34 -> -721.87902 | S34: =O34-R34 -> -10.422948 | T34: 4.045 | U34: =H34*T34 -> -726.91079 | V34: =R34-U34 -> 5.0317681 | W34: 4.0495 | X34: =H34*W34 -> -727.71947 | Y34: 4.146 | Z34: =H34*$Y$14 -> -745.0611 | AA34: 4.0975 | AB34: =U34-X34 -> 0.80867702 | AC34: =H34*$AA$14 -> -736.34536 | AD34: =Z34-AC34 -> -8.7157413
A35: 34 | B35: Hyrax Oil (OPF-I 1) | C35: Non trade | D35: Islamic | E35: SME | F35: Non Auto Mora | G35: USD | H35: -36268.48 | I35: 4.1555 | J35: =H35*I35 -> -150713.67 | K35: 4.1545 | L35: =H35*K35 -> -150677.4 | M35: =J35-L35 -> -36.26848 | N35: 4.075 | O35: =H35*N35 -> -147794.06 | P35: =L35-O35 -> -2883.3442 | Q35: 4.017 | R35: =H35*Q35 -> -145690.48 | S35: =O35-R35 -> -2103.5718 | T35: 4.045 | U35: =H35*T35 -> -146706 | V35: =R35-U35 -> 1015.5174 | W35: 4.0495 | X35: =H35*W35 -> -146869.21 | Y35: 4.146 | Z35: =H35*$Y$14 -> -150369.12 | AA35: 4.0975 | AB35: =U35-X35 -> 163.20816 | AC35: =H35*$AA$14 -> -148610.1 | AD35: =Z35-AC35 -> -1759.0213
A36: 35 | B36: Hyrax Oil (OPF-I 2) | C36: Non trade | D36: Islamic | E36: SME | F36: Non Auto Mora | G36: USD | H36: 2605.4616 | I36: 4.1555 | J36: =H36*I36 -> 10826.996 | K36: 4.1545 | L36: =H36*K36 -> 10824.39 | M36: =J36-L36 -> 2.6054616 | N36: 4.075 | O36: =H36*N36 -> 10617.256 | P36: =L36-O36 -> 207.13419 | Q36: 4.017 | R36: =H36*Q36 -> 10466.139 | S36: =O36-R36 -> 151.11677 | T36: 4.045 | U36: =H36*T36 -> 10539.092 | V36: =R36-U36 -> -72.952924 | W36: 4.0495 | X36: =H36*W36 -> 10550.817 | Y36: 4.146 | Z36: =H36*$Y$14 -> 10802.244 | AA36: 4.0975 | AB36: =U36-X36 -> -11.724577 | AC36: =H36*$AA$14 -> 10675.879 | AD36: =Z36-AC36 -> 126.36489
A37: 36 | B37: Istanbul Sabiha Gocken | C37: Non trade | D37: Conventional | E37: Non SME | F37: Non Auto Mora | G37: EUR | H37: 440822.79 | I37: 4.8661 | J37: =H37*I37 -> 2145087.8 | K37: 4.8479 | L37: =H37*K37 -> 2137064.8 | M37: =J37-L37 -> 8022.9748 | N37: 4.8812 | O37: =H37*N37 -> 2151744.2 | P37: =L37-O37 -> -14679.399 | Q37: 4.9413 | R37: =H37*Q37 -> 2178237.6 | S37: =O37-R37 -> -26493.45 | T37: 4.901 | U37: =H37*T37 -> 2160472.5 | V37: =R37-U37 -> 17765.158 | W37: 4.9201 | X37: =H37*W37 -> 2168892.2 | Y37: 4.8699 | Z37: =H37*$Y$14 -> 1827651.3 | AA37: 5.6986 | AB37: =U37-X37 -> -8419.7153 | AC37: =H37*AA37 -> 2512072.7 | AD37: =Z37-AC37 -> -684421.46
B39: TOTAL | G39: USD | H39: =SUMIF(G2:G37,G39,H2:H37) -> -10648605 | T39: MYR | U39: =SUM(U2:U37) -> -47369416 | W39: MYR | X39: =SUM(X2:X37) -> -47464444 | Y39: MYR | Z39: =SUM(Z2:Z37) -> -48833275 | AC39: =SUM(AC2:AC37) -> -41176115 | AD39: =SUM(AD31:AD36,AD19:AD29) -> -116665.15
G40: EUR | H40: =SUMIF(G3:G38,G40,H3:H38) -> 440822.79
G41: MYR | H41: =SUMIF(G2:G37,G41,H2:H37) -> -6456281.5
AD43: GL March 2021 | AE43: 16274157
B44: Conventional - Non SME - NT | AD44: GL April 2021 | AE44: -16429347
A45: 1 | B45: Impiana Ubud (Labuan) Co. Ltd | C45: USD | D45: -6585324.3 | AD45: GL | AE45: =SUM(AE43:AE44) -> -155190.47
A46: 2 | B46: Pertama Ferraalloys Sdn Bhd | C46: USD | D46: -37664.752 | AD46: Frx movement | AE46: =AD39+AE45 -> -271855.62
A47: 3 | B47: Pertama Ferraalloys Sdn Bhd | C47: USD | D47: -61497.389
A48: 4 | B48: Pertama Ferraalloys Sdn Bhd | C48: USD | D48: -87180.238
A49: 5 | B49: Istanbul Sabiha Gocken | C49: EUR | D49: 440822.79
B50: TOTAL | C50: USD | D50: =SUM(D45:D48) -> -6771666.6
B51: TOTAL | C51: EUR | D51: =D49 -> 440822.79
B53: Conventional - SME - NT
B54: Façade Treatment Engineering | C54: MYR | D54: 0
A55: 6 | B55: Wok Delights Sdn Bhd | C55: MYR | D55: -55529.455
A56: 7 | B56: Superboom Projects Sdn Bhd | C56: USD | D56: -1463337.6
B58: Conventional - SME - Trade
A59: 8 | B59: Mir Valve | C59: USD | D59: -8133.6474
B61: Islamic - SME - NT
A62: 9 | B62: Ingress Katayama technical centre (IF-i) | C62: MYR | D62: -451147.24
A63: 10 | B63: Ingress Katayama technical centre (TF-i) | C63: MYR | D63: -329666.72
A64: =A63+1 -> 11 | B64: Lipidchem 1 | C64: MYR | D64: -33516.044
A65: =A64+1 -> 12 | B65: Lipidchem 2 | C65: MYR | D65: -261559.97
A66: =A65+1 -> 13 | B66: PWN Excellence Sdn Bhd 1 | C66: MYR | D66: -3212958.2
A67: =A66+1 -> 14 | B67: PWN Excellence Sdn Bhd 2 | C67: MYR | D67: -306100.55
A68: =A67+1 -> 15 | B68: PWN Excellence Sdn Bhd 3 | C68: MYR | D68: -1662540.6
A69: =A68+1 -> 16 | B69: Tabco Food | C69: MYR | D69: -85330.865
A70: =A69+1 -> 17 | B70: Tabco food | C70: MYR | D70: -107821.04
A71: =A70+1 -> 18 | B71: Helms Geomarine | C71: USD | D71: -15168.479
A72: =A71+1 -> 19 | B72: Smart Glove Corporation Sdn Bhd | C72: USD | D72: -385716.25
A73: =A72+1 -> 20 | B73: SMH Rail Sdn Bhd 1 | C73: USD | D73: -46526.4
A74: =A73+1 -> 21 | B74: SMH Rail Sdn Bhd 2 | C74: USD | D74: -77178.265
A75: =A74+1 -> 22 | B75: SMH Rail Sdn Bhd 3 | C75: USD | D75: -197021.63
... A78: =A77+1 -> 25 | B78: Hyrax Oil (OPF-I 2) | C78: USD | D78: 2605.4616
B79: TOTAL | C79: MYR | D79: =SUMIF(C62:C78,C79,D62:D78) -> -6450641.2
B80: TOTAL | C80: USD | D80: =SUMIF(C62:C78,C80,D62:D78) -> -926004.69
B83: Islamic - SME - Trade
A84: =A78+1 -> 26 | B84: UCM Industrial Corporation | C84: MYR | D84: -5640.3697
A85: =A84+1 -> 27 | B85: Envico Enterprises Sdn Bhd | C85: USD | D85: -13002.709
A86: =A85+1 -> 28 | B86: International Brass | C86: USD | D86: -2352.5762
A87: =A86+1 -> 29 | B87: Nupon Technology Sdn Bhd | C87: USD | D87: -683.1548
A88: =A87+1 -> 30 | B88: Wilson International trading | C88: USD | D88: -14745.363
A89: =A88+1 -> 31 | B89: WSA Venture Australia (M) Sdn Bhd | C89: USD | D89: -1884.0242
A90: =A89+1 -> 32 | B90: WSA Venture Australia (M) Sdn Bhd | C90: USD | D90: -1143.2671
A91: =A90+1 -> 33 | B91: Hyrax Oil (LCTR) | C91: USD | D91: -179.70601
B92: TOTAL | C92: MYR | D92: =SUMIF(C84:C91,C92,D84:D91) -> -5640.3697
B93: TOTAL | C93: USD | D93: =SUMIF(C84:C91,C93,D84:D91) -> -33990.8
B95: Islamic - Non SME - NT
A96: =A91+1 -> 34 | B96: Impiana Seminyak (Labuan) Co Ltd (OIF-i 1) | C96: USD | D96: -1292915.6
A97: =A96+1 -> 35 | B97: Impiana Seminyak (Labuan) Co Ltd (OIF-i 2) | C97: USD | D97: -167301.16
B98: TOTAL | C98: USD | D98: =SUBTOTAL(9,D96:D97) -> -1460216.8
C100: USD | D100: =D98+D93+D80+D59+D56+D50 -> -10663350 | E100: =T30 -> 4.045 | F100: =D100*E100 -> -43133251
C101: MYR | D101: =D92+D79+D55 -> -6511811 | E101: =T2 -> 1 | F101: =D101*E101 -> -6511811
C102: EUR | D102: =D51 -> 440822.79 | E102: =T37 -> 4.901 | F102: =D102*E102 -> 2160472.5
F103: =SUM(F100:F102) -> -47484590
F104: =F103-U39 -> -115174.45 | G104: check

Sheet Debtors Listing (C) Feb2021
A1: Customer Balances as at February 2021
A3: Customer Account Number | B3: Customer Class & Industry | C3: Customer Name | D3: Loan Currency | E3: Opening Principal | F3: Disbursement | G3: Adjustment Capitalization | H3: Forex ( + ) | I3: Repayment | J3: Adjustment Capitalization | K3: Forex ( - ) | L3: Closing Principal
A5: 500470 | C5: MINISTRY OF FINANCE - LAO PDR | D5: USD | E5: 78877500 | F5: 0 | G5: 0 | H5: 87750.02 | I5: 0 | J5: 0 | K5: 0 | L5: 78965250
A6: 500937 | C6: THE MINISTRY OF FINANCE LAOS 2 | D6: USD | E6: 2.6166874e+08 | F6: 0 | G6: 0 | H6: 273602.45 | I6: -7069125 | J6: 0 | K6: 0 | L6: 2.5487322e+08
B7: Active (Cross Border Credit) (Buyer Credit) | E7: 3.4054624e+08 | F7: 0 | G7: 0 | H7: 361352.47 | I7: -7069125 | J7: 0 | K7: 0 | L7: 3.3383847e+08
A9: 500878 | C9: WOK DELIGHTS SDN BHD | D9: MYR | E9: 995874.1 | F9: 0 | G9: 0 | H9: 0 | I9: 0 | J9: 0 | K9: 0 | L9: 995874.1
B10: Active (Malaysia Kitchen Fin) | E10: 995874.1 | F10: 0 | G10: 0 | H10: 0 | I10: 0 | J10: 0 | K10: 0 | L10: 995874.1
A12: 500679 | C12: BUMI ARMADA CAPITAL OFFSHORE LTD | D12: USD | E12: 1.8836661e+08 | F12: 0 | G12: 0 | H12: 201367.48 | I12: -5092611.2 | J12: 0 | K12: 0 | L12: 1.8347536e+08
A13: 500708 | C13: SAPURAKENCANA TMC SDN BHD (1) | D13: USD | E13: 14842830 | F13: 0 | G13: 0 | H13: 16512.41 | I13: 0 | J13: 0 | K13: 0 | L13: 14859343
A14: 500709 | C14: SAPURAKENCANA TMC SDN BHD (2) | D14: USD | E14: 60056902 | F14: 0 | G14: 0 | H14: 66812.38 | I14: 0 | J14: 0 | K14: 0 | L14: 60123714
A15: 500749 | C15: ISTANBUL SABIHA GOKCEN ULUSLARARASI | D15: EUR | E15: 188692350 | F15: 0 | G15: 0 | H15: 731500 | I15: 0 | J15: 0 | K15: 0 | L15: 189423850
B16: Active (Overseas Investment) | E16: 4.5195869e+08 | F16: 0 | G16: 0 | H16: 1016192.3 | I16: -5092611.2 | J16: 0 | K16: 0 | L16: 4.4788227e+08
A18: 500271 | C18: MBI Development D.O.O, Bosnia&Herze | D18: EUR | E18: 2620911.4 | F18: 0 | G18: 0 | H18: 10160.45 | I18: 0 | J18: 0 | K18: 0 | L18: 2631071.9
A19: 500590 | C19: MBI Development 2 | D19: EUR | E19: 5875820.2 | F19: 0 | G19: 0 | H19: 22778.68 | I19: 0 | J19: 0 | K19: 0 | L19: 5898598.9
A20: 500640 | C20: OM MATERIAL (SARAWAK) SDN BHD | D20: USD | E20: 1.1694665e+08 | F20: 0 | G20: 0 | H20: 130101.37 | I20: 0 | J20: 0 | K20: 0 | L20: 1.1707676e+08
A21: 500642 | C21: OM MATERIAL (SARAWAK) 2 | D21: USD | E21: 1.5856435e+08 | F21: 0 | G21: 0 | H21: 176400.39 | I21: 0 | J21: 0 | K21: 0 | L21: 1.5874075e+08
A22: 500805 | C22: Armada Kraken Pte Ltd (OPF) | D22: USD | E22: 1.1812858e+08 | F22: 0 | G22: 0 | H22: 131416.25 | I22: 0 | J22: 0 | K22: 0 | L22: 1.1826e+08
A23: 500807 | C23: Pertama Ferroalloys Sdn Bhd (2) | D23: USD | E23: 49397282 | F23: 0 | G23: 0 | H23: 54953.74 | I23: 0 | J23: 0 | K23: 0 | L23: 49452236
A24: 500808 | C24: Pertama Ferroalloys Sdn Bhd (1) | D24: USD | E24: 30459996 | F24: 0 | G24: 0 | H24: 33886.25 | I24: 0 | J24: 0 | K24: 0 | L24: 30493883
A25: 500827 | C25: Pertama Ferroalloys Sdn Bhd (3) | D25: USD | E25: 66874025 | F25: 0 | G25: 0 | H25: 74396.31 | I25: 0 | J25: 0 | K25: 0 | L25: 66948422
A26: 500885 | C26: SUPERBOOM PROJECTS SDN BHD | D26: USD | E26: 80640909 | F26: 0 | G26: 0 | H26: 89711.76 | I26: 0 | J26: 0 | K26: 0 | L26: 80730621
A27: 500905 | C27: ZICO HOLDINGS INC (OPF) | D27: SGD | E27: 2096795.7 | F27: 0 | G27: 0 | H27: 7100.3 | I27: -123693.72 | J27: 0 | K27: 0 | L27: 1980202.3
A28: 500914 | C28: IMPIANA UBUD (LABUAN) CO. LTD. | D28: USD | E28: 88383250 | F28: 0 | G28: 0 | H28: 98324.99 | I28: 0 | J28: 0 | K28: 0 | L28: 88481575
A29: 500927 | C29: BRITISH UNIVERSITY VIETNAM | D29: USD | E29: 76120303 | F29: 0 | G29: 0 | H29: 84682.65 | I29: 0 | J29: 0 | K29: 0 | L29: 76204986
A30: 501031 | C30: YINSON BORONIA PRODUCTION BV | D30: USD | E30: 67770353 | F30: 39973550 | G30: 0 | H30: 70458.47 | I30: 0 | J30: 0 | K30: 0 | L30: 1.0781436e+08
B31: Active (Overseas Projec Fin) | E31: 8.6387923e+08 | F31: 39973550 | G31: 0 | H31: 984371.61 | I31: -123693.72 | J31: 0 | K31: 0 | L31: 9.0471346e+08
A33: 500538 | C33: MIR VALVE SDN BHD | D33: USD | E33: 11176113 | F33: 215902.85 | G33: 0 | H33: 9421.69 | I33: -546085.42 | J33: 0 | K33: 0 | L33: 10855352
A34: 500693 | C34: PERUSAHAAN OTOMOBIL NASIONAL (VF) | D34: MYR | E34: 8666976.7 | F34: 0 | G34: 0 | H34: 0 | I34: -4368985.7 | J34: 0 | K34: 0 | L34: 4297991
A35: 500724 | C35: OM Material (Sarawak) Sdn Bhd | D35: USD | E35: 64677657 | F35: 11916723 | G35: 0 | H35: 41262.7 | I35: -18160612 | J35: 0 | K35: 0 | L35: 58475031
A36: 500840 | C36: Pertama Ferroalloys (Trade) | D36: USD | E36: 29422342 | F36: 4283779.6 | G36: 0 | H36: 12874.55 | I36: -10020493 | J36: 0 | K36: 0 | L36: 23698502
B37: Active (Supplier Credit) (Trade Finance) | E37: =SUM(E33:E36) -> 1.1394309e+08 | F37: 16416406 | G37: 0 | H37: 63558.94 | I37: -33096176 | J37: 0 | K37: 0 | L37: =SUM(L33:L36) -> 97326876
A39: 501000 | C39: Brahim's Overseas Venture Sdn Bhd | D39: MYR | E39: 15467576 | F39: 0 | G39: 0 | H39: 0 | I39: 0 | J39: 0 | K39: 0 | L39: 15467576
B40: Active (Term Loan) | E40: 15467576 | F40: 0 | G40: 0 | H40: 0 | I40: 0 | J40: 0 | K40: 0 | L40: 15467576
A42: 500010 | C42: PT BUMI INTERNATIONAL TANKERS | D42: USD | E42: 11362164 | F42: 0 | G42: 0 | H42: 12640.21 | I42: 0 | J42: 0 | K42: 0 | L42: 11374804
A43: 500011 | C43: PT LAYAR SENTOSA | D43: USD | E43: 11534960 | F43: 0 | G43: 0 | H43: 12832.47 | I43: 0 | J43: 0 | K43: 0 | L43: 11547793
A44: 500042 | C44: PT EDEN CAPITAL INDONESIA | D44: USD | E44: 12287617 | F44: 0 | G44: 0 | H44: 13669.78 | I44: 0 | J44: 0 | K44: 0 | L44: 12301287
A45: 500265 | C45: PT SARI INDAH LESTARI | D45: USD | E45: 72327070 | F45: 0 | G45: 0 | H45: 80462.77 | I45: 0 | J45: 0 | K45: 0 | L45: 72407532
A46: 500274 | C46: HONDAAFUSHI INVESTMENT PVT LTD | D46: USD | E46: 35976152 | F46: 0 | G46: 0 | H46: 40022.92 | I46: 0 | J46: 0 | K46: 0 | L46: 36016175
A47: 500913 | C47: PT SRIWIJAYA AIR | D47: USD | E47: 3.2724583e+08 | F47: 0 | G47: 0 | H47: 364055.94 | I47: 0 | J47: 0 | K47: 0 | L47: 3.2760988e+08
B48: Impaired Loan (Buyer Credit) | E48: 4.7073379e+08 | F48: 0 | G48: 0 | H48: 523684.09 | I48: 0 | J48: 0 | K48: 0 | L48: 4.7125747e+08
A50: 500546 | C50: FRESH BOWL FOODS LIMITED | D50: MYR | E50: 387000.01 | F50: 0 | G50: 0 | H50: 0 | I50: -4125.69 | J50: 0 | K50: 0 | L50: 382874.32
A51: 500560 | C51: PANNAH RESOURCES 1 | D51: MYR | E51: 707800 | F51: 0 | G51: 0 | H51: 0 | I51: -23000 | J51: 0 | K51: 0 | L51: 684800
A52: 500577 | C52: NIRMALA VILAS RESTAURANT SDN BHD | D52: MYR | E52: 747562.14 | F52: 0 | G52: 0 | H52: 0 | I52: 0 | J52: 0 | K52: 0 | L52: 747562.14
A53: 500644 | C53: GOLD RAIN RESOURCES | D53: MYR | E53: 1067187.6 | F53: 0 | G53: 0 | H53: 0 | I53: 0 | J53: 0 | K53: 0 | L53: 1067187.6
A54: 500758 | C54: 3 PLUS1 STUDIO SDN BHD 2 | D54: MYR | E54: 975206.98 | F54: 0 | G54: 0 | H54: 0 | I54: 0 | J54: 0 | K54: 0 | L54: 975206.98
A55: 500806 | C55: I & C EATING NETWORK INTERNATIONAL | D55: MYR | E55: 988584.59 | F55: 0 | G55: 0 | H55: 0 | I55: 0 | J55: 0 | K55: 0 | L55: 988584.59
A56: 500852 | C56: NEE ASSETS SDN BHD | D56: MYR | E56: 539751.12 | F56: 0 | G56: 0 | H56: 0 | I56: 0 | J56: 0 | K56: 0 | L56: 539751.12
A57: 500866 | C57: NEE ASSETS SDN BHD 1 | D57: MYR | E57: 116666.69 | F57: 0 | G57: 0 | H57: 0 | I57: 0 | J57: 0 | K57: 0 | L57: 116666.69
B58: Impaired Loan (Malaysia Kitchen Fin) | E58: 5529759.1 | F58: 0 | G58: 0 | H58: 0 | I58: -27125.69 | J58: 0 | K58: 0 | L58: 5502633.4
A60: 500515 | C60: SCOMI TRANSIT PROJECTS BRAZIL | D60: USD | E60: 33141389 | F60: 0 | G60: 0 | H60: 36869.28 | I60: 0 | J60: 0 | K60: 0 | L60: 33178258
B61: Impaired Loan (Overseas Contract Fi) | E61: 33141389 | F61: 0 | G61: 0 | H61: 36869.28 | I61: 0 | J61: 0 | K61: 0 | L61: 33178258
A63: 500776 | C63: HUMMINGBIRD ENERGY (L) INC (OIF) | D63: USD | E63: 71610819 | F63: 0 | G63: 0 | H63: 79665.93 | I63: 0 | J63: 0 | K63: 0 | L63: 71690485
A64: 500980 | C64: VEERAM STONES PVT LTD | D64: USD | E64: 2527113.8 | F64: 0 | G64: 0 | H64: 2811.34 | I64: 0 | J64: 0 | K64: 0 | L64: 2529925.1
B65: Impaired Loan (Overseas Investment) | E65: 74137933 | F65: 0 | G65: 0 | H65: 82477.27 | I65: 0 | J65: 0 | K65: 0 | L65: 74220410
A67: 500297 | C67: PHOENIX SURGE SDN BHD (111) | D67: USD | E67: 3817472.2 | F67: 0 | G67: 0 | H67: 4247.79 | I67: 0 | J67: 0 | K67: 0 | L67: 3821720
A68: 500522 | C68: VIRTUAL PEAKS GROUP SDN BHD | D68: USD | E68: 6588176.4 | F68: 0 | G68: 0 | H68: 7329.25 | I68: 0 | J68: 0 | K68: 0 | L68: 6595505.7
A69: 500557 | C69: MARKMORE ENERGY 1 | D69: USD | E69: 1.4164969e+08 | F69: 0 | G69: 0 | H69: 157583.11 | I69: 0 | J69: 0 | K69: 0 | L69: 1.4180727e+08
A70: 500558 | C70: MARKMORE ENERGY II | D70: USD | E70: 1.6143062e+08 | F70: 0 | G70: 0 | H70: 179589.07 | I70: 0 | J70: 0 | K70: 0 | L70: 1.6161021e+08
A71: 500576 | C71: ILEAVES (UK) LTD | D71: GBP | E71: 3253085.5 | F71: 0 | G71: 0 | H71: 64265.15 | I71: 0 | J71: 0 | K71: 0 | L71: 3317350.7
A72: 500631 | C72: MALAYSIAN DELICACIES PTY LTD | D72: AUD | E72: 608615.18 | F72: 0 | G72: 0 | H72: 15032.14 | I72: 0 | J72: 0 | K72: 0 | L72: 623647.32
A73: 500781 | C73: HUMMINGBIRD ENERGY (L) INC (OPF) | D73: USD | E73: 14966500 | F73: 0 | G73: 0 | H73: 16650 | I73: 0 | J73: 0 | K73: 0 | L73: 14983150
A74: 500883 | C74: UPL LAO CO. LTD 1 | D74: USD | E74: 8637154.6 | F74: 0 | G74: 0 | H74: 9608.7 | I74: 0 | J74: 0 | K74: 0 | L74: 8646763.3
A75: 500884 | C75: UPL LAO CO. LTD 2 | D75: USD | E75: 15225099 | F75: 0 | G75: 0 | H75: 16937.68 | I75: 0 | J75: 0 | K75: 0 | L75: 15242036
B76: Impaired Loan (Overseas Projec Fin) | E76: 3.5617642e+08 | F76: 0 | G76: 0 | H76: 471242.89 | I76: 0 | J76: 0 | K76: 0 | L76: 3.5664766e+08
A78: 500187 | C78: JEWEL GROWTH SDN BHD | D78: MYR | E78: 26832.06 | F78: 0 | G78: 0 | H78: 0 | I78: 0 | J78: 0 | K78: 0 | L78: 26832.06
A79: 500197 | C79: VEHENG GLOBAL TRADERS SDN BHD | D79: MYR | E79: 8200000 | F79: 0 | G79: 0 | H79: 0 | I79: 0 | J79: 0 | K79: 0 | L79: 8200000
B80: Impaired Loan (Supplier Credit) (Trade Finance) | E80: 8226832.1 | F80: 0 | G80: 0 | H80: 0 | I80: 0 | J80: 0 | K80: 0 | L80: 8226832.1
A82: 500962 | C82: Scomi Transit Projects Brazil | E82: 40515000 | F82: 0 | G82: 0 | H82: 0 | I82: 0 | J82: 0 | K82: 0 | L82: 40515000
B83: Impaired Loan (Term Loan) | E83: 40515000 | F83: 0 | G83: 0 | H83: 0 | I83: 0 | J83: 0 | K83: 0 | L83: 40515000
A85: 500039 | C85: PT MAHAKARYA INTI BUANA | D85: USD | E85: 11478912 | F85: 0 | G85: 0 | H85: 12770.12 | I85: 0 | J85: 0 | K85: 0 | L85: 11491682
A86: 500613 | C86: HARTAMANIS (S) PTE LTD (TL2) | D86: MYR | E86: 7458382.5 | F86: 0 | G86: 0 | H86: 0 | I86: 0 | J86: 0 | K86: 0 | L86: 7458382.5
B87: Restuctured | E87: 18937295 | F87: 0 | G87: 0 | H87: 12770.12 | I87: 0 | J87: 0 | K87: 0 | L87: 18950065
A89: 500512 | C89: AL-MANARA WATER COMPANY LIMITED | D89: EUR | E89: 1.0310207e+08 | F89: 0 | G89: 0 | H89: 399693.8 | I89: 0 | J89: 0 | K89: 0 | L89: 1.0350176e+08
B90: Restuctured (Buyer Credit) | E90: 1.0310207e+08 | F90: 0 | G90: 0 | H90: 399693.8 | I90: 0 | J90: 0 | K90: 0 | L90: 1.0350176e+08
A92: 500555 | C92: SOLARTIF SDN BHD | D92: MYR | E92: 696182.84 | F92: 0 | G92: 0 | H92: 0 | I92: 0 | J92: 0 | K92: 0 | L92: 696182.84
B93: Restuctured (Supplier Credit) (Trade Finance) | E93: 696182.84 | F93: 0 | G93: 0 | H93: 0 | I93: 0 | J93: 0 | K93: 0 | L93: 696182.84
A95: 500400 | C95: THE REPUBLIC OF IRAQ | D95: USD | E95: 2324549.5 | F95: 0 | G95: 0 | H95: 2586.04 | I95: 0 | J95: 0 | K95: 0 | L95: 2327135.6
A96: 500401 | C96: THE REPUBLIC OF SEYCHELLES | D96: USD | E96: 18688677 | F96: 0 | G96: 0 | H96: 20790.88 | I96: 0 | J96: 0 | K96: 0 | L96: 18709468
B97: Restuctured (Term Loan) | E97: 21013226 | F97: 0 | G97: 0 | H97: 23376.92 | I97: 0 | J97: 0 | K97: 0 | L97: 21036603
E100: =E97+E93+E90+E87+E83+E80+E76+E65+E61+E58+E48+E40+E37+E31+E16+E10+E7 -> 2.9190006e+09 | F100: 56389956 | G100: 0 | H100: 3975589.7 | I100: -45408732 | J100: 0 | K100: 0 | L100: =L97+L93+L90+L87+L83+L80+L76+L65+L61+L58+L48+L40+L37+L31+L16+L10+L7 -> 2.9339574e+09

Sheet Debtors Listing (C) Apr2021
A1: Customer Balances as at April 2021
A3: Customer Account Number | B3: Customer Class & Industry | C3: Customer Name | D3: Loan Currency | E3: Opening Principal | F3: Disbursement | G3: Adjustment Capitalization | H3: Forex ( + ) | I3: Repayment | J3: Adjustment Capitalization | K3: Forex ( - ) | L3: Closing Principal
E5: 76769911 | F5: 0 | G5: 0 | H5: 0 | I5: 0 | J5: 0 | K5: -898056.12 | L5: 75871855
A6: 500470 | C6: MINISTRY OF FINANCE - LAO PDR | D6: USD | E6: 74109750 | F6: 0 | G6: 0 | H6: 0 | I6: 0 | J6: 0 | K6: -866937.48 | L6: 73242812
A7: 500937 | C7: THE MINISTRY OF FINANCE LAOS 2 | D7: USD | E7: 2.829645e+08 | F7: 0 | G7: 0 | H7: 0 | I7: 0 | J7: 0 | K7: -3310125 | L7: 2.7965437e+08
B8: Active (Cross Border Credit) (Buyer Credit) | E8: 3.5707425e+08 | F8: 0 | G8: 0 | H8: 0 | I8: 0 | J8: 0 | K8: -4177062.5 | L8: 3.5289719e+08
A10: 500878 | C10: WOK DELIGHTS SDN BHD | D10: MYR | E10: 863090.9 | F10: 0 | G10: 0 | H10: 0 | I10: -66391.6 | J10: 0 | K10: 0 | L10: 796699.3
B11: Active (Malaysia Kitchen Fin) | E11: 863090.9 | F11: 0 | G11: 0 | H11: 0 | I11: -66391.6 | J11: 0 | K11: 0 | L11: 796699.3
A13: 500679 | C13: BUMI ARMADA CAPITAL OFFSHORE LTD | D13: USD | E13: 1.8414164e+08 | F13: 0 | G13: 0 | H13: 0 | I13: -183626.87 | J13: 0 | K13: -2153588 | L13: 1.8180443e+08
A14: 500749 | C14: ISTANBUL SABIHA GOKCEN ULUSLARARASI | D14: EUR | E14: 187491150 | F14: 0 | G14: 0 | H14: 3311000 | I14: 0 | J14: 0 | K14: 0 | L14: 190802150
B15: Active (Overseas Investment) | E15: 3.7163279e+08 | F15: 0 | G15: 0 | H15: 3311000 | I15: -183626.87 | J15: 0 | K15: -2153588 | L15: 3.7260658e+08
A17: 500271 | C17: MBI Development D.O.O, Bosnia&Herze | D17: EUR | E17: 262827.1 | F17: 0 | G17: 0 | H17: 4641.45 | I17: 0 | J17: 0 | K17: 0 | L17: 267468.55
A18: 500590 | C18: MBI Development 2 | D18: EUR | E18: 5838415.2 | F18: 0 | G18: 0 | H18: 103103.5 | I18: 0 | J18: 0 | K18: 0 | L18: 5941518.7
A19: 500640 | C19: OM MATERIAL (SARAWAK) SDN BHD | D19: USD | E19: 1.1750349e+08 | F19: 0 | G19: 0 | H19: 0 | I19: 0 | J19: 0 | K19: -1374558.4 | L19: 1.1612893e+08
A20: 500642 | C20: OM MATERIAL (SARAWAK) 2 | D20: USD | E20: 1.5941406e+08 | F20: 0 | G20: 0 | H20: 0 | I20: 0 | J20: 0 | K20: -1864829.2 | L20: 1.5754923e+08
A21: 500805 | C21: Armada Kraken Pte Ltd (OPF) | D21: USD | E21: 1.1092586e+08 | F21: 0 | G21: 0 | H21: 0 | I21: 0 | J21: 0 | K21: -1297613.1 | L21: 1.0962824e+08
A22: 500807 | C22: Pertama Ferroalloys Sdn Bhd (2) | D22: USD | E22: 50630688 | F22: 0 | G22: 0 | H22: 0 | I22: 0 | J22: 0 | K22: -592278.92 | L22: 50038409
A23: 500808 | C23: Pertama Ferroalloys Sdn Bhd (1) | D23: USD | E23: 31220555 | F23: 0 | G23: 0 | H23: 0 | I23: 0 | J23: 0 | K23: -365218.76 | L23: 30855336
A24: 500827 | C24: Pertama Ferroalloys Sdn Bhd (3) | D24: USD | E24: 68543809 | F24: 0 | G24: 0 | H24: 0 | I24: 0 | J24: 0 | K24: -801827.01 | L24: 67741982
A25: 500885 | C25: SUPERBOOM PROJECTS SDN BHD | D25: USD | E25: 82654440 | F25: 0 | G25: 0 | H25: 0 | I25: 0 | J25: 0 | K25: -966893.47 | L25: 81687547
A26: 500905 | C26: ZICO HOLDINGS INC (OPF) | D26: SGD | E26: 1834454.8 | F26: 0 | G26: 0 | H26: 838.12 | I26: -166633.48 | J26: 0 | K26: 0 | L26: 1668659.4
A27: 500914 | C27: IMPIANA UBUD (LABUAN) CO. LTD. | D27: USD | E27: 90590100 | F27: 0 | G27: 0 | H27: 0 | I27: 0 | J27: 0 | K27: -1059725 | L27: 89530375
A28: 500927 | C28: BRITISH UNIVERSITY VIETNAM | D28: USD | E28: 78020958 | F28: 0 | G28: 0 | H28: 0 | I28: 0 | J28: 0 | K28: -912690.9 | L28: 77108268
A29: 501031 | C29: YINSON BORONIA PRODUCTION BV | D29: USD | E29: 2.3088432e+08 | F29: 41936971 | G29: 0 | H29: 0 | I29: 0 | J29: 0 | K29: -2853851.4 | L29: 2.6996744e+08
B30: Active (Overseas Projec Fin) | E30: 1.028324e+09 | F30: 41936971 | G30: 0 | H30: 108583.07 | I30: -166633.48 | J30: 0 | K30: -12089486 | L30: 1.0581134e+09
A32: 500538 | C32: MIR VALVE SDN BHD | D32: USD | E32: 10726035 | F32: 28994.07 | G32: 0 | H32: 0 | I32: -3782349.9 | J32: 0 | K32: -91361.71 | L32: 6881317.9
A33: 500693 | C33: PERUSAHAAN OTOMOBIL NASIONAL (VF) | D33: MYR | E33: 5764426.8 | F33: 4081220.5 | G33: 0 | H33: 0 | I33: 0 | J33: 0 | K33: 0 | L33: 9845647.4
A34: 500724 | C34: OM Material (Sarawak) Sdn Bhd | D34: USD | E34: 61535868 | F34: 17499838 | G34: 0 | H34: 0 | I34: -5708646.6 | J34: 0 | K34: -752130.59 | L34: 72574929
A35: 500840 | C35: Pertama Ferroalloys (Trade) | D35: USD | E35: 24263240 | F35: 16871500 | G35: 0 | H35: 0 | I35: -19641102 | J35: 0 | K35: -355581.91 | L35: 21138056
B36: Active (Supplier Credit) (Trade Finance) | E36: =SUM(E32:E35) -> 1.0228957e+08 | F36: =SUM(F32:F35) -> 38481553 | G36: =SUM(G32:G35) -> 0 | H36: =SUM(H32:H35) -> 0 | I36: =SUM(I32:I35) -> -29132098 | J36: 0 | K36: =SUM(K32:K35) -> -1199074.2 | L36: =SUM(L32:L35) -> 1.1043995e+08
A38: 501000 | C38: Brahim's Overseas Venture Sdn Bhd | D38: MYR | E38: 15467576 | F38: 0 | G38: 0 | H38: 0 | I38: 0 | J38: 0 | K38: 0 | L38: 15467576
B39: Active (Term Loan) | E39: 15467576 | F39: 0 | G39: 0 | H39: 0 | I39: 0 | J39: 0 | K39: 0 | L39: 15467576
A41: 500010 | C41: PT BUMI INTERNATIONAL TANKERS | D41: USD | E41: 11645867 | F41: 0 | G41: 0 | H41: 0 | I41: 0 | J41: 0 | K41: -136233.6 | L41: 11509633
A42: 500011 | C42: PT LAYAR SENTOSA | D42: USD | E42: 11822978 | F42: 0 | G42: 0 | H42: 0 | I42: 0 | J42: 0 | K42: -138305.46 | L42: 11684673
A43: 500042 | C43: PT EDEN CAPITAL INDONESIA | D43: USD | E43: 12594428 | F43: 0 | G43: 0 | H43: 0 | I43: 0 | J43: 0 | K43: -147329.87 | L43: 12447098
A44: 500265 | C44: PT SARI INDAH LESTARI | D44: USD | E44: 74133011 | F44: 0 | G44: 0 | H44: 0 | I44: 0 | J44: 0 | K44: -867209.6 | L44: 73265802
A45: 500274 | C45: HONDAAFUSHI INVESTMENT PVT LTD | D45: USD | E45: 36874445 | F45: 0 | G45: 0 | H45: 0 | I45: 0 | J45: 0 | K45: -431358.07 | L45: 36443086
A46: 500913 | C46: PT SRIWIJAYA AIR | D46: USD | E46: 3.3541686e+08 | F46: 0 | G46: 0 | H46: 0 | I46: 0 | J46: 0 | K46: -3923713.8 | L46: 3.3149314e+08
B47: Impaired Loan (Buyer Credit) | E47: 4.8248759e+08 | F47: 0 | G47: 0 | H47: 0 | I47: 0 | J47: 0 | K47: -5644150.4 | L47: 4.7684344e+08
A49: 500546 | C49: FRESH BOWL FOODS LIMITED | D49: MYR | E49: 382874.32 | F49: 0 | G49: 0 | H49: 0 | I49: 0 | J49: 0 | K49: 0 | L49: 382874.32
A50: 500560 | C50: PANNAH RESOURCES 1 | D50: MYR | E50: 680800 | F50: 0 | G50: 0 | H50: 0 | I50: -4000 | J50: 0 | K50: 0 | L50: 676800
A51: 500577 | C51: NIRMALA VILAS RESTAURANT SDN BHD | D51: MYR | E51: 747562.14 | F51: 0 | G51: 0 | H51: 0 | I51: 0 | J51: 0 | K51: 0 | L51: 747562.14
A52: 500644 | C52: GOLD RAIN RESOURCES | D52: MYR | E52: 1067187.6 | F52: 0 | G52: 0 | H52: 0 | I52: 0 | J52: 0 | K52: 0 | L52: 1067187.6
A53: 500758 | C53: 3 PLUS1 STUDIO SDN BHD 2 | D53: MYR | E53: 975206.98 | F53: 0 | G53: 0 | H53: 0 | I53: 0 | J53: 0 | K53: 0 | L53: 975206.98
A54: 500806 | C54: I & C EATING NETWORK INTERNATIONAL | D54: MYR | E54: 988584.59 | F54: 0 | G54: 0 | H54: 0 | I54: 0 | J54: 0 | K54: 0 | L54: 988584.59
A55: 500852 | C55: NEE ASSETS SDN BHD | D55: MYR | E55: 539751.12 | F55: 0 | G55: 0 | H55: 0 | I55: 0 | J55: 0 | K55: 0 | L55: 539751.12
A56: 500866 | C56: NEE ASSETS SDN BHD 1 | D56: MYR | E56: 116666.69 | F56: 0 | G56: 0 | H56: 0 | I56: 0 | J56: 0 | K56: 0 | L56: 116666.69
B57: Impaired Loan (Malaysia Kitchen Fin) | E57: 5498633.4 | F57: 0 | G57: 0 | H57: 0 | I57: -4000 | J57: 0 | K57: 0 | L57: 5494633.4
A59: 500515 | C59: SCOMI TRANSIT PROJECTS BRAZIL | D59: USD | E59: 33968899 | F59: 0 | G59: 0 | H59: 0 | I59: 0 | J59: 0 | K59: -397368.95 | L59: 33571530
B60: Impaired Loan (Overseas Contract Fi) | E60: 33968899 | F60: 0 | G60: 0 | H60: 0 | I60: 0 | J60: 0 | K60: -397368.95 | L60: 33571530
A62: 500776 | C62: HUMMINGBIRD ENERGY (L) INC (OIF) | D62: USD | E62: 73398877 | F62: 0 | G62: 0 | H62: 0 | I62: 0 | J62: 0 | K62: -858621.7 | L62: 72540255
A63: 500980 | C63: VEERAM STONES PVT LTD | D63: USD | E63: 2590213.5 | F63: 0 | G63: 0 | H63: 0 | I63: 0 | J63: 0 | K63: -30300.41 | L63: 2559913.1
A64: 501045 | C64: Sapura TMC Sdn Bhd | D64: USD | E64: 76769911 | F64: 0 | G64: 0 | H64: 0 | I64: 0 | J64: 0 | K64: -898056.12 | L64: 75871855
B65: Impaired Loan (Overseas Investment) | E65: =SUM(E62:E64) -> 1.52759e+08 | F65: 0 | G65: 0 | H65: 0 | I65: 0 | J65: 0 | K65: =SUM(K62:K64) -> -1786978.2 | L65: =SUM(L62:L64) -> 1.5097202e+08
A67: 500297 | C67: PHOENIX SURGE SDN BHD (111) | D67: USD | E67: 3912812.3 | F67: 0 | G67: 0 | H67: 0 | I67: 0 | J67: 0 | K67: -45782.13 | L67: 3867030.1
A68: 500522 | C68: VIRTUAL PEAKS GROUP SDN BHD | D68: USD | E68: 6752677.3 | F68: 0 | G68: 0 | H68: 0 | I68: 0 | J68: 0 | K68: -78992.97 | L68: 6673684.3
A69: 500557 | C69: MARKMORE ENERGY 1 | D69: USD | E69: 1.4518655e+08 | F69: 0 | G69: 0 | H69: 0 | I69: 0 | J69: 0 | K69: -1698395.5 | L69: 1.4348816e+08
A70: 500558 | C70: MARKMORE ENERGY II | D70: USD | E70: 1.654614e+08 | F70: 0 | G70: 0 | H70: 0 | I70: 0 | J70: 0 | K70: -1935571.2 | L70: 1.6352583e+08
A71: 500576 | C71: ILEAVES (UK) LTD | D71: GBP | E71: 3356591.2 | F71: 0 | G71: 0 | H71: 0 | I71: 0 | J71: 0 | K71: -9046.46 | L71: 3347544.7
A72: 500631 | C72: MALAYSIAN DELICACIES PTY LTD | D72: AUD | E72: 620798.09 | F72: 0 | G72: 0 | H72: 4715.97 | I72: 0 | J72: 0 | K72: 0 | L72: 625514.06
A73: 500781 | C73: HUMMINGBIRD ENERGY (L) INC (OPF) | D73: USD | E73: 15340200 | F73: 0 | G73: 0 | H73: 0 | I73: 0 | J73: 0 | K73: -179450 | L73: 15160750
A74: 500883 | C74: UPL LAO CO. LTD 1 | D74: USD | E74: 8852816.6 | F74: 0 | G74: 0 | H74: 0 | I74: 0 | J74: 0 | K74: -103560.45 | L74: 8749256.1
A75: 500884 | C75: UPL LAO CO. LTD 2 | D75: USD | E75: 15605256 | F75: 0 | G75: 0 | H75: 0 | I75: 0 | J75: 0 | K75: -182550.63 | L75: 15422705
B76: Impaired Loan (Overseas Projec Fin) | E76: 3.6508911e+08 | F76: 0 | G76: 0 | H76: 4715.97 | I76: 0 | J76: 0 | K76: -4233349.3 | L76: 3.6086047e+08
A78: 500187 | C78: JEWEL GROWTH SDN BHD | D78: MYR | E78: 26832.06 | F78: 0 | G78: 0 | H78: 0 | I78: 0 | J78: 0 | K78: 0 | L78: 26832.06
A79: 500197 | C79: VEHENG GLOBAL TRADERS SDN BHD | D79: MYR | E79: 8200000 | F79: 0 | G79: 0 | H79: 0 | I79: 0 | J79: 0 | K79: 0 | L79: 8200000
B80: Impaired Loan (Supplier Credit) (Trade Finance) | E80: 8226832.1 | F80: 0 | G80: 0 | H80: 0 | I80: 0 | J80: 0 | K80: 0 | L80: 8226832.1
A82: 500962 | C82: Scomi Transit Projects Brazil | E82: 40515000 | F82: 0 | G82: 0 | H82: 0 | I82: 0 | J82: 0 | K82: 0 | L82: 40515000
B83: Impaired Loan (Term Loan) | E83: 40515000 | F83: 0 | G83: 0 | H83: 0 | I83: 0 | J83: 0 | K83: 0 | L83: 40515000
A85: 500039 | C85: PT MAHAKARYA INTI BUANA | D85: USD | E85: 11765530 | F85: 0 | G85: 0 | H85: 0 | I85: 0 | J85: 0 | K85: -137633.43 | L85: 11627897
A86: 500613 | C86: HARTAMANIS (S) PTE LTD (TL2) | D86: MYR | E86: 7458382.5 | F86: 0 | G86: 0 | H86: 0 | I86: 0 | J86: 0 | K86: 0 | L86: 7458382.5
B87: Restuctured | E87: 19223913 | F87: 0 | G87: 0 | H87: 0 | I87: 0 | J87: 0 | K87: -137633.43 | L87: 19086279
A89: 500512 | C89: AL-MANARA WATER COMPANY LIMITED | D89: EUR | E89: 1.0216522e+08 | F89: 0 | G89: 0 | H89: 1804186.8 | I89: 0 | J89: 0 | K89: 0 | L89: 1.0396941e+08
B90: Restuctured (Buyer Credit) | E90: 1.0216522e+08 | F90: 0 | G90: 0 | H90: 1804186.8 | I90: 0 | J90: 0 | K90: 0 | L90: 1.0396941e+08
A92: 500555 | C92: SOLARTIF SDN BHD | D92: MYR | E92: 687556.33 | F92: 0 | G92: 0 | H92: 0 | I92: -23691.92 | J92: 0 | K92: 0 | L92: 663864.41
B93: Restuctured (Supplier Credit) (Trade Finance) | E93: 687556.33 | F93: 0 | G93: 0 | H93: 0 | I93: -23691.92 | J93: 0 | K93: 0 | L93: 663864.41
A95: 500400 | C95: THE REPUBLIC OF IRAQ | D95: USD | E95: 2223754.9 | F95: 0 | G95: 0 | H95: 0 | I95: 0 | J95: 0 | K95: -26013.48 | L95: 2197741.4
A96: 500401 | C96: THE REPUBLIC OF SEYCHELLES | D96: USD | E96: 19155316 | F96: 0 | G96: 0 | H96: 0 | I96: 0 | J96: 0 | K96: -224079.28 | L96: 18931237
B97: Restuctured (Term Loan) | E97: 21379071 | F97: 0 | G97: 0 | H97: 0 | I97: 0 | J97: 0 | K97: -250092.76 | L97: 21128978
E99: =E97+E93+E90+E87+E83+E80+E76+E65+E60+E57+E47+E39+E36+E30+E15+E11+E8 -> 3.1076521e+09 | F99: =F97+F93+F90+F87+F83+F80+F76+F65+F60+F57+F47+F39+F36+F30+F15+F11+F8 -> 80418524 | G99: 0 | H99: =H97+H93+H90+H87+H83+H80+H76+H65+H60+H57+H47+H39+H36+H30+H15+H11+H8 -> 5228485.8 | I99: =I97+I93+I90+I87+I83+I80+I76+I65+I60+I57+I47+I39+I36+I30+I15+I11+I8 -> -29576442 | J99: 0 | K99: =K97+K93+K90+K87+K83+K80+K76+K65+K60+K57+K47+K39+K36+K30+K15+K11+K8 -> -32068784 | L99: =L97+L93+L90+L87+L83+L80+L76+L65+L60+L57+L47+L39+L36+L30+L15+L11+L8 -> 3.1316538e+09

Sheet Debtors Listing (C) June2021
A1: Customer Balances as at June 2021
A3: Customer Account Number | B3: Customer Class & Industry | C3: Customer Name | D3: Loan Currency | E3: Opening Principal | F3: Disbursement | G3: Adjustment Capitalization | H3: Forex ( + ) | I3: Repayment | J3: Adjustment Capitalization | K3: Forex ( - ) | L3: Closing Principal
A7: 500470 | C7: MINISTRY OF FINANCE - LAO PDR | D7: USD | E7: 73805875 | F7: 0 | G7: 0 | H7: 62765033 | I7: -6753987.5 | J7: 0 | K7: 0 | L7: 1.2981692e+08
A8: 500937 | C8: THE MINISTRY OF FINANCE LAOS 2 | D8: USD | E8: 2.745785e+08 | F8: 0 | G8: 0 | H8: 0 | I8: 0 | J8: 0 | K8: -2243226.9 | L8: 2.7233527e+08
B9: Active (Cross Border Credit) (Buyer Credit) | E9: 3.4838437e+08 | F9: 0 | G9: 0 | H9: 62765033 | I9: -6753987.5 | J9: 0 | K9: -2243226.9 | L9: 4.0215219e+08
A11: 500878 | C11: WOK DELIGHTS SDN BHD | D11: MYR | E11: 730307.7 | F11: 0 | G11: 0 | H11: 0 | I11: -66391.6 | J11: 0 | K11: 0 | L11: 663916.1
B12: Active (Malaysia Kitchen Fin) | E12: 730307.7 | F12: 0 | G12: 0 | H12: 0 | I12: -66391.6 | J12: 0 | K12: 0 | L12: 663916.1
A14: 500679 | C14: BUMI ARMADA CAPITAL OFFSHORE LTD | D14: USD | E14: 1.7818566e+08 | F14: 0 | G14: 0 | H14: 65217381 | I14: -7446778 | J14: 0 | K14: 0 | L14: 2.3595626e+08
A15: 500749 | C15: ISTANBUL SABIHA GOKCEN ULUSLARARASI | D15: EUR | E15: 193939900 | F15: 0 | G15: 0 | H15: 39064600 | I15: 0 | J15: 0 | K15: 0 | L15: 233004500
A16: 501045 | C16: Sapura TMC Sdn Bhd | D16: USD | E16: 76455128 | F16: 0 | G16: 0 | H16: 111099.72 | I16: 0 | J16: 0 | K16: 0 | L16: 76566228
B17: Active (Overseas Investment) | E17: =SUM(E14:E16) -> 4.4858069e+08 | F17: 0 | G17: 0 | H17: =SUM(H14:H16) -> 1.0439308e+08 | I17: =SUM(I14:I16) -> -7446778 | J17: 0 | K17: 0 | L17: =SUM(L14:L16) -> 5.4552699e+08
A19: 500271 | C19: MBI Development D.O.O, Bosnia&Herze | D19: EUR | E19: 271867.06 | F19: 0 | G19: 0 | H19: 14643.56 | I19: -173635.05 | J19: 0 | K19: 0 | L19: 112875.57
A20: 500590 | C20: MBI Development 2 | D20: EUR | E20: 6039227.3 | F20: 0 | G20: 0 | H20: 1182882.5 | I20: -2432582.9 | J20: 0 | K20: 0 | L20: 4789527
A21: 500640 | C21: OM MATERIAL (SARAWAK) SDN BHD | D21: USD | E21: 1.1702168e+08 | F21: 0 | G21: 0 | H21: 32533727 | I21: -2366640 | J21: 0 | K21: 0 | L21: 1.4718877e+08
A22: 500642 | C22: OM MATERIAL (SARAWAK) 2 | D22: USD | E22: 1.587604e+08 | F22: 0 | G22: 0 | H22: 43049660 | I22: -3114000 | J22: 0 | K22: 0 | L22: 1.9869606e+08
A23: 500805 | C23: Armada Kraken Pte Ltd (OPF) | D23: USD | E23: 1.1047102e+08 | F23: 0 | G23: 0 | H23: 0 | I23: -10242125 | J23: 0 | K23: -5385215.8 | L23: 94843681
A24: 500807 | C24: Pertama Ferroalloys Sdn Bhd (2) | D24: USD | E24: 50423085 | F24: 0 | G24: 0 | H24: 0 | I24: 0 | J24: 0 | K24: -3869451.1 | L24: 46553634
A25: 500808 | C25: Pertama Ferroalloys Sdn Bhd (1) | D25: USD | E25: 31092540 | F25: 0 | G25: 0 | H25: 0 | I25: 0 | J25: 0 | K25: -2840754.7 | L25: 28251785
A26: 500827 | C26: Pertama Ferroalloys Sdn Bhd (3) | D26: USD | E26: 68262757 | F26: 0 | G26: 0 | H26: 0 | I26: 0 | J26: 0 | K26: -3140197.2 | L26: 65122559
A27: 500885 | C27: SUPERBOOM PROJECTS SDN BHD | D27: USD | E27: 82315529 | F27: 0 | G27: 0 | H27: 0 | I27: 0 | J27: 0 | K27: -4441417.6 | L27: 77874111
A28: 500905 | C28: ZICO HOLDINGS INC (OPF) | D28: SGD | E28: 1520186.8 | F28: 0 | G28: 0 | H28: 3781.28 | I28: -167812.13 | J28: 0 | K28: 0 | L28: 1356156
A29: 500914 | C29: IMPIANA UBUD (LABUAN) CO. LTD. | D29: USD | E29: 90218650 | F29: 0 | G29: 0 | H29: 0 | I29: 0 | J29: 0 | K29: -563451.92 | L29: 89655198
A30: 500927 | C30: BRITISH UNIVERSITY VIETNAM | D30: USD | E30: 77701046 | F30: 0 | G30: 0 | H30: 1437604.5 | I30: 0 | J30: 0 | K30: 0 | L30: 79138651
A31: 501031 | C31: YINSON BORONIA PRODUCTION BV | D31: USD | E31: 3.6560943e+08 | F31: 69605875 | G31: 0 | H31: 4887028.6 | I31: 0 | J31: 0 | K31: 0 | L31: 4.4010233e+08
B32: Active (Overseas Projec Fin) | E32: 1.1597074e+09 | F32: 69605875 | G32: 0 | H32: 83109328 | I32: -18496795 | J32: 0 | K32: -20240488 | L32: 1.2736853e+09
A34: 500538 | C34: MIR VALVE SDN BHD | D34: USD | E34: 4653157.5 | F34: 3057851.8 | G34: 0 | H34: 1429071 | I34: -3346126.5 | J34: 0 | K34: 0 | L34: 5793953.8
A35: 500693 | C35: PERUSAHAAN OTOMOBIL NASIONAL (VF) | D35: MYR | E35: 8177146.2 | F35: 2174208.3 | G35: 0 | H35: 0 | I35: -4081220.5 | J35: 0 | K35: 0 | L35: 6270134
A36: 500724 | C36: OM Material (Sarawak) Sdn Bhd | D36: USD | E36: 65403284 | F36: 12538789 | G36: 0 | H36: 882956.89 | I36: -16425020 | J36: 0 | K36: 0 | L36: 62400011
A37: 500840 | C37: Pertama Ferroalloys (Trade) | D37: USD | E37: 21300557 | F37: 19945108 | G37: 0 | H37: 457326.13 | I37: -4407655.6 | J37: 0 | K37: 0 | L37: 37295336
B38: Active (Supplier Credit) (Trade Finance) | E38: =SUM(E34:E37) -> 99534145 | F38: =SUM(F34:F37) -> 37715957 | G38: 0 | H38: =SUM(H34:H37) -> 2769354 | I38: =SUM(I34:I37) -> -28260022 | J38: 0 | K38: 0 | L38: =SUM(L34:L37) -> 1.1175943e+08
A40: 501000 | C40: Brahim's Overseas Venture Sdn Bhd | D40: MYR | E40: 15467576 | F40: 0 | G40: 0 | H40: 0 | I40: 0 | J40: 0 | K40: 0 | L40: 15467576
B41: Active (Term Loan) | E41: 15467576 | F41: 0 | G41: 0 | H41: 0 | I41: 0 | J41: 0 | K41: 0 | L41: 15467576
A43: 500010 | C43: PT BUMI INTERNATIONAL TANKERS | D43: USD | E43: 11598115 | F43: 0 | G43: 0 | H43: 2160314 | I43: 0 | J43: 0 | K43: 0 | L43: 13758429
A44: 500011 | C44: PT LAYAR SENTOSA | D44: USD | E44: 11774500 | F44: 0 | G44: 0 | H44: 2118035.3 | I44: 0 | J44: 0 | K44: 0 | L44: 13892535
A45: 500042 | C45: PT EDEN CAPITAL INDONESIA | D45: USD | E45: 12542786 | F45: 0 | G45: 0 | H45: 2464432.2 | I45: 0 | J45: 0 | K45: 0 | L45: 15007219
A46: 500265 | C46: PT SARI INDAH LESTARI | D46: USD | E46: 73829041 | F46: 0 | G46: 0 | H46: 12927362 | I46: 0 | J46: 0 | K46: 0 | L46: 86756403
A47: 500274 | C47: HONDAAFUSHI INVESTMENT PVT LTD | D47: USD | E47: 36723247 | F47: 0 | G47: 0 | H47: 9346050.4 | I47: 0 | J47: 0 | K47: 0 | L47: 46069297
A48: 500913 | C48: PT SRIWIJAYA AIR | D48: USD | E48: 3.3404154e+08 | F48: 0 | G48: 0 | H48: 0 | I48: 0 | J48: 0 | K48: -4886817.2 | L48: 329154719
B49: Impaired Loan (Buyer Credit) | E49: 4.8050923e+08 | F49: 0 | G49: 0 | H49: 29016194 | I49: 0 | J49: 0 | K49: -4886817.2 | L49: 5.046386e+08
A51: 500546 | C51: FRESH BOWL FOODS LIMITED | D51: MYR | E51: 382874.32 | F51: 0 | G51: 0 | H51: 0 | I51: 0 | J51: 0 | K51: 0 | L51: 382874.32
A52: 500560 | C52: PANNAH RESOURCES 1 | D52: MYR | E52: 668800 | F52: 0 | G52: 0 | H52: 0 | I52: -4000 | J52: 0 | K52: 0 | L52: 664800
A53: 500577 | C53: NIRMALA VILAS RESTAURANT SDN BHD | D53: MYR | E53: 747562.14 | F53: 0 | G53: 0 | H53: 0 | I53: 0 | J53: 0 | K53: 0 | L53: 747562.14
A54: 500644 | C54: GOLD RAIN RESOURCES | D54: MYR | E54: 1067187.6 | F54: 0 | G54: 0 | H54: 0 | I54: 0 | J54: 0 | K54: 0 | L54: 1067187.6
A55: 500758 | C55: 3 PLUS1 STUDIO SDN BHD 2 | D55: MYR | E55: 975206.98 | F55: 0 | G55: 0 | H55: 0 | I55: 0 | J55: 0 | K55: 0 | L55: 975206.98
A56: 500806 | C56: I & C EATING NETWORK INTERNATIONAL | D56: MYR | E56: 988584.59 | F56: 0 | G56: 0 | H56: 0 | I56: 0 | J56: 0 | K56: 0 | L56: 988584.59
A57: 500852 | C57: NEE ASSETS SDN BHD | D57: MYR | E57: 539751.12 | F57: 0 | G57: 0 | H57: 0 | I57: 0 | J57: 0 | K57: 0 | L57: 539751.12
A58: 500866 | C58: NEE ASSETS SDN BHD 1 | D58: MYR | E58: 116666.69 | F58: 0 | G58: 0 | H58: 0 | I58: 0 | J58: 0 | K58: 0 | L58: 116666.69
B59: Impaired Loan (Malaysia Kitchen Fin) | E59: 5486633.4 | F59: 0 | G59: 0 | H59: 0 | I59: -4000 | J59: 0 | K59: 0 | L59: 5482633.4
A61: 500515 | C61: SCOMI TRANSIT PROJECTS BRAZIL | D61: USD | E61: 33829615 | F61: 0 | G61: 0 | H61: 6389526.4 | I61: 0 | J61: 0 | K61: 0 | L61: 40219142
B62: Impaired Loan (Overseas Contract Fi) | E62: 33829615 | F62: 0 | G62: 0 | H62: 6389526.4 | I62: 0 | J62: 0 | K62: 0 | L62: 40219142
A64: 500776 | C64: HUMMINGBIRD ENERGY (L) INC (OIF) | D64: USD | E64: 73097917 | F64: 0 | G64: 0 | H64: 23567450 | I64: 0 | J64: 0 | K64: 0 | L64: 96665367
A65: 500980 | C65: VEERAM STONES PVT LTD | D65: USD | E65: 2579592.8 | F65: 0 | G65: 0 | H65: 0 | I65: 0 | J65: 0 | K65: -3908.91 | L65: 2575683.8
B66: Impaired Loan (Overseas Investment) | E66: 75677509 | F66: 0 | G66: 0 | H66: 23567450 | I66: 0 | J66: 0 | K66: -3908.91 | L66: 99241051
A68: 500297 | C68: PHOENIX SURGE SDN BHD (111) | D68: USD | E68: 3896765 | F68: 0 | G68: 0 | H68: 849872.59 | I68: 0 | J68: 0 | K68: 0 | L68: 4746637.5
A69: 500522 | C69: VIRTUAL PEAKS GROUP SDN BHD | D69: USD | E69: 6724989 | F69: 0 | G69: 0 | H69: 7817686.2 | I69: 0 | J69: 0 | K69: 0 | L69: 14542675
A70: 500557 | C70: MARKMORE ENERGY 1 | D70: USD | E70: 1.4459124e+08 | F70: 0 | G70: 0 | H70: 34645037 | I70: 0 | J70: 0 | K70: 0 | L70: 1.7923628e+08
A71: 500558 | C71: MARKMORE ENERGY II | D71: USD | E71: 1.6478295e+08 | F71: 0 | G71: 0 | H71: 44132864 | I71: 0 | J71: 0 | K71: 0 | L71: 2.0891582e+08
A72: 500576 | C72: ILEAVES (UK) LTD | D72: GBP | E72: 3437187 | F72: 0 | G72: 0 | H72: 574866.41 | I72: 0 | J72: 0 | K72: 0 | L72: 4012053.4
A73: 500631 | C73: MALAYSIAN DELICACIES PTY LTD | D73: AUD | E73: 627891.69 | F73: 0 | G73: 0 | H73: 37646.48 | I73: 0 | J73: 0 | K73: 0 | L73: 665538.17
A74: 500781 | C74: HUMMINGBIRD ENERGY (L) INC (OPF) | D74: USD | E74: 15277300 | F74: 0 | G74: 0 | H74: 4427858.2 | I74: 0 | J74: 0 | K74: 0 | L74: 19705158
A75: 500883 | C75: UPL LAO CO. LTD 1 | D75: USD | E75: 8816517 | F75: 0 | G75: 0 | H75: 0 | I75: 0 | J75: 0 | K75: -776828.29 | L75: 8039688.7
A76: 500884 | C76: UPL LAO CO. LTD 2 | D76: USD | E76: 15541269 | F76: 0 | G76: 0 | H76: 0 | I76: 0 | J76: 0 | K76: -1543112.9 | L76: 13998156
B77: Impaired Loan (Overseas Projec Fin) | E77: 3.6369611e+08 | F77: 0 | G77: 0 | H77: 92485831 | I77: 0 | J77: 0 | K77: -2319941.2 | L77: 4.53862e+08
A79: 500187 | C79: JEWEL GROWTH SDN BHD | D79: MYR | E79: 26832.06 | F79: 0 | G79: 0 | H79: 0 | I79: 0 | J79: 0 | K79: 0 | L79: 26832.06
A80: 500197 | C80: VEHENG GLOBAL TRADERS SDN BHD | D80: MYR | E80: 8200000 | F80: 0 | G80: 0 | H80: 0 | I80: 0 | J80: 0 | K80: 0 | L80: 8200000
B81: Impaired Loan (Supplier Credit) (Trade Finance) | E81: 8226832.1 | F81: 0 | G81: 0 | H81: 0 | I81: 0 | J81: 0 | K81: 0 | L81: 8226832.1
A83: 500962 | C83: Scomi Transit Projects Brazil | E83: 40515000 | F83: 0 | G83: 0 | H83: 0 | I83: 0 | J83: 0 | K83: 0 | L83: 40515000
B84: Impaired Loan (Term Loan) | E84: 40515000 | F84: 0 | G84: 0 | H84: 0 | I84: 0 | J84: 0 | K84: 0 | L84: 40515000
A86: 500039 | C86: PT MAHAKARYA INTI BUANA | D86: USD | E86: 11717287 | F86: 0 | G86: 0 | H86: 23128743 | I86: 0 | J86: 0 | K86: 0 | L86: 34846031
A87: 500613 | C87: HARTAMANIS (S) PTE LTD (TL2) | D87: MYR | E87: 7458382.5 | F87: 0 | G87: 0 | H87: 0 | I87: 0 | J87: 0 | K87: 0 | L87: 7458382.5
B88: Restuctured | E88: 19175670 | F88: 0 | G88: 0 | H88: 23128743 | I88: 0 | J88: 0 | K88: 0 | L88: 42304413
A90: 500512 | C90: AL-MANARA WATER COMPANY LIMITED | D90: EUR | E90: 1.0567919e+08 | F90: 0 | G90: 0 | H90: 15111754 | I90: -1447192.6 | J90: 0 | K90: 0 | L90: 1.1934375e+08
B91: Restuctured (Buyer Credit) | E91: 1.0567919e+08 | F91: 0 | G91: 0 | H91: 15111754 | I91: -1447192.6 | J91: 0 | K91: 0 | L91: 1.1934375e+08
A93: 500555 | C93: SOLARTIF SDN BHD | D93: MYR | E93: 663864.41 | F93: 0 | G93: 0 | H93: 0 | I93: -57.76 | J93: 0 | K93: 0 | L93: 663806.65
B94: Restuctured (Supplier Credit) (Trade Finance) | E94: 663864.41 | F94: 0 | G94: 0 | H94: 0 | I94: -57.76 | J94: 0 | K94: 0 | L94: 663806.65
A96: 500400 | C96: THE REPUBLIC OF IRAQ | D96: USD | E96: 2214636.6 | F96: 0 | G96: 0 | H96: 692091.21 | I96: 0 | J96: 0 | K96: 0 | L96: 2906727.8
A97: 500401 | C97: THE REPUBLIC OF SEYCHELLES | D97: USD | E97: 19076773 | F97: 0 | G97: 0 | H97: 4794509.5 | I97: 0 | J97: 0 | K97: 0 | L97: 23871283
B98: Restuctured (Term Loan) | E98: 21291410 | F98: 0 | G98: 0 | H98: 5486600.7 | I98: 0 | J98: 0 | K98: 0 | L98: 26778010
E100: =E98+E94+E91+E88+E84+E81+E77+E66+E62+E59+E49+E41+E38+E32+E17+E12+E9 -> 3.2271556e+09 | F100: =F98+F94+F91+F88+F84+F81+F77+F66+F62+F59+F49+F41+F38+F32+F17+F12+F9 -> 1.0732183e+08 | G100: 0 | H100: =H98+H94+H91+H88+H84+H81+H77+H66+H62+H59+H49+H41+H38+H32+H17+H12+H9 -> 4.4822289e+08 | I100: =I98+I94+I91+I88+I84+I81+I77+I66+I62+I59+I49+I41+I38+I32+I17+I12+I9 -> -62475224 | J100: 0 | K100: =K98+K94+K91+K88+K84+K81+K77+K66+K62+K59+K49+K41+K38+K32+K17+K12+K9 -> -29694383 | L100: =L98+L94+L91+L88+L84+L81+L77+L66+L62+L59+L49+L41+L38+L32+L17+L12+L9 -> 3.6905307e+09

Sheet Sheet9
A1: Customer Balances as at March 2023
A3: Customer Account Number | B3: Customer Class & Industry | C3: Customer Name | D3: Loan Currency | E3: Opening Principal | F3: Disbursement | G3: Adjustment Capitalization | H3: Forex ( + ) | I3: Repayment | J3: Adjustment Capitalization | K3: Forex ( - ) | L3: Closing Principal
A5: 500470 | C5: MINISTRY OF FINANCE - LAO PDR | D5: USD | E5: 29175250 | F5: 0 | G5: 0 | H5: 0 | I5: -7192250 | J5: 0 | K5: -450125.01 | L5: =SUM(E5:K5) -> 21532875
A6: 500937 | C6: THE MINISTRY OF FINANCE LAOS 2 | D6: USD | E6: 2.4350112e+08 | F6: 0 | G6: 0 | H6: 0 | I6: 0 | J6: 0 | K6: -3878875 | L6: =SUM(E6:K6) -> 2.3962225e+08
B7: Active (Cross Border Credit) (Buyer Credit) | E7: 2.7267637e+08 | F7: 0 | G7: 0 | H7: 0 | I7: -7192250 | J7: 0 | K7: -4329000 | L7: 2.6115512e+08
A9: 500679 | C9: BUMI ARMADA CAPITAL OFFSHORE LTD | D9: USD | E9: 84254246 | F9: 0 | G9: 0 | H9: 0 | I9: -526202.46 | J9: 0 | K9: -1341838.6 | L9: =SUM(E9:K9) -> 82386204
A10: 500749 | C10: ISTANBUL SABIHA GOKCEN ULUSLARARASI | D10: EUR | E10: 157251600 | F10: 0 | G10: 0 | H10: 1481700 | I10: 0 | J10: 0 | K10: 0 | L10: =SUM(E10:K10) -> 158733300
A11: 501045 | C11: Sapura TMC Sdn Bhd | D11: USD | E11: 83111853 | F11: 0 | G11: 0 | H11: 5020846.8 | I11: -122417.96 | J11: 0 | K11: 0 | L11: =SUM(E11:K11) -> 88010282
B12: Active (Overseas Investment) | E12: 3.246177e+08 | F12: 0 | G12: 0 | H12: 6502546.8 | I12: -648620.42 | J12: 0 | K12: -1341838.6 | L12: 3.2912979e+08
A14: 500640 | C14: OM MATERIAL (SARAWAK) SDN BHD | D14: USD | E14: 1.0589005e+08 | F14: 0 | G14: 0 | H14: 0 | I14: -4797031.4 | J14: 0 | K14: -1684289.2 | L14: =SUM(E14:K14) -> 99408724
A15: 500642 | C15: OM MATERIAL (SARAWAK) 2 | D15: USD | E15: 1.4453008e+08 | F15: 0 | G15: 0 | H15: 0 | I15: -6361911.3 | J15: 0 | K15: -2298995.1 | L15: =SUM(E15:K15) -> 1.3586918e+08
A16: 500805 | C16: Armada Kraken Pte Ltd (OPF) | D16: USD | E16: 31919537 | F16: 0 | G16: 0 | H16: 0 | I16: -31439517 | J16: 0 | K16: -445090.33 | L16: =SUM(E16:K16) -> 34929.39
A17: 500807 | C17: Pertama Ferroalloys Sdn Bhd (2) | D17: USD | E17: 53845608 | F17: 0 | G17: 0 | H17: 0 | I17: -52987869 | J17: 0 | K17: -218630.04 | L17: =SUM(E17:K17) -> 639108.86
A18: 500808 | C18: Pertama Ferroalloys Sdn Bhd (1) | D18: USD | E18: 27774838 | F18: 0 | G18: 0 | H18: 439029.28 | I18: -27332396 | J18: 0 | K18: 0 | L18: =SUM(E18:K18) -> 881471.28
A19: 500827 | C19: Pertama Ferroalloys Sdn Bhd (3) | D19: USD | E19: 72896167 | F19: 0 | G19: 0 | H19: 0 | I19: -71734960 | J19: 0 | K19: -2394245.6 | L19: =SUM(E19:K19) -> -1233039.1
A20: 501051 | C20: Yinson Boronia Production 2 (OPF) | D20: USD | E20: 538620000 | F20: 0 | G20: 0 | H20: 0 | I20: 0 | J20: 0 | K20: -8580000 | L20: =SUM(E20:K20) -> 5.3004e+08
A21: 501072 | C21: Seri Erlang (Singapore) Pte Ltd | D21: USD | E21: 30302909 | F21: 0 | G21: 0 | H21: 0 | I21: 0 | J21: 0 | K21: -482713.16 | L21: =SUM(E21:K21) -> 29820196
A22: 501073 | C22: Seri Everest (Singapore) Pte Ltd | D22: USD | E22: 30302909 | F22: 0 | G22: 0 | H22: 0 | I22: 0 | J22: 0 | K22: -482713.16 | L22: =SUM(E22:K22) -> 29820196
B23: Active (Overseas Projec Fin) | E23: =SUM(E14:E22) -> 1.0360821e+09 | F23: =SUM(F14:F22) -> 0 | G23: =SUM(G14:G22) -> 0 | H23: =SUM(H14:H22) -> 439029.28 | I23: =SUM(I14:I22) -> -1.9465368e+08 | J23: =SUM(J14:J22) -> 0 | K23: =SUM(K14:K22) -> -16586677 | L23: =SUM(L14:L22) -> 8.2528077e+08
A25: 500693 | C25: PERUSAHAAN OTOMOBIL NASIONAL (VF) | D25: MYR | E25: 792854.01 | F25: 358907.32 | G25: 0 | H25: 0 | I25: -483637.55 | J25: 0 | K25: 0 | L25: =SUM(E25:K25) -> 668123.78
A26: 500724 | C26: OM Material (Sarawak) Sdn Bhd | D26: USD | E26: 40652490 | F26: 19682216 | G26: 0 | H26: 0 | I26: -1754532.3 | J26: 0 | K26: -642314.75 | L26: =SUM(E26:K26) -> 57937859
A27: 500840 | C27: Pertama Ferroalloys (Trade) | D27: USD | E27: 42972497 | F27: 0 | G27: 0 | H27: 128726 | I27: -43101223 | J27: 0 | K27: 0 | L27: =SUM(E27:K27) -> 7.4505806e-09
B28: Active (Supplier Credit) (Trade Finance) | E28: =SUM(E25:E27) -> 84417841 | F28: =SUM(F25:F27) -> 20041124 | G28: =SUM(G25:G27) -> 0 | H28: =SUM(H25:H27) -> 128726 | I28: =SUM(I25:I27) -> -45339393 | J28: =SUM(J25:J27) -> 0 | K28: =SUM(K25:K27) -> -642314.75 | L28: =SUM(L25:L27) -> 58605983
A30: 501000 | C30: Brahim's Overseas Venture Sdn Bhd | D30: MYR | E30: 15467576 | F30: 0 | G30: 0 | H30: 0 | I30: 0 | J30: 0 | K30: 0 | L30: =SUM(E30:K30) -> 15467576
B31: Active (Term Loan) | E31: 15467576 | F31: 0 | G31: 0 | H31: 0 | I31: 0 | J31: 0 | K31: 0 | L31: 15467576
A33: 500010 | C33: PT BUMI INTERNATIONAL TANKERS | D33: USD | E33: 12607929 | F33: 0 | G33: 0 | H33: 0 | I33: 0 | J33: 0 | K33: -200839.23 | L33: =SUM(E33:K33) -> 12407090
A34: 500011 | C34: PT LAYAR SENTOSA | D34: USD | E34: 12799671 | F34: 0 | G34: 0 | H34: 0 | I34: 0 | J34: 0 | K34: -203893.61 | L34: =SUM(E34:K34) -> 12595778
A35: 500042 | C35: PT EDEN CAPITAL INDONESIA | D35: USD | E35: 13634850 | F35: 0 | G35: 0 | H35: 0 | I35: 0 | J35: 0 | K35: -217197.67 | L35: =SUM(E35:K35) -> 13417653
A36: 500265 | C36: PT SARI INDAH LESTARI | D36: USD | E36: 80257120 | F36: 0 | G36: 0 | H36: 0 | I36: 0 | J36: 0 | K36: -1278463.7 | L36: =SUM(E36:K36) -> 78978657
A37: 500274 | C37: HONDAAFUSHI INVESTMENT PVT LTD | D37: USD | E37: 39920633 | F37: 0 | G37: 0 | H37: 0 | I37: 0 | J37: 0 | K37: -635919.63 | L37: =SUM(E37:K37) -> 39284713
A38: 500913 | C38: PT SRIWIJAYA AIR | D38: USD | E38: 3.6312556e+08 | F38: 0 | G38: 0 | H38: 0 | I38: 0 | J38: 0 | K38: -5784444.1 | L38: =SUM(E38:K38) -> 3.5734112e+08
A39: 500400 | C39: THE REPUBLIC OF IRAQ | D39: USD | E39: 1891539.4 | F39: 0 | G39: 0 | H39: 0 | I39: -171345.15 | J39: 0 | K39: -28005.1 | L39: =SUM(E39:K39) -> 1692189.1
B40: Impaired Loan (Buyer Credit) | E40: =SUM(E33:E39) -> 5.242373e+08 | F40: =SUM(F33:F39) -> 0 | G40: =SUM(G33:G39) -> 0 | H40: =SUM(H33:H39) -> 0 | I40: =SUM(I33:I39) -> -171345.15 | J40: =SUM(J33:J39) -> 0 | K40: =SUM(K33:K39) -> -8348763.1 | L40: =SUM(L33:L39) -> 5.1571719e+08
A42: 500546 | C42: FRESH BOWL FOODS LIMITED | D42: MYR | E42: 382874.32 | F42: 0 | G42: 0 | H42: 0 | I42: 0 | J42: 0 | K42: 0 | L42: =SUM(E42:K42) -> 382874.32
A43: 500577 | C43: NIRMALA VILAS RESTAURANT SDN BHD | D43: MYR | E43: 747562.14 | F43: 0 | G43: 0 | H43: 0 | I43: 0 | J43: 0 | K43: 0 | L43: =SUM(E43:K43) -> 747562.14
A44: 500644 | C44: GOLD RAIN RESOURCES | D44: MYR | E44: 1067187.6 | F44: 0 | G44: 0 | H44: 0 | I44: 0 | J44: 0 | K44: 0 | L44: =SUM(E44:K44) -> 1067187.6
A45: 500758 | C45: 3 PLUS1 STUDIO SDN BHD 2 | D45: MYR | E45: 975206.98 | F45: 0 | G45: 0 | H45: 0 | I45: 0 | J45: 0 | K45: 0 | L45: =SUM(E45:K45) -> 975206.98
A46: 500852 | C46: NEE ASSETS SDN BHD | D46: MYR | E46: 539751.12 | F46: 0 | G46: 0 | H46: 0 | I46: 0 | J46: 0 | K46: 0 | L46: =SUM(E46:K46) -> 539751.12
A47: 500866 | C47: NEE ASSETS SDN BHD 1 | D47: MYR | E47: 116666.69 | F47: 0 | G47: 0 | H47: 0 | I47: 0 | J47: 0 | K47: 0 | L47: =SUM(E47:K47) -> 116666.69
B48: Impaired Loan (Malaysia Kitchen Fin) | E48: 3829248.8 | F48: 0 | G48: 0 | H48: 0 | I48: 0 | J48: 0 | K48: 0 | L48: 3829248.8
A50: 500776 | C50: HUMMINGBIRD ENERGY (L) INC (OIF) | D50: USD | E50: 79462339 | F50: 0 | G50: 0 | H50: 0 | I50: 0 | J50: 0 | K50: -1265803.1 | L50: =SUM(E50:K50) -> 78196536
A51: 500980 | C51: VEERAM STONES PVT LTD | D51: USD | E51: 2689733.6 | F51: 0 | G51: 0 | H51: 0 | I51: 0 | J51: 0 | K51: -42846.33 | L51: =SUM(E51:K51) -> 2646887.2
B52: Impaired Loan (Overseas Investment) | E52: 82152073 | F52: 0 | G52: 0 | H52: 0 | I52: 0 | J52: 0 | K52: -1308649.4 | L52: 80843423
A54: 500522 | C54: VIRTUAL PEAKS GROUP SDN BHD | D54: USD | E54: 7310514.2 | F54: 0 | G54: 0 | H54: 0 | I54: 0 | J54: 0 | K54: -116453.55 | L54: =SUM(E54:K54) -> 7194060.7
A55: 500557 | C55: MARKMORE ENERGY 1 | D55: USD | E55: 1.5718038e+08 | F55: 0 | G55: 0 | H55: 0 | I55: 0 | J55: 0 | K55: -2503820.2 | L55: =SUM(E55:K55) -> 1.5467656e+08
A56: 500558 | C56: MARKMORE ENERGY II | D56: USD | E56: 1.7913013e+08 | F56: 0 | G56: 0 | H56: 0 | I56: 0 | J56: 0 | K56: -2853470.9 | L56: =SUM(E56:K56) -> 1.7627666e+08
A57: 500576 | C57: ILEAVES (UK) LTD | D57: GBP | E57: 3186294.4 | F57: 0 | G57: 0 | H57: 22146.22 | I57: 0 | J57: 0 | K57: 0 | L57: =SUM(E57:K57) -> 3208440.6
A58: 500914 | C58: IMPIANA UBUD (LABUAN) CO. LTD. | D58: USD | E58: 98073725 | F58: 0 | G58: 0 | H58: 0 | I58: 0 | J58: 0 | K58: -1562275 | L58: =SUM(E58:K58) -> 96511450
A59: 500631 | C59: MALAYSIAN DELICACIES PTY LTD | D59: AUD | E59: 592875.64 | F59: 0 | G59: 0 | H59: 0 | I59: 0 | J59: 0 | K59: -12497.32 | L59: =SUM(E59:K59) -> 580378.32
A60: 500781 | C60: HUMMINGBIRD ENERGY (L) INC (OPF) | D60: USD | E60: 16607450 | F60: 0 | G60: 0 | H60: 0 | I60: 0 | J60: 0 | K60: -264550 | L60: =SUM(E60:K60) -> 16342900
A61: 500883 | C61: UPL LAO CO. LTD 1 | D61: USD | E61: 9584145.5 | F61: 0 | G61: 0 | H61: 0 | I61: 0 | J61: 0 | K61: -152671.58 | L61: =SUM(E61:K61) -> 9431473.9
A62: 500884 | C62: UPL LAO CO. LTD 2 | D62: USD | E62: 16894402 | F62: 0 | G62: 0 | H62: 0 | I62: 0 | J62: 0 | K62: -269121.05 | L62: =SUM(E62:K62) -> 16625281
A63: 500885 | C63: SUPERBOOM PROJECTS SDN BHD | D63: USD | E63: 89482502 | F63: 0 | G63: 0 | H63: 0 | I63: 0 | J63: 0 | K63: -1425420.3 | L63: =SUM(E63:K63) -> 88057082
B64: Impaired Loan (Overseas Projec Fin) | E64: =SUM(E54:E63) -> 5.7804241e+08 | F64: =SUM(F54:F63) -> 0 | G64: =SUM(G54:G63) -> 0 | H64: =SUM(H54:H63) -> 22146.22 | I64: =SUM(I54:I63) -> 0 | J64: =SUM(J54:J63) -> 0 | K64: =SUM(K54:K63) -> -9160279.9 | L64: =SUM(L54:L63) -> 5.6890428e+08
A66: 500538 | B66: Active (Supplier Credit) (Trade Finance) | C66: MIR VALVE SDN BHD | D66: USD | E66: 14619493 | F66: 0 | G66: 0 | H66: 0 | I66: 0 | J66: 0 | K66: -232882.64 | L66: =SUM(E66:K66) -> 14386610
B67: Impaired (Supplier Credit) (Trade Finance) | E67: =SUM(E66) -> 14619493 | F67: =SUM(F66) -> 0 | G67: =SUM(G66) -> 0 | H67: =SUM(H66) -> 0 | I67: =SUM(I66) -> 0 | J67: =SUM(J66) -> 0 | K67: =SUM(K66) -> -232882.64 | L67: =SUM(L66) -> 14386610
A69: 500039 | C69: PT MAHAKARYA INTI BUANA | D69: USD | E69: 11683565 | F69: 0 | G69: 0 | H69: 0 | I69: 0 | J69: 0 | K69: -186114.49 | L69: =SUM(E69:K69) -> 11497451
A70: 500613 | C70: HARTAMANIS (S) PTE LTD (TL2) | D70: MYR | E70: 7458382.5 | F70: 0 | G70: 0 | H70: 0 | I70: 0 | J70: 0 | K70: 0 | L70: =SUM(E70:K70) -> 7458382.5
B71: Restuctured | E71: 19141948 | F71: 0 | G71: 0 | H71: 0 | I71: 0 | J71: 0 | K71: -186114.49 | L71: 18955833
A73: 500512 | C73: AL-MANARA WATER COMPANY LIMITED | D73: EUR | E73: 99968730 | F73: 0 | G73: 0 | H73: 941953.33 | I73: 0 | J73: 0 | K73: 0 | L73: =SUM(E73:K73) -> 1.0091068e+08
B74: Restuctured (Buyer Credit) | E74: 99968730 | F74: 0 | G74: 0 | H74: 941953.33 | I74: 0 | J74: 0 | K74: 0 | L74: 1.0091068e+08
A76: 500555 | C76: SOLARTIF SDN BHD | D76: MYR | E76: 645015.03 | F76: 0 | G76: 0 | H76: 0 | I76: 0 | J76: 0 | K76: 0 | L76: =SUM(E76:K76) -> 645015.03
B77: Restuctured (Supplier Credit) (Trade Finance) | E77: =SUM(E76) -> 645015.03 | F77: =SUM(F76) -> 0 | G77: =SUM(G76) -> 0 | H77: =SUM(H76) -> 0 | I77: =SUM(I76) -> 0 | J77: =SUM(J76) -> 0 | K77: =SUM(K76) -> 0 | L77: =SUM(L76) -> 645015.03
A79: 500401 | C79: THE REPUBLIC OF SEYCHELLES | D79: USD | E79: 16201727 | F79: 0 | G79: 0 | H79: 0 | I79: 0 | J79: 0 | K79: -258087.03 | L79: =SUM(E79:K79) -> 15943640
B80: Restuctured (Term Loan) | E80: =SUM(E79) -> 16201727 | F80: =SUM(F79) -> 0 | G80: =SUM(G79) -> 0 | H80: =SUM(H79) -> 0 | I80: =SUM(I79) -> 0 | J80: =SUM(J79) -> 0 | K80: =SUM(K79) -> -258087.03 | L80: =SUM(L79) -> 15943640
E82: =E80+E77+E74+E71+E67+E64+E52+E48+E40+E31+E28+E23+E12+E7 -> 3.0720995e+09 | F82: =F80+F77+F74+F71+F67+F64+F52+F48+F40+F31+F28+F23+F12+F7 -> 20041124 | G82: =G80+G77+G74+G71+G67+G64+G52+G48+G40+G31+G28+G23+G12+G7 -> 0 | H82: =H80+H77+H74+H71+H67+H64+H52+H48+H40+H31+H28+H23+H12+H7 -> 8034401.7 | I82: =I80+I77+I74+I71+I67+I64+I52+I48+I40+I31+I28+I23+I12+I7 -> -2.4800529e+08 | J82: =J80+J77+J74+J71+J67+J64+J52+J48+J40+J31+J28+J23+J12+J7 -> 0 | K82: =K80+K77+K74+K71+K67+K64+K52+K48+K40+K31+K28+K23+K12+K7 -> -42394607 | L82: =L80+L77+L74+L71+L67+L64+L52+L48+L40+L31+L28+L23+L12+L7 -> 2.8097752e+09
L84: 2.8070786e+09
L87: 2.8074068e+09
L88: =L82-L87 -> 2368400.4

Sheet Principal Feb 2024
A1: EXIM Bank of Malaysia Customer Balances in Local Currency Time 09:09:56 Date 03.03.2024
A2: Kuala Lumpur RFDSLD00/EIDIL Page 1
A3: Carryforwd Perio 01 - 01 2024 Reporting Period 02 - 02 2024
D5: CoCd | F5: Reconciliation acct | I5: Customer | J5: SearchTerm | K5: SGL Ind. | L5: Crcy | N5: Balance Carryforward | P5: Debit rept.period | Q5: Credit report per. | R5: Accumulated balance
D7: EXIM | F7: 138901 | I7: 500010 | J7: PT BUMI | L7: MYR | N7: 9502406.7 | P7: 0 | Q7: 0 | R7: 9502406.7
D8: EXIM | F8: 138901 | I8: 500010 | J8: PT BUMI | K8: N | L8: MYR | N8: 3782477.1 | P8: 21490490 | Q8: 21425884 | R8: 3847082.8
D9: EXIM | F9: 138901 | I9: 500011 | J9: PTLAYAR | L9: MYR | N9: 9722052.6 | P9: 0 | Q9: 0 | R9: 9722052.6
D10: EXIM | F10: 138901 | I10: 500011 | J10: PTLAYAR | K10: N | L10: MYR | N10: 3764868.4 | P10: 21612417 | Q10: 21546829 | R10: 3830456.5
D11: EXIM | F11: 138901 | I11: 500039 | J11: PTMAHAKARY | L11: MYR | N11: -12317330 | P11: 0 | Q11: 0 | R11: -12317330
D12: EXIM | F12: 138901 | I12: 500039 | J12: PTMAHAKARY | K12: N | L12: MYR | N12: 24628219 | P12: 50504626 | Q12: 50444756 | R12: 24688088
D13: EXIM | F13: 138901 | I13: 500042 | J13: PTEDEN | L13: MYR | N13: 10140948 | P13: 0 | Q13: 0 | R13: 10140948
D14: EXIM | F14: 138901 | I14: 500042 | J14: PTEDEN | K14: N | L14: MYR | N14: 4225995.7 | P14: 5445968.6 | Q14: 5376100.8 | R14: 4295863.4
D15: EXIM | F15: 138901 | I15: 500222 | J15: NEPLINE | L15: MYR | N15: 46393.79 | P15: 0 | Q15: 46393.79 | R15: 0
D16: EXIM | F16: 138901 | I16: 500222 | J16: NEPLINE | K16: N | L16: MYR | N16: 2918234.5 | P16: 855680.91 | Q16: 3773915.4 | R16: 0
D17: EXIM | F17: 138901 | I17: 500265 | J17: PTSARI | L17: MYR | N17: 61312933 | P17: 0 | Q17: 0 | R17: 61312933
D18: EXIM | F18: 138901 | I18: 500265 | J18: PTSARI | K18: N | L18: MYR | N18: 23253414 | P18: 42881987 | Q18: 42470733 | R18: 23664668
D19: EXIM | F19: 138901 | I19: 500271 | J19: MBI | K19: N | L19: MYR | N19: -0.01 | P19: 0.01 | Q19: 0 | R19: 0
D20: EXIM | F20: 138901 | I20: 500274 | J20: HONDAAFUSH | L20: MYR | N20: 27577487 | P20: 0 | Q20: 0 | R20: 27577487
D21: EXIM | F21: 138901 | I21: 500274 | J21: HONDAAFUSH | K21: N | L21: MYR | N21: 14486596 | P21: 16166311 | Q21: 15961750 | R21: 14691157
D22: EXIM | F22: 138901 | I22: 500400 | J22: IRAQ | L22: MYR | N22: 692960.12 | P22: 183010.79 | Q22: 183010.79 | R22: 692960.12
D23: EXIM | F23: 138901 | I23: 500400 | J23: IRAQ | K23: N | L23: MYR | N23: 937759.31 | P23: 2583310.1 | Q23: 2575379.8 | R23: 945689.63
D24: EXIM | F24: 138901 | I24: 500401 | J24: SEYCHELLES | L24: MYR | N24: 7113425.4 | P24: 0 | Q24: 0 | R24: 7113425.4
D25: EXIM | F25: 138901 | I25: 500401 | J25: SEYCHELLES | K25: N | L25: MYR | N25: 7020584.7 | P25: 10867681 | Q25: 10798946 | R25: 7089319.7
D26: EXIM | F26: 138901 | I26: 500512 | J26: AL-MANARA | L26: MYR | N26: 88432683 | P26: 0 | Q26: 0 | R26: 88432683
D27: EXIM | F27: 138901 | I27: 500512 | J27: AL-MANARA | K27: N | L27: MYR | N27: 18922723 | P27: 24238182 | Q27: 23535388 | R27: 19625517
D28: EXIM | F28: 138901 | I28: 500522 | J28: VIRTUAL | L28: MYR | N28: -1055236.6 | P28: 0 | Q28: 0 | R28: -1055236.6
D29: EXIM | F29: 138901 | I29: 500522 | J29: VIRTUAL | K29: N | L29: MYR | N29: 8758272.6 | P29: 10981735 | Q29: 10944275 | R29: 8795733.1
D30: EXIM | F30: 138901 | I30: 500538 | J30: MIR | L30: MYR | N30: 10182074 | P30: 0 | Q30: 0 | R30: 10182074
D31: EXIM | F31: 138901 | I31: 500538 | J31: MIR | K31: N | L31: MYR | N31: 3090190.9 | P31: 62535511 | Q31: 62471001 | R31: 3154701.7
D32: EXIM | F32: 138901 | I32: 500555 | J32: SOLARTIF | L32: MYR | N32: 598006.7 | P32: 0 | Q32: 8962.9 | R32: 589043.8
D33: EXIM | F33: 138901 | I33: 500557 | J33: MARKMORE | L33: MYR | N33: 1.1075163e+08 | P33: 0 | Q33: 0 | R33: 1.1075163e+08
D34: EXIM | F34: 138901 | I34: 500557 | J34: MARKMORE | K34: N | L34: MYR | N34: 54868200 | P34: 61335739 | Q34: 60530314 | R34: 55673625
D35: EXIM | F35: 138901 | I35: 500558 | J35: MARKMORE | L35: MYR | N35: 1.2156799e+08 | P35: 0 | Q35: 0 | R35: 1.2156799e+08
D36: EXIM | F36: 138901 | I36: 500558 | J36: MARKMORE | K36: N | L36: MYR | N36: 67180129 | P36: 76798122 | Q36: 75880222 | R36: 68098029
D37: EXIM | F37: 138901 | I37: 500577 | J37: NIRMALA | L37: MYR | N37: 747562.14 | P37: 0 | Q37: 0 | R37: 747562.14
D38: EXIM | F38: 138901 | I38: 500640 | J38: OM MATERIA | L38: MYR | N38: 44599177 | P38: 0 | Q38: 0 | R38: 44599177
D39: EXIM | F39: 138901 | I39: 500640 | J39: OM MATERIA | K39: N | L39: MYR | N39: 46441418 | P39: 67640974 | Q39: 67198235 | R39: 46884157
D40: EXIM | F40: 138901 | I40: 500642 | J40: OM MATERIA | L40: MYR | N40: 63038016 | P40: 0 | Q40: 0 | R40: 63038016
D41: EXIM | F41: 138901 | I41: 500642 | J41: OM MATERIA | K41: N | L41: MYR | N41: 62018420 | P41: 82595299 | Q41: 81987138 | R41: 62626581
D42: EXIM | F42: 138901 | I42: 500693 | J42: PROTON (VF | L42: MYR | N42: 809495.86 | P42: 460089.09 | Q42: 435706.34 | R42: 833878.61
D43: EXIM | F43: 138901 | I43: 500724 | J43: OM MATERIA | L43: MYR | N43: 71597407 | P43: 25811956 | Q43: 36796618 | R43: 60612745
D44: EXIM | F44: 138901 | I44: 500724 | J44: OM MATERIA | K44: N | L44: MYR | N44: 8239404.1 | P44: 3.9344349e+08 | Q44: 3.929955e+08 | R44: 8687389.8
D45: EXIM | F45: 138901 | I45: 500749 | J45: ISTANBUL S | L45: MYR | N45: 99616600 | P45: 0 | Q45: 0 | R45: 99616600
D46: EXIM | F46: 138901 | I46: 500749 | J46: ISTANBUL S | K46: N | L46: MYR | N46: 43667800 | P46: 212546200 | Q46: 211608200 | R46: 44605800
D47: EXIM | F47: 138901 | I47: 500758 | J47: 3 PLUS1 ST | L47: MYR | N47: 975206.98 | P47: 0 | Q47: 0 | R47: 975206.98
D48: EXIM | F48: 138901 | I48: 500776 | J48: HUMMINGBIR | L48: MYR | N48: 49937648 | P48: 0 | Q48: 0 | R48: 49937648
D49: EXIM | F49: 138901 | I49: 500776 | J49: HUMMINGBIR | K49: N | L49: MYR | N49: 33791245 | P49: 66398874 | Q49: 65991692 | R49: 34198426
D50: EXIM | F50: 138901 | I50: 500781 | J50: HUMMINGBIR | L50: MYR | N50: 10934542 | P50: 0 | Q50: 0 | R50: 10934542
D51: EXIM | F51: 138901 | I51: 500781 | J51: HUMMINGBIR | K51: N | L51: MYR | N51: 6564608.2 | P51: 23616689 | Q51: 23531589 | R51: 6649708.2
D52: EXIM | F52: 138901 | I52: 500839 | J52: RHODIUM IN | K52: N | L52: MYR | N52: -0.03 | P52: 67728293 | Q52: 67728293 | R52: 0
D53: EXIM | F53: 138901 | I53: 500840 | J53: PERTAMA (T | L53: MYR | N53: 20861902 | P53: 26090610 | Q53: 0 | R53: 46952512
D54: EXIM | F54: 138901 | I54: 500840 | J54: PERTAMA (T | K54: N | L54: MYR | N54: 430638.56 | P54: 7228918.9 | Q54: 7267331.3 | R54: 392226.17
D55: EXIM | F55: 138901 | I55: 500852 | J55: NEE ASSETS | L55: MYR | N55: 539751.12 | P55: 0 | Q55: 0 | R55: 539751.12
D56: EXIM | F56: 138901 | I56: 500866 | J56: NEE ASSETS | L56: MYR | N56: 116666.69 | P56: 0 | Q56: 0 | R56: 116666.69
D57: EXIM | F57: 138901 | I57: 500883 | J57: UPL LAO CO | L57: MYR | N57: 9642456.5 | P57: 0 | Q57: 0 | R57: 9642456.5
D58: EXIM | F58: 138901 | I58: 500883 | J58: UPL LAO CO | K58: N | L58: MYR | N58: 456288.33 | P58: 2436548.7 | Q58: 2387437.5 | R58: 505399.47
D59: EXIM | F59: 138901 | I59: 500884 | J59: UPL LAO CO | L59: MYR | N59: 17170952 | P59: 0 | Q59: 0 | R59: 17170952
D60: EXIM | F60: 138901 | I60: 500884 | J60: UPL LAO CO | K60: N | L60: MYR | N60: 630556.92 | P60: 2716935.5 | Q60: 2630365.1 | R60: 717127.3
D61: EXIM | F61: 138901 | I61: 500885 | J61: SUPERBOOM | L61: MYR | N61: 87215473 | P61: 0 | Q61: 0 | R61: 87215473
D62: EXIM | F62: 138901 | I62: 500885 | J62: SUPERBOOM | K62: N | L62: MYR | N62: 7071592.3 | P62: 7600704.5 | Q62: 7142177.7 | R62: 7530119.1
D63: EXIM | F63: 138901 | I63: 500913 | J63: PT SRIWIJA | L63: MYR | N63: 3.4078908e+08 | P63: 0 | Q63: 0 | R63: 3.4078908e+08
D64: EXIM | F64: 138901 | I64: 500913 | J64: PT SRIWIJA | K64: N | L64: MYR | N64: 41833693 | P64: 45787065 | Q64: 43926335 | R64: 43694423
D65: EXIM | F65: 138901 | I65: 500914 | J65: IMPIANA UB | L65: MYR | N65: 91284652 | P65: 0 | Q65: 0 | R65: 91284652
D66: EXIM | F66: 138901 | I66: 500914 | J66: IMPIANA UB | K66: N | L66: MYR | N66: 12054923 | P66: 12557473 | Q66: 12054923 | R66: 12557473
